Workbook
Name circ: #REF!
Name scen: #REF!

Sheet Cover >>>
C15: DIASORIN
C16: Valuation

Sheet Inputs >>>
C16: Financial Model
C17: Inputs

Sheet AFS
A1: Company Fundamentals - Income Statement
A2: Company Name | K2: DiaSorin SpA (DIAS.MI)
A3: Country of Exchange | K3: Italy
A4: Country of Headquarters | K4: Italy
A5: TRBC Industry Group | K5: Healthcare Equipment & Supplies
A6: CF Template | K6: IND
A7: Consolidation Basis | K7: Consolidated
A8: Scaling | K8: Millions
A9: Period | K9: Annual
A10: Export Date | K10: 46050.798
A11: Statement Data | B11: 2015 | C11: 2016 | D11: 2017 | E11: 2018 | F11: 2019 | G11: 2020 | H11: 2021 | I11: 2022 | J11: 2023 | K11: 2024
A12: Period End Date | B12: 42369 | C12: 42735 | D12: 43100 | E12: 43465 | F12: 43830 | G12: 44196 | H12: 44561 | I12: 44926 | J12: 45291 | K12: 45657
A13: Statement Date | B13: 42369 | C13: 42735 | D13: 43100 | E13: 43465 | F13: 43830 | G13: 44196 | H13: 44561 | I13: 44926 | J13: 45291 | K13: 45657
A14: Standardized Currency | B14: EUR | C14: EUR | D14: EUR | E14: EUR | F14: EUR | G14: EUR | H14: EUR | I14: EUR | J14: EUR | K14: EUR
A15: Template Type | B15: Industrial - Gross Profit | C15: Industrial - Gross Profit | D15: Industrial - Gross Profit | E15: Industrial - Gross Profit | F15: Industrial - Gross Profit | G15: Industrial - Gross Profit | H15: Industrial - Gross Profit | I15: Industrial - Gross Profit | J15: Industrial - Gross Profit | K15: Industrial - Gross Profit
A17: Income Statement - Standardized (Currency: Euro)
A18: Field Name | B18: 31-12-2015 | C18: 31-12-2016 | D18: 31-12-2017 | E18: 31-12-2018 | F18: 31-12-2019 | G18: 31-12-2020 | H18: 31-12-2021 | I18: 31-12-2022 | J18: 31-12-2023 | K18: 31-12-2024
A19: Revenues
A20: Revenue from Goods & Services | B20: 499.18 | C20: 569.31 | D20: 637.49 | E20: 669.2 | F20: 706.32 | G20: 881.31 | H20: 1237.65 | I20: 1361.14 | J20: 1148.21 | K20: 1185.43
A21: Sales of Goods & Services - Net - Unclassified | B21: 499.18 | C21: 569.31 | D21: 637.49 | E21: 669.2 | F21: 706.32 | G21: 881.31 | H21: 1237.65 | I21: 1361.14 | J21: 1148.21 | K21: 1185.43
A22: Revenue from Business Activities - Total | B22: 499.18 | C22: 569.31 | D22: 637.49 | E22: 669.2 | F22: 706.32 | G22: 881.31 | H22: 1237.65 | I22: 1361.14 | J22: 1148.21 | K22: 1185.43
A23: Operating Expenses
A24: Cost of Operating Revenue | B24: 157.28 | C24: 180.16 | D24: 205.59 | E24: 213.43 | F24: 217.63 | G24: 278.4 | H24: 412.88 | I24: 460.53 | J24: 407.02 | K24: 403.73
A25: Cost of Revenues - Total | B25: 157.28 | C25: 180.16 | D25: 205.59 | E25: 213.43 | F25: 217.63 | G25: 278.4 | H25: 412.88 | I25: 460.53 | J25: 407.02 | K25: 403.73
A26: Cost of Revenues - Unclassified | B26: 139.63 | C26: 161.69 | D26: 187.82 | E26: 196.75 | F26: 201.18 | G26: 260.56 | H26: 393.39 | I26: 436.85 | J26: 385.54 | K26: 383.98
A27: Amortization in Cost of Revenues | B27: 17.65 | C27: 18.47 | D27: 17.77 | E27: 16.68 | F27: 16.45 | G27: 17.84 | H27: 19.49 | I27: 23.67 | J27: 21.49 | K27: 19.75
A28: Gross Profit - Industrials/Property - Total | B28: 341.9 | C28: 389.15 | D28: 431.9 | E28: 455.77 | F28: 488.69 | G28: 602.91 | H28: 824.77 | I28: 900.61 | J28: 741.19 | K28: 781.7
A29: Selling, General & Administrative Expenses - Total | B29: 183.55 | C29: 211.97 | D29: 233.01 | E29: 247.22 | F29: 262.37 | G29: 269.83 | H29: 380.24 | I29: 518.4 | J29: 505.4 | K29: 510.44
A30: Selling, General & Administrative Expenses - Unclassified | B30: 153.54 | C30: 169.51 | D30: 187.87 | E30: 195.49 | F30: 205.33 | G30: 208.14 | H30: 296.24 | I30: 406.74 | J30: 406.25 | K30: 407.62
A31: Labor & Related Expenses including Stock-Based Compensation in Selling, General & Administrative Expenses | E31: 4.79 | F31: 7.02 | G31: 8 | H31: 8.37 | I31: 8.01 | J31: 8.16 | K31: 8.15
A32: Research & Development Expense | B32: 24.03 | C32: 32.42 | D32: 37.64 | E32: 39.63 | F32: 41.75 | G32: 43.12 | H32: 57.49 | I32: 78.7 | J32: 69.09 | K32: 72.39
A33: Amortization of Intangibles in Selling, General & Administrative Expenses | B33: 2.13 | C33: 5.29 | D33: 5.98 | E33: 5.45 | F33: 6.2 | G33: 7.68 | H33: 12.61 | I33: 18.2 | J33: 21.86 | K33: 19.18
A34: Selling, General & Administrative Expenses - Other - Total | B34: 3.85 | C34: 4.74 | D34: 1.51 | E34: 1.86 | F34: 2.08 | G34: 2.88 | H34: 5.54 | I34: 6.75 | J34: 0.04 | K34: 3.1
A35: Property & Other Taxes | E35: 0.75 | F35: 0.94 | G35: 0.8 | H35: 1.41 | I35: 1.37 | J35: 1.7 | K35: 1.81
A36: Provision for Doubtful Accounts & Write-off | B36: 3.85 | C36: 4.74 | D36: 1.51 | E36: 1.11 | F36: 1.14 | G36: 2.08 | H36: 4.13 | I36: 5.38 | J36: -1.66 | K36: 1.29
A37: Other Operating Expense/(Income) - Net | B37: 2.28 | C37: -0.75 | D37: 1.33 | E37: -1.3 | F37: 3.86 | G37: 2.97 | H37: 3.13 | I37: 6.89 | J37: -2.06 | K37: 6.22
A38: Other Operating Expense | G38: 0 | K38: 0
A39: Operating Provisions - Increase/(Decrease) | E39: -1.3 | F39: 3.86 | G39: 2.97 | H39: 3.13 | I39: 6.89 | J39: -2.06 | K39: 6.22
A40: Operating Expenses - Total | B40: 343.11 | C40: 391.37 | D40: 439.93 | E40: 459.35 | F40: 483.86 | G40: 551.19 | H40: 796.25 | I40: 985.82 | J40: 910.36 | K40: 920.38
A41: Operating Profit
A42: Operating Profit before Non-Recurring Income/Expense | B42: 156.07 | C42: 177.94 | D42: 197.56 | E42: 209.85 | F42: 222.46 | G42: 330.11 | H42: 441.4 | I42: 375.32 | J42: 237.85 | K42: 265.05
A43: Non-Operating Expenses
A44: Financing Income/(Expense) - Net - Total | B44: -3.43 | C44: -3.76 | D44: -6.42 | E44: -3.63 | F44: -1.45 | G44: -2.85 | H44: -20.16 | I44: -29.36 | J44: -16.48 | K44: -15.88
A45: Interest Expense - Net of (Interest Income) | B45: -0.59 | C45: 1.38 | D45: 2.6 | E45: 2.49 | F45: 0.68 | G45: 0.94 | H45: 21.06 | I45: 30.72 | J45: 19.59 | K45: 19.45
C46: 1.07 | D46: 1.22 | E46: 1.52 | F46: 2.83 | G46: 2.01 | H46: 0.28 | I46: 3.35 | J46: 8.7 | K46: 6.95
C47: 2.45 | D47: 3.82 | E47: 4 | F47: 3.52 | G47: 2.94 | H47: 21.34 | I47: 34.07 | J47: 28.29 | K47: 26.39
A48: Non-Interest Financial Income/(Expense) - Total | B48: -4.02 | C48: -2.38 | D48: -3.83 | E48: -1.14 | F48: -0.76 | G48: -1.91 | H48: 0.89 | I48: 1.37 | J48: 3.11 | K48: 3.57
C49: -1.12 | D49: -3.04 | E49: -0.28 | F49: 0.28 | G49: -0.99 | H49: 2
C50: -1.26 | D50: -0.79 | E50: -0.87 | F50: -1.04 | G50: -0.92 | H50: -1.11 | I50: 1.37 | J50: 3.11 | K50: 3.57
A51: Equity Earnings/(Loss) - before Taxes including Non-Recurring | B51: -0.43 | C51: -0.56 | D51: -0.4 | E51: -0.14 | F51: -0.11 | G51: 0
A52: Normalized Pre-tax Profit | B52: 152.21 | C52: 173.62 | D52: 190.73 | E52: 206.07 | F52: 220.9 | G52: 327.26 | H52: 421.24 | I52: 345.97 | J52: 221.37 | K52: 249.17
A53: Non-Recurring Income/Expense
A54: Non-Recurring Income/(Expense) - Total | B54: -2.11 | C54: -5.43 | D54: -12.02 | E54: -1.71 | F54: -4.61 | G54: -5.88 | H54: -21.9 | I54: -20.02 | J54: -20.15 | K54: -6.72
A55: Impairment - Tangible & Intangible Fixed Assets | G55: 2.22 | H55: 0 | I55: 9.04 | J55: 4.4 | K55: 0
A56: Impairment - Fixed Assets | G56: 2.22 | H56: 0 | I56: 9.04 | J56: 4.4 | K56: 0
A57: Derivatives - Hedging - Ineffective Gain/(Loss) | I57: 4.04 | J57: 1.44
A58: Fair Value Adjustments - Financial Investments | E58: 2.43 | F58: 0
A59: Sale & Acquisition of Group Companies - Gain/(Loss) | J59: -8.34
A60: Non-Recurring Income/(Expense) - Other - Total | E60: -4.14 | F60: -4.61 | G60: -3.66 | H60: -21.9 | I60: -15.02 | J60: -8.85 | K60: -6.72
A61: Pre-Tax Income
A62: Income before Taxes | B62: 150.1 | C62: 168.2 | D62: 178.71 | E62: 204.37 | F62: 216.29 | G62: 321.37 | H62: 399.34 | I62: 325.94 | J62: 201.22 | K62: 242.45
A63: Taxes
A64: Income Taxes | B64: 49.55 | C64: 55.58 | D64: 38.83 | E64: 46.24 | F64: 40.55 | G64: 73.08 | H64: 88.6 | I64: 85.83 | J64: 42.71 | K64: 55.39
A65: Income Taxes for the Year - Current | B65: 50.46 | C65: 57.56 | D65: 37.58 | E65: 41.77 | F65: 41.36 | G65: 71.79 | H65: 92.75 | I65: 65.89 | J65: 57.89 | K65: 64.69
A66: Income Taxes - Deferred | B66: -0.91 | C66: -1.98 | D66: 1.25 | E66: 3.2 | F66: -8.3 | G66: 1.72 | H66: -1.6 | I66: 22.99 | J66: -12.99 | K66: -7.94
A67: Income Taxes - Other (by Type) | E67: 1.26 | F67: 7.5 | G67: -0.44 | H67: -2.55 | I67: -3.05 | J67: -2.19 | K67: -1.36
A68: Net Income After Tax
A69: Net Income after Tax | B69: 100.55 | C69: 112.62 | D69: 139.88 | E69: 158.13 | F69: 175.74 | G69: 248.3 | H69: 310.73 | I69: 240.11 | J69: 158.51 | K69: 187.06
A70: After Tax Income/Expense
A71: Income before Discontinued Operations & Extraordinary Items | B71: 100.55 | C71: 112.62 | D71: 139.88 | E71: 158.13 | F71: 175.74 | G71: 248.3 | H71: 310.73 | I71: 240.11 | J71: 158.51 | K71: 187.06
A72: Net Income before Minority Interest | B72: 100.55 | C72: 112.62 | D72: 139.88 | E72: 158.13 | F72: 175.74 | G72: 248.3 | H72: 310.73 | I72: 240.11 | J72: 158.51 | K72: 187.06
A73: Minority Interest | B73: 0.13 | C73: 0.24 | D73: 0 | E73: 0 | F73: 0 | G73: 0.43 | H73: -0.24 | I73: -0.8 | J73: -1.34 | K73: -1.05
A74: Net Income after Minority Interest | B74: 100.42 | C74: 112.38 | D74: 139.88 | E74: 158.13 | F74: 175.74 | G74: 247.87 | H74: 310.97 | I74: 240.91 | J74: 159.85 | K74: 188.11
A75: Net Income
A76: Income Available to Common Shares | B76: 100.42 | C76: 112.38 | D76: 139.88 | E76: 158.13 | F76: 175.74 | G76: 247.87 | H76: 310.97 | I76: 240.91 | J76: 159.85 | K76: 188.11
A77: Other Comprehensive Income
A78: Other Comprehensive Income - Starting Line | D78: 139.88 | E78: 158.13 | F78: 175.74 | G78: 248.3 | H78: 310.73 | I78: 240.11 | J78: 158.51 | K78: 187.06
A79: Other Comprehensive Income - Foreign Currency | D79: -39.9 | E79: 12.19 | F79: 8.14 | G79: -48.6 | H79: 73.19 | I79: 74.79 | J79: -53.49 | K79: 100.86
A80: Other Comprehensive Income - Hedging Gain/(Loss) | H80: 6.22 | I80: 37.35 | J80: -17.55 | K80: -15.28
A81: Other Comprehensive Income - Other | E81: -0.06 | F81: 0.06 | G81: 0 | J81: 0
A82: Other Comprehensive Income - Pension Related | D82: 0.59 | E82: 0.02 | F82: -2.65 | G82: -1.49 | H82: 1.55 | I82: 6.84 | J82: -2.63 | K82: 1.11
A83: Other Comprehensive Income - Net of Tax - Total | D83: -39.32 | E83: 12.15 | F83: 5.55 | G83: -50.09 | H83: 80.97 | I83: 118.97 | J83: -73.67 | K83: 86.68
A84: Comprehensive Income before Minority Interest - Total | D84: 100.56 | E84: 170.28 | F84: 181.28 | G84: 198.21 | H84: 391.7 | I84: 359.08 | J84: 84.84 | K84: 273.74
A85: Comprehensive Income - Attributable to Minority Interest - Total | D85: -0.03 | E85: 0 | F85: 0 | G85: 0.43 | H85: -0.24 | I85: -0.8 | J85: -1.4 | K85: -1.25
A86: Comprehensive Income - Attributable to Parent Company Equity Holders - Total | D86: 100.59 | E86: 170.27 | F86: 181.28 | G86: 197.78 | H86: 391.94 | I86: 359.88 | J86: 86.25 | K86: 274.99
A87: Share/Per Share - Basic
A88: Net Income - Basic - including Extraordinary Items Applicable to Common - Total | B88: 100.42 | C88: 112.38 | D88: 139.88 | E88: 158.13 | F88: 175.74 | G88: 247.87 | H88: 310.97 | I88: 240.91 | J88: 159.85 | K88: 188.11
A89: Income available to Common excluding Extraordinary Items | B89: 100.42 | C89: 112.38 | D89: 139.88 | E89: 158.13 | F89: 175.74 | G89: 247.87 | H89: 310.97 | I89: 240.91 | J89: 159.85 | K89: 188.11
A90: Shares used to calculate Basic EPS - Total | B90: 54.88 | C90: 54.85 | D90: 55 | E90: 55.51 | F90: 54.71 | G90: 54.76 | H90: 57.12 | I90: 55.95 | J90: 55.75 | K90: 55.87
A91: EPS - Basic - including Extraordinary Items Applicable to Common - Total | B91: 1.83 | C91: 2.05 | D91: 2.54 | E91: 2.85 | F91: 3.21 | G91: 4.53 | H91: 5.44 | I91: 4.31 | J91: 2.87 | K91: 3.37
A92: EPS - Basic - excluding Extraordinary Items Applicable to Common - Total | B92: 1.83 | C92: 2.05 | D92: 2.54 | E92: 2.85 | F92: 3.21 | G92: 4.53 | H92: 5.44 | I92: 4.31 | J92: 2.87 | K92: 3.37
A93: EPS - Basic - excluding Extraordinary Items - Normalized - Total | B93: 1.87 | C93: 2.15 | D93: 2.76 | E93: 2.88 | F93: 3.3 | G93: 4.63 | H93: 5.83 | I93: 4.66 | J93: 3.23 | K93: 3.49
A94: Allocated Net Income including Extraordinary Items Applicable to Common - Issue Specific | B94: 100.42 | C94: 112.38 | D94: 139.88 | E94: 158.13 | F94: 175.74 | G94: 247.87 | H94: 310.97 | I94: 240.91 | J94: 159.85 | K94: 188.11
A95: Earnings Allocation Factor - Basic - Issue Specific | B95: 1 | C95: 1 | D95: 1 | E95: 1 | F95: 1 | G95: 1 | H95: 1 | I95: 1 | J95: 1 | K95: 1
A96: Shares used to calculate Basic EPS - Issue Specific | B96: 54.88 | C96: 54.85 | D96: 55 | E96: 55.51 | F96: 54.71 | G96: 54.76 | H96: 57.12 | I96: 55.95 | J96: 55.75 | K96: 55.87
A97: EPS - Basic - including Extraordinary Items Applicable to Common - Issue Specific | B97: 1.83 | C97: 2.05 | D97: 2.54 | E97: 2.85 | F97: 3.21 | G97: 4.53 | H97: 5.44 | I97: 4.31 | J97: 2.87 | K97: 3.37
A98: EPS - Basic - excluding Extraordinary Items Applicable to Common - Issue Specific | B98: 1.83 | C98: 2.05 | D98: 2.54 | E98: 2.85 | F98: 3.21 | G98: 4.53 | H98: 5.44 | I98: 4.31 | J98: 2.87 | K98: 3.37
A99: EPS - Basic - excluding Extraordinary Items - Normalized - Issue Specific | B99: 1.87 | C99: 2.15 | D99: 2.76 | E99: 2.88 | F99: 3.3 | G99: 4.63 | H99: 5.83 | I99: 4.66 | J99: 3.23 | K99: 3.49
A100: EPS - Basic from Discontinued Operations & Extraordinary Items | B100: 0 | C100: 0 | D100: 0 | E100: 0 | F100: 0 | G100: 0 | H100: 0 | I100: 0 | J100: 0 | K100: 0
A101: Comprehensive Earnings Per Share - Basic - Issue Specific | D101: 1.83 | E101: 3.07 | F101: 3.31 | G101: 3.61 | H101: 6.86 | I101: 6.43 | J101: 1.55 | K101: 4.92
...

Sheet AFS2
I2: HISTORICAL (ACTUALS) | K2: FORECAST (MEAN)
B3: FY Dec-17 | C3: FY Dec-18 | D3: FY Dec-19 | E3: FY Dec-20 | F3: FY Dec-21 | G3: FY Dec-22 | H3: FY Dec-23 | I3: FY Dec-24 | K3: FY Dec-25 | L3: FY Dec-26 | M3: FY Dec-27 | N3: FY Dec-28 | O3: FY Dec-29
A4: REVENUE | B4: 637.5 | C4: 669.2 | D4: 706.3 | E4: 881.305 | F4: 1237.7 | G4: 1361.1 | H4: 1148 | I4: 1185 | K4: 1203.7806 | L4: 1275.5036 | M4: 1375.6088 | N4: 1463.3333 | O4: 1563
A5: COST OF GOODS SOLD | B5: 205.6 | C5: 213.4 | D5: 217.6 | E5: 278.4 | F5: 412.9 | G5: 460.5 | H5: 407 | I5: 403.726 | K5: 424 | L5: 445.5 | M5: 475.5 | N5: 512 | O5: 546
A6: GROSS INCOME | B6: 431.9 | C6: 455.8 | D6: 488.7 | E6: 602.905 | F6: 824.8 | G6: 900.6 | H6: 741 | I6: 781.701 | K6: 782.33333 | L6: 813 | M6: 866 | N6: 946 | O6: 1018
A7: GROSS PROFIT MARGIN | B7: 0.677 | C7: 0.6811 | D7: 0.6919 | E7: 0.6841 | F7: 0.6664 | G7: 0.6616 | H7: 0.6454 | I7: 0.6594 | K7: 0.6494567 | L7: 0.6478 | M7: 0.6474 | N7: 0.646 | O7: 0.65
A9: R&D EXPENSE | B9: 43.6 | C9: 45.1 | D9: 41.752 | E9: 50.8 | F9: 70.1 | G9: 78.702 | H9: 69.09 | I9: 91.567 | K9: 92 | L9: 95 | M9: 99 | N9: 106 | O9: 114
A10: SELLING & MARKETING EXPENSE | B10: 123.2 | C10: 133.1 | D10: 142.8 | E10: 144.064 | F10: 211.3 | G10: 292.05 | H10: 286 | I10: 287.748 | K10: 287 | L10: 296 | M10: 308 | N10: 330 | O10: 357
A11: GENERAL & ADMIN EXPENSE | B11: 64.7 | C11: 67.2 | D11: 69.6 | E11: 72.083 | F11: 93.299 | G11: 122.7 | H11: 129 | I11: 128.023 | K11: 122 | L11: 123.5 | M11: 127 | N11: 132 | O11: 136
A12: SG&A EXPENSE | B12: 187.9 | C12: 200.3 | D12: 205.328 | E12: 216.147 | F12: 304.6 | G12: 406.737 | H12: - | I12: - | K12: 131 | L12: 133 | M12: 134 | N12: - | O12: -
A14: EBITDA | B14: 237.922 | C14: 255.4 | D14: 276.8 | E14: 385.26 | F14: 543.1 | G14: 514.2 | H14: 375 | I14: 394 | K14: 393.05854 | L14: 426.75162 | M14: 469.09458 | N14: 480 | O14: 546.5
A15: EBITDA MARGIN | B15: - | C15: - | D15: - | E15: - | F15: - | G15: - | H15: - | I15: 0.33247 | K15: 0.334 | L15: 0.34 | M15: 0.3485714 | N15: 0.356 | O15: 0.354
A16: EBITDA PER SHARE | B16: - | C16: - | D16: - | E16: 7.04 | F16: 9.43 | G16: 9.41 | H16: 7.04 | I16: 7.049 | K16: 6.6 | L16: 7.22 | M16: 7.895 | N16: 8.655 | O16: 10.28
A17: DEPRECIATION & AMORTIZATION | B17: 69.609 | C17: 50.826 | D17: 58.972 | E17: 61.034 | F17: 115.506 | G17: 137.546 | H17: 158.371 | I17: 148.79 | K17: 133.35833 | L17: 137.34333 | M17: 141.65167 | N17: 141.465 | O17: 140.5
A18: DEPRECIATION | B18: 29.666 | C18: 28.97 | D18: 35.132 | E18: 33.558 | F18: 47.131 | G18: 60.404 | H18: 61.829 | I18: 53.871 | K18: 78.70225 | L18: 84.127 | M18: 91.3055 | N18: 82.7475 | O18: 77.013
A19: AMORTIZATION | B19: - | C19: 21.855 | D19: 23.84 | E19: 27.476 | F19: - | G19: 40.142 | H19: 10.919 | I19: 94.919 | K19: 88.88233 | L19: 86.526 | M19: 86.448 | N19: 63.1055 | O19: 61.133
A20: EBITA | B20: 208.236 | C20: 226.355 | D20: 241.74 | E20: 351.702 | F20: - | G20: 457.163 | H20: 192 | I20: - | K20: 276.5 | L20: 297.66667 | M20: 333 | N20: 320 | O20: -
A22: EBIT | B22: 184.4 | C22: 204.5 | D22: 217.9 | E22: 324.226 | F22: 465.1 | G22: 417.021 | H22: 216 | I22: 258 | K22: 275.15015 | L22: 303.63631 | M22: 345.33931 | N22: 357 | O22: 406
A23: EBIT MARGIN | B23: - | C23: - | D23: - | E23: - | F23: - | G23: - | H23: - | I23: 0.2177 | K23: 0.2235 | L23: 0.2373333 | M23: 0.2506667 | N23: 0.264 | O23: 0.2655
A24: INTEREST EXPENSE | B24: 5.7 | C24: 0.2 | D24: 3.517 | E24: 2.9 | F24: 20.2 | G24: 34.072 | H24: 15 | I24: 28.801 | K24: 17 | L24: 15.26 | M24: 12.88 | N24: 10 | O24: 7
A25: OTHER INCOME/EXPENSE | B25: - | C25: - | D25: - | E25: - | F25: - | G25: - | H25: - | I25: - | K25: 17 | L25: 18 | M25: 18 | N25: 17 | O25: 17
A27: PRE-TAX PROFIT | B27: 178.7 | C27: 204.4 | D27: 216.3 | E27: 321.373 | F27: 399.3 | G27: 325.9 | H27: 201 | I27: 242.448 | K27: 272.38578 | L27: 289.99944 | M27: 325.347 | N27: 342.5 | O27: 427
A28: TAX PROVISION | B28: 38.8 | C28: 46.2 | D28: 40.6 | E28: 73.077 | F28: 88.6 | G28: 85.8 | H28: 42 | I28: 55.391 | K28: 58.075 | L28: 67.35 | M28: 77.9 | N28: 87 | O28: 94.5
A29: TAX RATE | B29: 0.2171237 | C29: 0.2259 | D29: 0.1877023 | E29: 0.2274424 | F29: 0.2218883 | G29: 0.2632709 | H29: 0.2089552 | I29: 0.2272727 | K29: 0.2455143 | L29: 0.246 | M29: 0.2422857 | N29: 0.235 | O29: 0.25
A31: NET INCOME | B31: 139.9 | C31: 158.1 | D31: 175.7 | E31: 248.3 | F31: 310.7 | G31: 240.1 | H31: 159 | I31: 187 | K31: 210.032 | L31: 233.67567 | M31: 266.1495 | N31: 281.33333 | O31: 323
A32: NET INCOME MARGIN | B32: - | C32: - | D32: - | E32: - | F32: - | G32: - | H32: - | I32: 0.15699 | K32: 0.1761667 | L32: 0.1878 | M32: 0.2 | N32: 0.218 | O32: 0.205
A34: EARNINGS PER SHARE | B34: 2.54 | C34: 2.85 | D34: 3.2 | E34: 4.5 | F34: 5.4 | G34: 4.392 | H34: 2.98 | I34: 3.342 | K34: 3.5505 | L34: 4.0372 | M34: 4.64836 | N34: 4.66 | O34: 5.3
A35: CASH EPS | B35: - | C35: - | D35: - | E35: - | F35: - | G35: - | H35: - | I35: 6.01 | K35: 5.745 | L35: 6.116 | M35: 6.595 | N35: - | O35: -
A36: EBITDA REPORTED | B36: 237.922 | C36: 255.4 | D36: 276.8 | E36: 385.26 | F36: 556.907 | G36: 536.542 | H36: 375 | I36: 387.366 | K36: 389.74667 | L36: 426.08833 | M36: 475.54 | N36: 497.34 | O36: 546.5
A37: PRE-TAX PROFIT REPORTED | B37: 178.7 | C37: 204.4 | D37: 216.3 | E37: 321.373 | F37: 399.3 | G37: 325.9 | H37: 201 | I37: 242.448 | K37: 250.5545 | L37: 282.39475 | M37: 325.7395 | N37: 350 | O37: 387
A38: NET INCOME REPORTED | B38: 139.9 | C38: 158.1 | D38: 175.7 | E38: 248.3 | F38: 310.7 | G38: 240.1 | H38: 159 | I38: 187 | K38: 177.32571 | L38: 207.82257 | M38: 243.33443 | N38: 262 | O38: 290
A39: EARNINGS PER SHARE REPORTED | B39: 2.54 | C39: 2.85 | D39: 3.2 | E39: 4.5 | F39: 5.4 | G39: 4.392 | H39: 2.98 | I39: 3.342 | K39: 3.31711 | L39: 3.9299 | M39: 4.48589 | N39: 4.79 | O39: 5.3
A40: DIVIDEND PER SHARE | B40: 0.85 | C40: 0.9 | D40: 0.9 | E40: 0.95 | F40: 1.05 | G40: 1.1 | H40: 1.15 | I40: 1.15 | K40: 1.2024 | L40: 1.28333 | M40: 1.3685 | N40: 1.47667 | O40: 1.535
A41: NUMBER OF SHARES OUTSTANDING | B41: 53.56836 | C41: 55.51311 | D41: 54.712 | E41: 54.758 | F41: 57.58667 | G41: 54.665 | H41: 53.289 | I41: 55.86871 | K41: 55.78 | L41: 55.066 | M41: 55.066 | N41: 53.69 | O41: 55
A42: NET INTEREST EXPENSES (INCOME) | B42: - | C42: - | D42: - | E42: - | F42: - | G42: - | H42: - | I42: - | K42: 14 | L42: 10 | M42: 6 | N42: 2 | O42: 7
K44: =K50/I50-1 -> 0.014850586 | L44: =L50/K50-1 -> 0.040399523 | M44: =M50/L50-1 -> 0.048431007 | N44: =N50/M50-1 -> 0.0087011972 | O44: =O50/N50-1 -> 0.077138471
B45: FY Dec-17 | C45: FY Dec-18 | D45: FY Dec-19 | E45: FY Dec-20 | F45: FY Dec-21 | G45: FY Dec-22 | H45: FY Dec-23 | I45: FY Dec-24 | K45: FY Dec-25 | L45: FY Dec-26 | M45: FY Dec-27 | N45: FY Dec-28 | O45: FY Dec-29
A46: CASH AND CASH EQUIVALENTS | B46: 159.34 | C46: 73.1 | D46: 157.552 | E46: 339.881 | F46: 403.02 | G46: 241.776 | H46: 280.314 | I46: 344.27 | K46: 423 | L46: 560.5 | M46: 720.75 | N46: 735.66667 | O46: 1006
A47: INVENTORY | B47: 142.802 | C47: 160.396 | D47: 171.127 | E47: 191.234 | F47: 298.049 | G47: 306.503 | H47: 315.5 | I47: 344.043 | K47: 319 | L47: 340.25 | M47: 365.25 | N47: 388 | O47: 409.5
A48: CURRENT ASSETS | B48: 481.241 | C48: 414.86 | D48: 530.761 | E48: 713.917 | F48: 958.291 | G48: 1028.94 | H48: 982.692 | I48: 967.181 | K48: 1039 | L48: 1178.6667 | M48: 1355.3333 | N48: 1260.5 | O48: 1344
A49: GOODWILL | B49: 150.744 | C49: 162.616 | D49: 164.681 | E49: 154.774 | F49: 0.001 | G49: 1995 | H49: 0.001 | I49: 846.86 | K49: 846.965 | L49: 846.965 | M49: 846.965 | N49: 847 | O49: 847
A50: TOTAL ASSETS | B50: 945.723 | C50: 905.94 | D50: 1063.552 | E50: 1246.446 | F50: 3231.152 | G50: 3408.082 | H50: 3211.439 | I50: 3304.92 | K50: 3354 | L50: 3489.5 | M50: 3658.5 | N50: 3690.3333 | O50: 3975
A51: CURRENT LIABILITIES | B51: 141.12 | C51: 138.452 | D51: 122.479 | E51: 160.213 | F51: 298.229 | G51: 341.314 | H51: 320.117 | I51: 275.299 | K51: 267.66667 | L51: 275.33333 | M51: 288 | N51: 299.5 | O51: 315
A52: TOTAL LIABILITIES | B52: - | C52: - | D52: - | E52: - | F52: - | G52: 1842 | H52: - | I52: 1505.898 | K52: 1453.05 | L52: 1437.075 | M52: 1425.5 | N52: 1295 | O52: 1319
A53: SHAREHOLDERS EQUITY | B53: 742 | C53: 704.7 | D53: 848.6 | E53: 954.678 | F53: 1366.377 | G53: 1518.989 | H53: 1538.611 | I53: 1800.918 | K53: 1893.9563 | L53: 2040.0896 | M53: 2215.385 | N53: 2626.3333 | O53: 2658
A54: TOTAL DEBT | B54: - | C54: - | D54: - | E54: 34.66 | F54: - | G54: - | H54: - | I54: 1076.707 | K54: 1015 | L54: 1015 | M54: 1015 | N54: 1015 | O54: 1015
A55: NET DEBT | B55: -149.3 | C55: -75.3 | D55: -128.274 | E55: -305.221 | F55: 985.9 | G55: 906.611 | H55: - | I55: 732.437 | K55: 540.27615 | L55: 382.96808 | M55: 258.78982 | N55: 457.33333 | O55: -
A56: NET ASSET VALUE | B56: 742 | C56: 704.7 | D56: 848.6 | E56: 956.319 | F56: 1367.9 | G56: 1519.8 | H56: 1538 | I56: 1799.022 | K56: 1875.8857 | L56: 1994.7 | M56: 2170.2714 | N56: 2530 | O56: 2777
A57: BOOK VALUE PER SHARE | B57: 13.38312 | C57: 12.89368 | D57: 15.48846 | E57: 17.43 | F57: 24.95836 | G57: 28.38548 | H57: 28.83455 | I57: 33.41719 | K57: 32.5018 | L57: 34.3333 | M57: 36.9056 | N57: 40.69 | O57: 45.78
A58: ENTERPRISE VALUE | B58: 3950.256 | C58: 3880.242 | D58: - | E58: 9010.756 | F58: - | G58: 8616 | H58: - | I58: 6203.52 | K58: 4381.673 | L58: 4167.1136 | M58: 3992.6271 | N58: 4253.5 | O58: 4016

Sheet AFS3
A1: DiaSorin S.p.A. (DIA-IT)
B2: DEC '15 | C2: DEC '16 | D2: DEC '17 | E2: DEC '18 | F2: DEC '19 | G2: DEC '20 | H2: DEC '21 | I2: DEC '22 | J2: DEC '23 | K2: DEC '24
A3: Sales | B3: 499.181 | C3: 569.312 | D3: 637.487 | E3: 669.197 | F3: 706.319 | G3: 881.305 | H3: 1237.654 | I3: 1361.138 | J3: 1148.21 | K3: 1185.427
A4: Cost of Goods Sold (COGS) incl. D&A | B4: 165.674 | C4: 198.729 | D4: 225.094 | E4: 234.956 | F4: 244.163 | G4: 298.932 | H4: 455.587 | I4: 534.632 | J4: 479.127 | K4: 477.909
A5: COGS excluding D&A | B5: 132.69 | C5: 154.022 | D5: 179.243 | E5: 189.581 | F5: 191.387 | G5: 240.119 | H5: 372.181 | I5: 415.288 | J5: 364.101 | K5: 348.868
A6: Depreciation & Amortization Expense | B6: 32.984 | C6: 44.707 | D6: 45.851 | E6: 45.375 | F6: 52.776 | G6: 58.813 | H6: 83.406 | I6: 119.344 | J6: 115.026 | K6: 129.041
A7: Depreciation | B7: 24.875 | C7: 27.141 | D7: 29.666 | E7: 28.531 | F7: 35.132 | G7: 33.558 | H7: 47.131 | I7: 60.404 | J7: 61.829 | K7: 53.871
A8: Amortization of Intangibles | B8: 8.109 | C8: 17.566 | D8: 16.185 | E8: 16.844 | F8: 17.644 | G8: 25.255 | H8: 36.275 | I8: 58.94 | J8: 53.197 | K8: 75.17
A9: Gross Income | B9: 333.507 | C9: 370.583 | D9: 412.393 | E9: 434.241 | F9: 462.156 | G9: 582.373 | H9: 782.067 | I9: 826.506 | J9: 669.083 | K9: 707.518
A10: SG&A Expense | B10: 175.134 | C10: 189.567 | D10: 211.997 | E10: 223.828 | F10: 233.516 | G10: 247.628 | H10: 332.827 | I10: 438.599 | J10: 433.175 | K10: 426.764
A11: Research & Development | B11: 23.889 | C11: 31.519 | D11: 41.999 | E11: 42.542 | F11: 45.616 | G11: 50.8 | H11: 63.385 | I11: 93.146 | J11: 89.71 | K11: 68.458
A12: Other SG&A | B12: 151.245 | C12: 158.048 | D12: 169.998 | E12: 181.286 | F12: 187.9 | G12: 196.828 | H12: 269.442 | I12: 345.453 | J12: 343.465 | K12: 358.306
A13: Other Operating Expense | B13: 2.008 | C13: 5.337 | D13: 2.208 | E13: 1.861 | F13: 2.317 | G13: 1.667 | H13: 4.707 | I13: 5.691 | J13: 0.12 | K13: 3.102
A14: EBIT (Operating Income) | B14: 156.365 | C14: 175.679 | D14: 198.188 | E14: 208.552 | F14: 226.323 | G14: 333.078 | H14: 444.533 | I14: 382.216 | J14: 235.788 | K14: 277.652
... A20: Unusual Expense - Net | B20: 2.108 | C20: 5.426 | D20: 12.022 | E20: 1.709 | F20: 4.615 | G20: 5.885 | H20: 21.902 | I20: 20.025 | J20: 11.814 | K20: 6.391
A21: Impairments | G21: 2.222 | H21: 0 | I21: 9.039 | J21: 4.404 | K21: 0
A22: Other Intangibles | D22: 0 | E22: 0 | F22: 0 | G22: 0 | H22: 0 | I22: 9.039 | J22: 4.404 | K22: 0
A23: Property,Plant & Equipment | G23: 2.222 | H23: 0
A24: Restructuring Expense | B24: 2.108 | C24: 5.426 | D24: 12.022 | E24: 0 | F24: 0 | G24: 0 | H24: 21.902 | I24: 15.023 | J24: 8.847 | K24: 6.391
A25: Unrealized Valuation Gain/Loss | E25: 2.43 | F25: 0 | I25: 4.037 | J25: 1.437
A26: Hedges/Derivatives | I26: 4.037 | J26: 1.437
A27: Other Intangibles | E27: 2.43 | F27: 0
A28: Excpl Chrgs - Others | E28: 4.139 | F28: 4.615 | G28: 3.663
A29: Other Unusual Expense | B29: 2.108 | E29: 4.139 | F29: 4.615 | G29: 3.663
A30: Pretax Income | B30: 150.533 | C30: 168.751 | D30: 179.11 | E30: 204.508 | F30: 216.402 | G30: 321.373 | H30: 399.335 | I30: 325.94 | J30: 201.216 | K30: 242.448
A31: Income Taxes | B31: 49.554 | C31: 55.578 | D31: 38.828 | E31: 46.235 | F31: 40.552 | G31: 73.077 | H31: 88.603 | I31: 85.83 | J31: 42.708 | K31: 55.391
A32: Income Taxes - Current Domestic | B32: 50.462 | C32: 57.557 | D32: 37.575 | E32: 43.034 | F32: 48.857 | G32: 71.355 | H32: 90.201 | I32: 62.842 | J32: 55.695 | K32: 63.332
A33: Income Taxes - Deferred Domestic | B33: -0.908 | C33: -1.979 | D33: 1.253 | E33: 3.201 | F33: -8.305 | G33: 1.722 | H33: -1.598 | I33: 22.988 | J33: -12.987 | K33: -7.941
A34: Equity in Earnings of Affiliates | B34: -0.431 | C34: -0.555 | D34: -0.404 | E34: -0.143 | F34: -0.115 | K34: 0
A35: Consolidated Net Income | B35: 100.548 | C35: 112.618 | D35: 139.878 | E35: 158.13 | F35: 175.735 | G35: 248.296 | H35: 310.732 | I35: 240.11 | J35: 158.508 | K35: 187.057
A36: Minority Interest | B36: 0.128 | C36: 0.235 | D36: 0 | E36: 0.002 | F36: 0 | G36: 0.425 | H36: -0.236 | I36: -0.797 | J36: -1.341 | K36: -1.048
A37: Net Income | B37: 100.42 | C37: 112.383 | D37: 139.878 | E37: 158.128 | F37: 175.735 | G37: 247.871 | H37: 310.968 | I37: 240.907 | J37: 159.849 | K37: 188.105
A38: Net Income available to Common | B38: 100.42 | C38: 112.383 | D38: 139.878 | E38: 158.128 | F38: 175.735 | G38: 247.871 | H38: 310.968 | I38: 240.907 | J38: 159.849 | K38: 188.105
A39: Per Share
A40: EPS (recurring) | B40: 1.856579 | C40: 2.108946 | D40: 2.69637 | E40: 2.87003 | F40: 3.258825 | G40: 4.574788 | H40: 5.666232 | I40: 4.391473 | J40: 3.015804 | K40: 3.429673
A41: EPS (basic) | B41: 1.83 | C41: 2.05 | D41: 2.54 | E41: 2.8485 | F41: 3.212 | G41: 4.5267 | H41: 5.4443 | I41: 4.1715 | J41: 2.8675 | K41: 3.3669
A42: Basic Shares Outstanding | B42: 54.883529 | C42: 54.849893 | D42: 54.997425 | E42: 55.513113 | F42: 54.711844 | G42: 54.757637 | H42: 57.117998 | I42: 57.75085 | J42: 55.745935 | K42: 55.868709
A43: Total Shares Outstanding | B43: 54.978307 | C43: 54.758307 | D43: 55.3994 | E43: 54.65725 | F43: 54.790656 | G43: 54.722145 | H43: 54.746257 | I43: 53.512885 | J43: 53.359979 | K43: 53.891959
A44: EPS (diluted) | B44: 1.83 | C44: 2.04 | D44: 2.54 | E44: 2.8485 | F44: 3.2 | G44: 4.5 | H44: 5.4 | I44: 4.15 | J44: 2.8675 | K44: 3.35
A45: Diluted Shares Outstanding | B45: 54.883529 | C45: 55.089706 | D45: 54.997425 | E45: 55.513113 | F45: 54.917187 | G45: 55.082444 | H45: 57.586667 | I45: 58.04988 | J45: 55.745935 | K45: 56.150746
A46: Total Shares Outstanding | B46: 54.978307 | C46: 54.758307 | D46: 55.3994 | E46: 54.65725 | F46: 54.790656 | G46: 54.722145 | H46: 54.746257 | I46: 53.512885 | J46: 53.359979 | K46: 53.891959
A47: Earnings Persistence | B47: 94.684 | C47: 62.331 | D47: 89.566 | E47: 89.311 | F47: 90.311 | G47: 91.637 | H47: 48.34 | I47: 90.291 | J47: 88.492 | K47: 89.394
A48: Dividends per Share | B48: 0.65 | C48: 0.8 | D48: 0.85 | E48: 0.9 | F48: 0.95 | G48: 1 | H48: 1.05 | I48: 1.1 | J48: 1.15 | K48: 1.2
A49: Payout Ratio | B49: 35.519126 | C49: 39.02439 | D49: 33.464567 | E49: 31.595577 | F49: 29.576588 | G49: 22.091148 | H49: 19.286226 | I49: 26.369411 | J49: 40.104621 | K49: 35.641094
A50: EBITDA
A51: EBITDA | B51: 189.349 | C51: 220.386 | D51: 244.039 | E51: 253.927 | F51: 279.099 | G51: 391.891 | H51: 527.939 | I51: 501.56 | J51: 350.814 | K51: 406.693
A52: EBIT | B52: 156.365 | C52: 175.679 | D52: 198.188 | E52: 208.552 | F52: 226.323 | G52: 333.078 | H52: 444.533 | I52: 382.216 | J52: 235.788 | K52: 277.652
A53: Depreciation & Amortization Expense | B53: 32.984 | C53: 44.707 | D53: 45.851 | E53: 45.375 | F53: 52.776 | G53: 58.813 | H53: 83.406 | I53: 119.344 | J53: 115.026 | K53: 129.041
A54: All figures in millions of Euro except per share items.
B56: DEC '15 | C56: DEC '16 | D56: DEC '17 | E56: DEC '18 | F56: DEC '19 | G56: DEC '20 | H56: DEC '21 | I56: DEC '22 | J56: DEC '23 | K56: DEC '24
A57: Assets
A58: Cash & Short-Term Investments | B58: 270.357 | C58: 130.468 | D58: 173.314 | E58: 96.525 | F58: 202.14 | G58: 340.007 | H58: 403.02 | I58: 413.218 | J58: 403.389 | K58: 393.268
A59: Cash Only | B59: 212.178 | C59: 130.468 | D59: 159.34 | E59: 73.103 | F59: 157.552 | G59: 339.881 | H59: 403.02 | I59: 241.776 | J59: 280.314 | K59: 344.27
A60: Total Short Term Investments | B60: 58.179 | C60: 0 | D60: 13.974 | E60: 23.422 | F60: 44.588 | G60: 0.126 | H60: 0 | I60: 171.442 | J60: 123.075 | K60: 48.998
A61: Short-Term Receivables | B61: 105.609 | C61: 120.261 | D61: 147.24 | E61: 136.244 | F61: 140.5 | G61: 166.687 | H61: 226.249 | I61: 241.353 | J61: 228.711 | K61: 204.111
A62: Accounts Receivables, Net | B62: 105.609 | C62: 120.261 | D62: 128.822 | E62: 131.092 | F62: 132.513 | G62: 165.678 | H62: 217.588 | I62: 220.035 | J62: 198.56 | K62: 194.696
A63: Accounts Receivables, Gross | B63: 115.43 | C63: 130.876 | D63: 138.437 | E63: 139.974 | F63: 141.133 | G63: 174.415 | H63: 229.557 | I63: 233.539 | J63: 209.807 | K63: 206.122
A64: Bad Debt/Doubtful Accounts | B64: -9.821 | C64: -10.615 | D64: -9.615 | E64: -8.882 | F64: -8.62 | G64: -8.737 | H64: -11.969 | I64: -13.504 | J64: -11.247 | K64: -11.426
A65: Other Receivables | B65: 0 | C65: 0 | D65: 18.418 | E65: 5.152 | F65: 7.987 | G65: 1.009 | H65: 8.661 | I65: 21.318 | J65: 30.151 | K65: 9.415
A66: Inventories | B66: 106.193 | C66: 128.87 | D66: 142.802 | E66: 160.396 | F66: 171.127 | G66: 191.234 | H66: 298.049 | I66: 306.503 | J66: 315.5 | K66: 344.043
A67: Finished Goods | B67: 35.988 | C67: 49.281 | D67: 57.135 | E67: 66.976 | F67: 71.458 | G67: 71.276 | H67: 73.011 | I67: 95.041 | J67: 103.19 | K67: 103.692
A68: Work in Progress | B68: 37.664 | C68: 42.28 | D68: 45.335 | E68: 47.387 | F68: 49.904 | G68: 52.472 | H68: 75.606 | I68: 74.841 | J68: 76.393 | K68: 82.339
A69: Raw Materials | B69: 32.541 | C69: 37.309 | D69: 40.332 | E69: 46.033 | F69: 49.765 | G69: 67.486 | H69: 149.432 | I69: 136.621 | J69: 135.917 | K69: 158.012
A70: Other Current Assets | B70: 12.173 | C70: 15.784 | D70: 17.885 | E70: 21.695 | F70: 16.994 | G70: 15.989 | H70: 30.973 | I70: 67.866 | J70: 35.092 | K70: 25.759
A71: Prepaid Expenses | D71: 3.223 | E71: 3.86 | I71: 10.958
A72: Miscellaneous Current Assets | B72: 12.173 | C72: 15.784 | D72: 14.662 | E72: 17.835 | F72: 16.994 | G72: 15.989 | H72: 30.973 | I72: 56.908 | J72: 35.092 | K72: 25.759
A73: Total Current Assets | B73: 494.332 | C73: 395.383 | D73: 481.241 | E73: 414.86 | F73: 530.761 | G73: 713.917 | H73: 958.291 | I73: 1028.94 | J73: 982.692 | K73: 967.181
A74: Net Property, Plant & Equipment | B74: 74.493 | C74: 92.134 | D74: 92.332 | E74: 94.981 | F74: 128.385 | G74: 140.497 | H74: 276.197 | I74: 268.448 | J74: 256.286 | K74: 271.359
A75: Property, Plant & Equipment - Gross | B75: 227.356 | C75: 258.776 | D75: 268.044 | E75: 281.657 | F75: 330.774 | G75: 347.884 | H75: 524.313 | I75: 555.269 | J75: 598.459 | K75: 644.853
A76: Buildings | B76: 20.024 | C76: 20.597 | D76: 22.221 | E76: 23.635 | F76: 25.565 | G76: 27.635 | H76: 35.555 | I76: 42.632 | J76: 47.594 | K76: 58.714
A77: Land & Improvements | B77: 2.375 | C77: 2.385 | D77: 2.348 | E77: 2.361 | F77: 2.366 | G77: 2.342 | H77: 4.982 | I77: 5.161 | J77: 5.053 | K77: 5.242 | M77: =SUM(B76:B82) -> 227.356
A78: Machinery & Equipment | B78: 183.544 | C78: 204.652 | D78: 206.165 | E78: 216.178 | F78: 225.514 | G78: 228.699 | H78: 301.065 | I78: 318.497 | J78: 337.366 | K78: 351.79
A79: Construction in Progress | B79: 3.918 | C79: 7.069 | D79: 12.756 | E79: 10.353 | F79: 14.301 | G79: 15.656 | H79: 27.607 | I79: 34.382 | J79: 30.165 | K79: 33.935
A80: Leases | F80: 34.043 | G80: 43.654 | H80: 90.448 | I80: 82.32 | J80: 97.851 | K80: 101.858
A81: Other Property, Plant & Equipment | B81: 17.495 | C81: 24.073 | D81: 24.554 | E81: 29.13 | F81: 28.985 | G81: 29.898 | H81: 64.656 | I81: 72.277 | J81: 80.43 | K81: 93.314
A82: Operating Lease Right-of-Use Assets | F82: 28.63 | G82: 33.36 | H82: 72.584 | I82: 62.852 | J82: 67.017 | K82: 69.307
A83: Accumulated Depreciation | B83: 152.863 | C83: 166.642 | D83: 175.712 | E83: 186.676 | F83: 202.389 | G83: 207.387 | H83: 248.116 | I83: 286.821 | J83: 342.173 | K83: 373.494
A84: Buildings | B84: 15.487 | C84: 16.206 | D84: 15.972 | E84: 16.776 | F84: 17.02 | G84: 17.336 | H84: 18.938 | I84: 20.756 | J84: 22.006 | K84: 24.943
A85: Machinery & Equipment | B85: 126.919 | C85: 138.728 | D85: 144.57 | E85: 152.815 | F85: 163.435 | G85: 161.723 | H85: 187.095 | I85: 213.691 | J85: 251.821 | K85: 270.529
A86: Leases | F86: 5.413 | G86: 10.294 | H86: 17.864 | I86: 19.468 | J86: 30.834 | K86: 32.551
A87: Other Property, Plant & Equipment | B87: 10.457 | C87: 11.708 | D87: 15.17 | E87: 17.085 | F87: 16.521 | G87: 18.034 | H87: 24.219 | I87: 32.906 | J87: 37.512 | K87: 45.471
A88: Total Long-Term Investments | B88: 0.219 | C88: 0.027 | D88: 0.027 | E88: 0.027 | F88: 0.027 | G88: 0.026 | H88: 10.742 | I88: 32.182 | J88: 12.917 | K88: 3.589
A89: LT Investment - Affiliate Companies | B89: 0.219 | C89: 0.027 | D89: 0.027 | E89: 0.027 | F89: 0.027 | G89: 0.026 | H89: 0.026 | I89: 0.026 | J89: 0.026 | K89: 0.026
A90: Other Long-Term Investments | B90: 0 | C90: 0 | D90: 0 | E90: 0 | F90: 0 | G90: 0 | H90: 10.716 | I90: 32.156 | J90: 12.891 | K90: 3.563
A91: Intangible Assets | B91: 117.906 | C91: 357.086 | D91: 344.35 | E91: 373.084 | F91: 370.279 | G91: 356.737 | H91: 1943.369 | I91: 1995.063 | J91: 1924.97 | K91: 2028.486
A92: Goodwill | B92: 68.502 | C92: 163.204 | D92: 150.744 | E92: 162.616 | F92: 164.681 | G92: 154.774 | H92: 789.631 | I92: 826.352 | J92: 799.365 | K92: 846.86
A93: Other Intangible Assets | B93: 49.404 | C93: 193.882 | D93: 193.606 | E93: 210.468 | F93: 205.598 | G93: 201.963 | H93: 1153.738 | I93: 1168.711 | J93: 1125.605 | K93: 1181.626
A94: Deferred Tax Assets | B94: 20.198 | C94: 22.989 | D94: 22.171 | E94: 20.958 | F94: 31.647 | G94: 33.08 | H94: 38.23 | I94: 34.459 | J94: 31.813 | K94: 31.604
A95: Other Assets | B95: 0.758 | C95: 0.999 | D95: 5.602 | E95: 2.03 | F95: 2.453 | G95: 2.189 | H95: 4.323 | I95: 48.99 | J95: 2.761 | K95: 2.701
A96: Tangible Other Assets | B96: 0.758 | C96: 0.999 | D96: 5.602 | E96: 2.03 | F96: 2.453 | G96: 2.189 | H96: 4.323 | I96: 48.99 | J96: 2.761 | K96: 2.701
A97: Total Assets | B97: 707.906 | C97: 868.618 | D97: 945.723 | E97: 905.94 | F97: 1063.552 | G97: 1246.446 | H97: 3231.152 | I97: 3408.082 | J97: 3211.439 | K97: 3304.92
A98: Liabilities & Shareholders' Equity
A99: Current
A100: ST Debt & Curr. Portion LT Debt | B100: 2.3 | C100: 26.512 | D100: 23.91 | E100: 20.601 | F100: 4.812 | G100: 4.209 | H100: 100.411 | I100: 120.02 | J100: 109.649 | K100: 47.784
A101: Accounts Payable | B101: 40.775 | C101: 47.674 | D101: 62.331 | E101: 57.286 | F101: 55.733 | G101: 65.485 | H101: 84.773 | I101: 104.204 | J101: 100.706 | K101: 99.52
A102: Income Tax Payable | B102: 6.384 | C102: 10.325 | D102: 5.19 | E102: 9.513 | F102: 10.8 | G102: 29.831 | H102: 6.255 | I102: 13.786 | J102: 9.399 | K102: 18.069
A103: Other Current Liabilities | B103: 32.981 | C103: 47.372 | D103: 49.689 | E103: 51.052 | F103: 51.134 | G103: 60.688 | H103: 106.79 | I103: 103.304 | J103: 100.363 | K103: 109.926
A104: Accrued Payroll | B104: 22.544 | C104: 28.361 | D104: 28.749 | E104: 30.3 | F104: 34.666 | G104: 41.026 | H104: 46.146 | I104: 47.512 | J104: 44.373 | K104: 51.308
A105: Miscellaneous Current Liabilities | B105: 10.437 | C105: 19.011 | D105: 20.94 | E105: 20.752 | F105: 16.468 | G105: 19.662 | H105: 60.644 | I105: 55.792 | J105: 55.99 | K105: 58.618
A106: Total Current Liabilities | B106: 82.44 | C106: 131.883 | D106: 141.12 | E106: 138.452 | F106: 122.479 | G106: 160.213 | H106: 298.229 | I106: 341.314 | J106: 320.117 | K106: 275.299
...

Sheet Restatements
A1: Restated Financial Statements
C3: Historicals
B4: USD: mln | C4: 2015 | D4: 2016 | E4: 2017 | F4: 2018 | G4: 2019 | H4: 2020 | I4: 2021 | J4: 2022 | K4: 2023 | L4: 2024 | XFC4: =XFB4+365 -> 365
B6: Income statement
B8: Revenues from the sale of goods and services | C8: =AFS!B20 -> 499.18 | D8: =AFS!C20 -> 569.31 | E8: =AFS!D20 -> 637.49 | F8: =AFS!E20 -> 669.2 | G8: =AFS!F20 -> 706.32 | H8: =AFS!G20 -> 881.31 | I8: =AFS!H20 -> 1237.65 | J8: =AFS!I20 -> 1361.14 | ... L8: =AFS!K20 -> 1185.43
B9: Growth | C9: n.a. | D9: n.a. | E9: n.a. | F9: n.a. | G9: n.a. | H9: n.a. | I9: n.a. | J9: n.a. | K9: n.a. | L9: n.a.
B10: COGS | C10: =AFS!B24 -> 157.28 | D10: =AFS!C24 -> 180.16 | E10: =AFS!D24 -> 205.59 | F10: =AFS!E24 -> 213.43 | G10: =AFS!F24 -> 217.63 | H10: =AFS!G24 -> 278.4 | I10: =AFS!H24 -> 412.88 | J10: =AFS!I24 -> 460.53 | ... L10: =AFS!K24 -> 403.73
B11: SGA | C11: =AFS!B29-AFS!B136 -> 132.91 | D11: =AFS!C29-AFS!C136 -> 148.79 | E11: =AFS!D29-AFS!D136 -> 163.4 | F11: =AFS!E29-AFS!E136 -> 179.71 | G11: =AFS!F29-AFS!F136 -> 186.95 | H11: =AFS!G29-AFS!G136 -> 193.18 | I11: =AFS!H29-AFS!H136 -> 264.73 | J11: =AFS!I29-AFS!I136 -> 357.18 | ... L11: =AFS!K29-AFS!K136 -> 361.65
B12: Other | C12: =AFS!B37 -> 2.28 | D12: =AFS!C37 -> -0.75 | E12: =AFS!D37 -> 1.33 | F12: =AFS!E37 -> -1.3 | G12: =AFS!F37 -> 3.86 | H12: =AFS!G37 -> 2.97 | I12: =AFS!H37 -> 3.13 | J12: =AFS!I37 -> 6.89 | ... L12: =AFS!K37 -> 6.22
B13: Total operating expenses | C13: =C10+C12+C11 -> 292.47 | D13: =D10+D12+D11 -> 328.2 | E13: =E10+E12+E11 -> 370.32 | F13: =F10+F12+F11 -> 391.84 | G13: =G10+G12+G11 -> 408.44 | H13: =H10+H12+H11 -> 474.55 | I13: =I10+I12+I11 -> 680.74 | J13: =J10+J12+J11 -> 824.6 | ... L13: =L10+L12+L11 -> 771.6
B14: EBITDA | C14: =C8-C13 -> 206.71 | D14: =D8-D13 -> 241.11 | E14: =E8-E13 -> 267.17 | F14: =F8-F13 -> 277.36 | G14: =G8-G13 -> 297.88 | H14: =H8-H13 -> 406.76 | I14: =I8-I13 -> 556.91 | J14: =J8-J13 -> 536.54 | ... L14: =L8-L13 -> 413.83
B15: Margin | C15: =C14/C8 -> 0.41409912 | D15: =D14/D8 -> 0.42351267 | E15: =E14/E8 -> 0.41909677 | F15: =F14/F8 -> 0.41446503 | G15: =G14/G8 -> 0.42173519 | H15: =H14/H8 -> 0.46154021 | I15: =I14/I8 -> 0.44997374 | J15: =J14/J8 -> 0.39418429 | ... L15: =L14/L8 -> 0.34909695
B16: Depreciation | C16: =AFS!B136 -> 50.64 | D16: =AFS!C136 -> 63.18 | E16: =AFS!D136 -> 69.61 | F16: =AFS!E136 -> 67.51 | G16: =AFS!F136 -> 75.42 | H16: =AFS!G136 -> 76.65 | I16: =AFS!H136 -> 115.51 | J16: =AFS!I136 -> 161.22 | ... L16: =AFS!K136 -> 148.79
B17: Net write-downs of fixed assets
B18: EBIT | C18: =C14-C16 -> 156.07 | D18: =D14-D16 -> 177.93 | E18: =E14-E16 -> 197.56 | F18: =F14-F16 -> 209.85 | G18: =G14-G16 -> 222.46 | H18: =H14-H16 -> 330.11 | I18: =I14-I16 -> 441.4 | J18: =J14-J16 -> 375.32 | ... L18: =L14-L16 -> 265.04
B19: Interest income | C19: =AFS!B48 -> -4.02 | D19: =AFS!C48 -> -2.38 | E19: =AFS!D48 -> -3.83 | F19: =AFS!E48 -> -1.14 | G19: =AFS!F48 -> -0.76 | H19: =AFS!G48 -> -1.91 | I19: =AFS!H48 -> 0.89 | J19: =AFS!I48 -> 1.37 | ... L19: =AFS!K48 -> 3.57
B20: Interest expenses | C20: =AFS!B45 -> -0.59 | D20: =AFS!C45 -> 1.38 | E20: =AFS!D45 -> 2.6 | F20: =AFS!E45 -> 2.49 | G20: =AFS!F45 -> 0.68 | H20: =AFS!G45 -> 0.94 | I20: =AFS!H45 -> 21.06 | J20: =AFS!I45 -> 30.72 | ... L20: =AFS!K45 -> 19.45
B21: Net Interest expenses | C21: =C19-C20 -> -3.43 | D21: =D19-D20 -> -3.76 | E21: =E19-E20 -> -6.43 | F21: =F19-F20 -> -3.63 | G21: =G19-G20 -> -1.44 | H21: =H19-H20 -> -2.85 | I21: =I19-I20 -> -20.17 | J21: =J19-J20 -> -29.35 | ... L21: =L19-L20 -> -15.88
B22: Gross Operating Income from Continuing Operations | C22: =C18+C21+AFS!B51 -> 152.21 | D22: =D18+D21+AFS!C51 -> 173.61 | E22: =E18+E21+AFS!D51 -> 190.73 | F22: =F18+F21+AFS!E51 -> 206.08 | G22: =G18+G21+AFS!F51 -> 220.91 | H22: =H18+H21+AFS!G51 -> 327.26 | I22: =I18+I21+AFS!H51 -> 421.23 | J22: =J18+J21+AFS!I51 -> 345.97 | ... L22: =L18+L21+AFS!K51 -> 249.16
B23: Non-Recurring | C23: =AFS!B54 -> -2.11 | D23: =AFS!C54 -> -5.43 | E23: =AFS!D54 -> -12.02 | F23: =AFS!E54 -> -1.71 | G23: =AFS!F54 -> -4.61 | H23: =AFS!G54 -> -5.88 | I23: =AFS!H54 -> -21.9 | J23: =AFS!I54 -> -20.02 | ... L23: =AFS!K54 -> -6.72
B24: EBT | C24: =C22+C23 -> 150.1 | D24: =D22+D23 -> 168.18 | E24: =E22+E23 -> 178.71 | F24: =F22+F23 -> 204.37 | G24: =G22+G23 -> 216.3 | H24: =H22+H23 -> 321.38 | I24: =I22+I23 -> 399.33 | J24: =J22+J23 -> 325.95 | ... L24: =L22+L23 -> 242.44
B25: Margin | C25: =C24/C8 -> 0.30069314 | D25: =D24/D8 -> 0.29541023 | E25: =E24/E8 -> 0.28033381 | F25: =F24/F8 -> 0.3053945 | G25: =G24/G8 -> 0.30623513 | H25: =H24/H8 -> 0.3646617 | I25: =I24/I8 -> 0.3226518 | J25: =J24/J8 -> 0.23946839 | ... L25: =L24/L8 -> 0.2045165
B26: Income taxes | C26: =-AFS!B64 -> -49.55 | D26: =-AFS!C64 -> -55.58 | E26: =-AFS!D64 -> -38.83 | F26: =-AFS!E64 -> -46.24 | G26: =-AFS!F64 -> -40.55 | H26: =-AFS!G64 -> -73.08 | I26: =-AFS!H64 -> -88.6 | J26: =-AFS!I64 -> -85.83 | ... L26: =-AFS!K64 -> -55.39
B27: Net Income | C27: =C24+C26 -> 100.55 | D27: =D24+D26 -> 112.6 | E27: =E24+E26 -> 139.88 | F27: =F24+F26 -> 158.13 | G27: =G24+G26 -> 175.75 | H27: =H24+H26 -> 248.3 | I27: =I24+I26 -> 310.73 | J27: =J24+J26 -> 240.12 | ... L27: =L24+L26 -> 187.05
B28: Minorities | C28: =AFS!B73 -> 0.13 | D28: =AFS!C73 -> 0.24 | E28: =AFS!D73 -> 0 | F28: =AFS!E73 -> 0 | G28: =AFS!F73 -> 0 | H28: =AFS!G73 -> 0.43 | I28: =AFS!H73 -> -0.24 | J28: =AFS!I73 -> -0.8 | ... L28: =AFS!K73 -> -1.05
B29: Group result of the year | C29: =C27-C28 -> 100.42 | D29: =D27-D28 -> 112.36 | E29: =E27-E28 -> 139.88 | F29: =F27-F28 -> 158.13 | G29: =G27-G28 -> 175.75 | H29: =H27-H28 -> 247.87 | I29: =I27-I28 -> 310.97 | J29: =J27-J28 -> 240.92 | ... L29: =L27-L28 -> 188.1
B30: Margin | C30: =C29/C8 -> 0.20116992 | D30: =D29/D8 -> 0.19736172 | E30: =E29/E8 -> 0.21942305 | F30: =F29/F8 -> 0.23629707 | G30: =G29/G8 -> 0.2488249 | H30: =H29/H8 -> 0.28125177 | I30: =I29/I8 -> 0.25125843 | J30: =J29/J8 -> 0.17699869 | ... L30: =L29/L8 -> 0.1586766
B31: Check
B32: Dividend distribution | C32: =AFS!B118+AFS!B120 -> 0.6 | D32: =AFS!C118+AFS!C120 -> 0.65 | E32: =AFS!D118+AFS!D120 -> 0.8 | F32: =AFS!E118+AFS!E120 -> 2.65 | G32: =AFS!F118+AFS!F120 -> 0.9 | H32: =AFS!G118+AFS!G120 -> 0.95 | I32: =AFS!H118+AFS!H120 -> 1 | J32: =AFS!I118+AFS!I120 -> 1.05 | ... L32: =AFS!K118+AFS!K120 -> 1.15
B33: Retained portion | C33: =C27-C28 -> 100.42 | D33: =D27-D28 -> 112.36 | E33: =E27-E28 -> 139.88 | F33: =F27-F28 -> 158.13 | G33: =G27-G28 -> 175.75 | H33: =H27-H28 -> 247.87 | I33: =I27-I28 -> 310.97 | J33: =J27-J28 -> 240.92 | ... L33: =L27-L28 -> 188.1
B36: Income statement
B38: Sales | C38: ='AFS3'!B3 -> 499.181 | D38: ='AFS3'!C3 -> 569.312 | E38: ='AFS3'!D3 -> 637.487 | F38: ='AFS3'!E3 -> 669.197 | G38: ='AFS3'!F3 -> 706.319 | H38: ='AFS3'!G3 -> 881.305 | I38: ='AFS3'!H3 -> 1237.654 | J38: ='AFS3'!I3 -> 1361.138 | ... L38: ='AFS3'!K3 -> 1185.427
B39: Growth | C39: n/a | D39: =D38/C38-1 -> 0.14049213 | E39: =E38/D38-1 -> 0.1197498 | F39: =F38/E38-1 -> 0.049742191 | G39: =G38/F38-1 -> 0.055472454 | H39: =H38/G38-1 -> 0.24774358 | I39: =I38/H38-1 -> 0.40434242 | J39: =J38/I38-1 -> 0.099772634 | K39: =K38/J38-1 -> -0.15643381 | L39: =L38/K38-1 -> 0.03241306
B41: (Cost of goods sold) | C41: =-'AFS3'!B5 -> -132.69 | D41: =-'AFS3'!C5 -> -154.022 | E41: =-'AFS3'!D5 -> -179.243 | F41: =-'AFS3'!E5 -> -189.581 | G41: =-'AFS3'!F5 -> -191.387 | H41: =-'AFS3'!G5 -> -240.119 | I41: =-'AFS3'!H5 -> -372.181 | J41: =-'AFS3'!I5 -> -415.288 | ... L41: =-'AFS3'!K5 -> -348.868
B42: (Selling, general & adminsitrative expenses) | C42: =-('AFS3'!B13+'AFS3'!B10) -> -177.142 | D42: =-('AFS3'!C13+'AFS3'!C10) -> -194.904 | E42: =-('AFS3'!D13+'AFS3'!D10) -> -214.205 | F42: =-('AFS3'!E13+'AFS3'!E10) -> -225.689 | G42: =-('AFS3'!F13+'AFS3'!F10) -> -235.833 | H42: =-('AFS3'!G13+'AFS3'!G10) -> -249.295 | I42: =-('AFS3'!H13+'AFS3'!H10) -> -337.534 | J42: =-('AFS3'!I13+'AFS3'!I10) -> -444.29 | ... L42: =-('AFS3'!K13+'AFS3'!K10) -> -429.866
B43: EBITDA | C43: =SUM(C38,C41,C42) -> 189.349 | D43: =SUM(D38,D41,D42) -> 220.386 | E43: =SUM(E38,E41,E42) -> 244.039 | F43: =SUM(F38,F41,F42) -> 253.927 | G43: =SUM(G38,G41,G42) -> 279.099 | H43: =SUM(H38,H41,H42) -> 391.891 | I43: =SUM(I38,I41,I42) -> 527.939 | J43: =SUM(J38,J41,J42) -> 501.56 | ... L43: =SUM(L38,L41,L42) -> 406.693
B44: Margin | C44: =C43/C38 -> 0.37931933 | D44: =D43/D38 -> 0.38710935 | E44: =E43/E38 -> 0.38281408 | F44: =F43/F38 -> 0.3794503 | G44: =G43/G38 -> 0.39514582 | H44: =H43/H38 -> 0.44467125 | I44: =I43/I38 -> 0.42656429 | J44: =J43/J38 -> 0.36848578 | ... L44: =L43/L38 -> 0.34307722
B46: (Depreciation) | C46: =-'AFS3'!B7 -> -24.875 | D46: =-'AFS3'!C7 -> -27.141 | E46: =-'AFS3'!D7 -> -29.666 | F46: =-'AFS3'!E7 -> -28.531 | G46: =-'AFS3'!F7 -> -35.132 | H46: =-'AFS3'!G7 -> -33.558 | I46: =-'AFS3'!H7 -> -47.131 | J46: =-'AFS3'!I7 -> -60.404 | ... L46: =-'AFS3'!K7 -> -53.871
B47: (Amortization) | C47: =-'AFS3'!B8 -> -8.109 | D47: =-'AFS3'!C8 -> -17.566 | E47: =-'AFS3'!D8 -> -16.185 | F47: =-'AFS3'!E8 -> -16.844 | G47: =-'AFS3'!F8 -> -17.644 | H47: =-'AFS3'!G8 -> -25.255 | I47: =-'AFS3'!H8 -> -36.275 | J47: =-'AFS3'!I8 -> -58.94 | ... L47: =-'AFS3'!K8 -> -75.17
B48: EBIT | C48: =SUM(C43,C46,C47) -> 156.365 | D48: =SUM(D43,D46,D47) -> 175.679 | E48: =SUM(E43,E46,E47) -> 198.188 | F48: =SUM(F43,F46,F47) -> 208.552 | G48: =SUM(G43,G46,G47) -> 226.323 | H48: =SUM(H43,H46,H47) -> 333.078 | I48: =SUM(I43,I46,I47) -> 444.533 | J48: =SUM(J43,J46,J47) -> 382.216 | ... L48: =SUM(L43,L46,L47) -> 277.652
B49: Margin | C49: =C48/C38 -> 0.31324309 | D49: =D48/D38 -> 0.30858123 | E49: =E48/E38 -> 0.31088948 | F49: =F48/F38 -> 0.31164515 | G49: =G48/G38 -> 0.32042604 | H49: =H48/H38 -> 0.37793726 | I49: =I48/I38 -> 0.35917389 | J49: =J48/J38 -> 0.28080621 | ... L49: =L48/L38 -> 0.23422109
B51: Other Interest Income | C51: ='AFS3'!B17 -> -3.22 | D51: ='AFS3'!C17 -> 0.532 | E51: ='AFS3'!D17 -> -4.146 | F51: ='AFS3'!E17 -> 0.468 | G51: ='AFS3'!F17 -> -4.175 | H51: ='AFS3'!G17 -> -4.396 | I51: ='AFS3'!H17 -> -1.766 | J51: ='AFS3'!I17 -> -7.432 | ... L51: ='AFS3'!K17 -> -14.097
B52: Interest income | C52: =('AFS3'!B16) -> 1.778 | D52: =('AFS3'!C16) -> 1.071 | E52: =-(-'AFS3'!D16) -> 1.223 | F52: =-(-'AFS3'!E16) -> 1.515 | G52: =-(-'AFS3'!F16) -> 2.833 | H52: =-(-'AFS3'!G16) -> 2.005 | I52: =-(-'AFS3'!H16) -> 0.284 | J52: =-(-'AFS3'!I16) -> 5.608 | K52: =-(-'AFS3'!J16) -> 13.931 | L52: =-(-'AFS3'!K16) -> 12.924
B53: Interest Expense | C53: =-'AFS3'!B18 -> -2.282 | D53: =-'AFS3'!C18 -> -3.105 | E53: =-'AFS3'!D18 -> -4.133 | F53: =-'AFS3'!E18 -> -4.318 | G53: =-'AFS3'!F18 -> -3.964 | H53: =-'AFS3'!G18 -> -3.429 | I53: =-'AFS3'!H18 -> -21.814 | J53: =-'AFS3'!I18 -> -34.427 | ... L53: =-'AFS3'!K18 -> -27.64
B54: Income from Associates | C54: ='AFS3'!B34 -> -0.431 | D54: ='AFS3'!C34 -> -0.555 | E54: ='AFS3'!D34 -> -0.404 | F54: ='AFS3'!E34 -> -0.143 | G54: ='AFS3'!F34 -> -0.115 | H54: ='AFS3'!G34 -> 0 | I54: ='AFS3'!H34 -> 0 | J54: ='AFS3'!I34 -> 0 | ... L54: ='AFS3'!K34 -> 0
B55: Unusual Interest Expense | C55: =-'AFS3'!B20 -> -2.108 | D55: =-'AFS3'!C20 -> -5.426 | E55: =-'AFS3'!D20 -> -12.022 | F55: =-'AFS3'!E20 -> -1.709 | G55: =-'AFS3'!F20 -> -4.615 | H55: =-'AFS3'!G20 -> -5.885 | I55: =-'AFS3'!H20 -> -21.902 | J55: =-'AFS3'!I20 -> -20.025 | ... L55: =-'AFS3'!K20 -> -6.391
B56: (Interest expenses)
B57: Income from associates
B58: EBT | C58: =SUM(C48,C51:C55) -> 150.102 | D58: =SUM(D48,D51:D55) -> 168.196 | E58: =SUM(E48,E51:E55) -> 178.706 | F58: =SUM(F48,F51:F55) -> 204.365 | G58: =SUM(G48,G51:G55) -> 216.287 | H58: =SUM(H48,H51:H55) -> 321.373 | I58: =SUM(I48,I51:I55) -> 399.335 | J58: =SUM(J48,J51:J55) -> 325.94 | ... L58: =SUM(L48,L51:L55) -> 242.448
B60: (Income taxes) | C60: =-'AFS3'!B31 -> -49.554 | D60: =-'AFS3'!C31 -> -55.578 | E60: =-'AFS3'!D31 -> -38.828 | F60: =-'AFS3'!E31 -> -46.235 | G60: =-'AFS3'!F31 -> -40.552 | H60: =-'AFS3'!G31 -> -73.077 | I60: =-'AFS3'!H31 -> -88.603 | J60: =-'AFS3'!I31 -> -85.83 | ... L60: =-'AFS3'!K31 -> -55.391
B61: (Minority Interest) | C61: =-'AFS3'!B36 -> -0.128 | D61: =-'AFS3'!C36 -> -0.235 | E61: =-'AFS3'!D36 -> 0 | F61: =-'AFS3'!E36 -> -0.002 | G61: =-'AFS3'!F36 -> 0 | H61: =-'AFS3'!G36 -> -0.425 | I61: =-'AFS3'!H36 -> 0.236 | J61: =-'AFS3'!I36 -> 0.797 | ... L61: =-'AFS3'!K36 -> 1.048
B62: Net income | C62: =SUM(C58:C61) -> 100.42 | D62: =SUM(D58:D61) -> 112.383 | E62: =SUM(E58:E61) -> 139.878 | F62: =SUM(F58:F61) -> 158.128 | G62: =SUM(G58:G61) -> 175.735 | H62: =SUM(H58:H61) -> 247.871 | I62: =SUM(I58:I61) -> 310.968 | J62: =SUM(J58:J61) -> 240.907 | ... L62: =SUM(L58:L61) -> 188.105
B63: Margin | C63: =C62/C38 -> 0.20116952 | D63: =D62/D38 -> 0.19740142 | E63: =E62/E38 -> 0.21942095 | F63: =F62/F38 -> 0.23629514 | G63: =G62/G38 -> 0.24880401 | H63: =H62/H38 -> 0.2812545 | I63: =I62/I38 -> 0.25125601 | J63: =J62/J38 -> 0.1769894 | ... L63: =L62/L38 -> 0.15868122
B65: Dividend distribution | C65: ='AFS3'!B48 -> 0.65 | D65: ='AFS3'!C48 -> 0.8 | E65: ='AFS3'!D48 -> 0.85 | F65: ='AFS3'!E48 -> 0.9 | G65: ='AFS3'!F48 -> 0.95 | H65: ='AFS3'!G48 -> 1 | I65: ='AFS3'!H48 -> 1.05 | J65: ='AFS3'!I48 -> 1.1 | ... L65: ='AFS3'!K48 -> 1.2
B66: Retained portion | C66: =C65/C62 -> 0.0064728142 | D66: =D65/D62 -> 0.0071185144 | E66: =E65/E62 -> 0.006076724 | F66: =F65/F62 -> 0.0056915916 | G66: =G65/G62 -> 0.0054058668 | H66: =H65/H62 -> 0.0040343566 | I66: =I65/I62 -> 0.0033765532 | J66: =J65/J62 -> 0.0045660774 | ... L66: =L65/L62 -> 0.0063794158
B68: Balance sheet
B70: Trade receivables | C70: ='AFS3'!B62+'AFS3'!B65 -> 105.609 | D70: ='AFS3'!C62+'AFS3'!C65 -> 120.261 | E70: ='AFS3'!D62+'AFS3'!D65 -> 147.24 | F70: ='AFS3'!E62+'AFS3'!E65 -> 136.244 | G70: ='AFS3'!F62+'AFS3'!F65 -> 140.5 | H70: ='AFS3'!G62+'AFS3'!G65 -> 166.687 | I70: ='AFS3'!H62+'AFS3'!H65 -> 226.249 | J70: ='AFS3'!I62+'AFS3'!I65 -> 241.353 | ... L70: ='AFS3'!K62+'AFS3'!K65 -> 204.111
B71: (Trade payables) | C71: =-'AFS3'!B101 -> -40.775 | D71: =-'AFS3'!C101 -> -47.674 | E71: =-'AFS3'!D101 -> -62.331 | F71: =-'AFS3'!E101 -> -57.286 | G71: =-'AFS3'!F101 -> -55.733 | H71: =-'AFS3'!G101 -> -65.485 | I71: =-'AFS3'!H101 -> -84.773 | J71: =-'AFS3'!I101 -> -104.204 | ... L71: =-'AFS3'!K101 -> -99.52
B72: Inventory | C72: ='AFS3'!B66 -> 106.193 | D72: ='AFS3'!C66 -> 128.87 | E72: ='AFS3'!D66 -> 142.802 | F72: ='AFS3'!E66 -> 160.396 | G72: ='AFS3'!F66 -> 171.127 | H72: ='AFS3'!G66 -> 191.234 | I72: ='AFS3'!H66 -> 298.049 | J72: ='AFS3'!I66 -> 306.503 | ... L72: ='AFS3'!K66 -> 344.043
B73: Other current assets and liabilities | C73: ='AFS3'!B70-'AFS3'!B103 -> -20.808 | D73: ='AFS3'!C70-'AFS3'!C103 -> -31.588 | E73: ='AFS3'!D70-'AFS3'!D103 -> -31.804 | F73: ='AFS3'!E70-'AFS3'!E103 -> -29.357 | G73: ='AFS3'!F70-'AFS3'!F103 -> -34.14 | H73: ='AFS3'!G70-'AFS3'!G103 -> -44.699 | I73: ='AFS3'!H70-'AFS3'!H103 -> -75.817 | J73: ='AFS3'!I70-'AFS3'!I103 -> -35.438 | ... L73: ='AFS3'!K70-'AFS3'!K103 -> -84.167
B74: Deferred Tax Assets | C74: =('AFS3'!B94)-('AFS3'!B112) -> 18.149 | D74: =('AFS3'!C94)-('AFS3'!C112) -> 21.588 | E74: =('AFS3'!D94)-('AFS3'!D112) -> 20.272 | F74: =('AFS3'!E94)-('AFS3'!E112) -> 15.908 | G74: =('AFS3'!F94)-('AFS3'!F112) -> 24.512 | H74: =('AFS3'!G94)-('AFS3'!G112) -> 23.014 | I74: =('AFS3'!H94)-('AFS3'!H112) -> -147.107 | J74: =('AFS3'!I94)-('AFS3'!I112) -> -194.851 | ... L74: =('AFS3'!K94)-('AFS3'!K112) -> -167.969
B75: (Tax Payables) | C75: =-'AFS3'!B102 -> -6.384 | D75: =-'AFS3'!C102 -> -10.325 | E75: =-'AFS3'!D102 -> -5.19 | F75: =-'AFS3'!E102 -> -9.513 | G75: =-'AFS3'!F102 -> -10.8 | H75: =-'AFS3'!G102 -> -29.831 | I75: =-'AFS3'!H102 -> -6.255 | J75: =-'AFS3'!I102 -> -13.786 | ... L75: =-'AFS3'!K102 -> -18.069
B76: (long term provisions) | C76: =-'AFS3'!B111 -> -35.021 | D76: =-'AFS3'!C111 -> -41.584 | E76: =-'AFS3'!D111 -> -32.532 | F76: =-'AFS3'!E111 -> -32.659 | G76: =-'AFS3'!F111 -> -36.263 | H76: =-'AFS3'!G111 -> -41.242 | I76: =-'AFS3'!H111 -> -40.917 | J76: =-'AFS3'!I111 -> -62.753 | ... L76: =-'AFS3'!K111 -> -54.663
B77: Noncash working capital | C77: =SUM(C70:C76) -> 126.963 | D77: =SUM(D70:D76) -> 139.548 | E77: =SUM(E70:E76) -> 178.457 | F77: =SUM(F70:F76) -> 183.733 | G77: =SUM(G70:G76) -> 199.203 | H77: =SUM(H70:H76) -> 199.678 | I77: =SUM(I70:I76) -> 169.429 | J77: =SUM(J70:J76) -> 136.824 | ... L77: =SUM(L70:L76) -> 123.766
B79: Tangible | C79: ='AFS3'!B74 -> 74.493 | D79: ='AFS3'!C74 -> 92.134 | E79: ='AFS3'!D74 -> 92.332 | F79: ='AFS3'!E74 -> 94.981 | G79: ='AFS3'!F74 -> 128.385 | H79: ='AFS3'!G74 -> 140.497 | I79: ='AFS3'!H74 -> 276.197 | J79: ='AFS3'!I74 -> 268.448 | ... L79: ='AFS3'!K74 -> 271.359
B80: Goodwill | C80: ='AFS3'!B92 -> 68.502 | D80: ='AFS3'!C92 -> 163.204 | E80: ='AFS3'!D92 -> 150.744 | F80: ='AFS3'!E92 -> 162.616 | G80: ='AFS3'!F92 -> 164.681 | H80: ='AFS3'!G92 -> 154.774 | I80: ='AFS3'!H92 -> 789.631 | J80: ='AFS3'!I92 -> 826.352 | ... L80: ='AFS3'!K92 -> 846.86
B81: Other Intagible Assets | C81: ='AFS3'!B93 -> 49.404 | D81: ='AFS3'!C93 -> 193.882 | E81: ='AFS3'!D93 -> 193.606 | F81: ='AFS3'!E93 -> 210.468 | G81: ='AFS3'!F93 -> 205.598 | H81: ='AFS3'!G93 -> 201.963 | I81: ='AFS3'!H93 -> 1153.738 | J81: ='AFS3'!I93 -> 1168.711 | ... L81: ='AFS3'!K93 -> 1181.626
B82: Fixed assets | C82: =SUM(C79:C81) -> 192.399 | D82: =SUM(D79:D81) -> 449.22 | E82: =SUM(E79:E81) -> 436.682 | F82: =SUM(F79:F81) -> 468.065 | G82: =SUM(G79:G81) -> 498.664 | H82: =SUM(H79:H81) -> 497.234 | I82: =SUM(I79:I81) -> 2219.566 | J82: =SUM(J79:J81) -> 2263.511 | ... L82: =SUM(L79:L81) -> 2299.845
B84: Core capital employed | C84: =C77+C82 -> 319.362 | D84: =D77+D82 -> 588.768 | E84: =E77+E82 -> 615.139 | F84: =F77+F82 -> 651.798 | G84: =G77+G82 -> 697.867 | H84: =H77+H82 -> 696.912 | I84: =I77+I82 -> 2388.995 | J84: =J77+J82 -> 2400.335 | ... L84: =L77+L82 -> 2423.611
B86: Long-Term Investments | C86: ='AFS3'!B88 -> 0.219 | D86: ='AFS3'!C88 -> 0.027 | E86: ='AFS3'!D88 -> 0.027 | F86: ='AFS3'!E88 -> 0.027 | G86: ='AFS3'!F88 -> 0.027 | H86: ='AFS3'!G88 -> 0.026 | I86: ='AFS3'!H88 -> 10.742 | J86: ='AFS3'!I88 -> 32.182 | ... L86: ='AFS3'!K88 -> 3.589
B87: (Other LT Liabilities) | C87: =-'AFS3'!B113 -> -1.238 | D87: =-'AFS3'!C113 -> -6.477 | E87: =-'AFS3'!D113 -> -28.115 | F87: =-'AFS3'!E113 -> -24.963 | G87: =-'AFS3'!F113 -> -24.586 | H87: =-'AFS3'!G113 -> -48.155 | I87: =-'AFS3'!H113 -> -43.983 | J87: =-'AFS3'!I113 -> -22.99 | ... L87: =-'AFS3'!K113 -> -9.582
B88: Tangible Other assets | C88: ='AFS3'!B96 -> 0.758 | D88: ='AFS3'!C96 -> 0.999 | E88: ='AFS3'!D96 -> 5.602 | F88: ='AFS3'!E96 -> 2.03 | G88: ='AFS3'!F96 -> 2.453 | H88: ='AFS3'!G96 -> 2.189 | I88: ='AFS3'!H96 -> 4.323 | J88: ='AFS3'!I96 -> 48.99 | ... L88: ='AFS3'!K96 -> 2.701
B89: Surplus and other liabilities | C89: =SUM(C86:C88) -> -0.261 | D89: =SUM(D86:D88) -> -5.451 | E89: =SUM(E86:E88) -> -22.486 | F89: =SUM(F86:F88) -> -22.906 | G89: =SUM(G86:G88) -> -22.106 | H89: =SUM(H86:H88) -> -45.94 | I89: =SUM(I86:I88) -> -28.918 | J89: =SUM(J86:J88) -> 58.182 | ... L89: =SUM(L86:L88) -> -3.292
B91: Net capital employed | C91: =C84+C89 -> 319.101 | D91: =D84+D89 -> 583.317 | E91: =E84+E89 -> 592.653 | F91: =F84+F89 -> 628.892 | G91: =G84+G89 -> 675.761 | H91: =H84+H89 -> 650.972 | I91: =I84+I89 -> 2360.077 | J91: =J84+J89 -> 2458.517 | ... L91: =L84+L89 -> 2420.319
B93: ST financial debt | C93: ='AFS3'!B100 -> 2.3 | D93: ='AFS3'!C100 -> 26.512 | E93: ='AFS3'!D100 -> 23.91 | F93: ='AFS3'!E100 -> 20.601 | G93: ='AFS3'!F100 -> 4.812 | H93: ='AFS3'!G100 -> 4.209 | I93: ='AFS3'!H100 -> 100.411 | J93: ='AFS3'!I100 -> 120.02 | ... L93: ='AFS3'!K100 -> 47.784
B94: LT financial debt | C94: ='AFS3'!B108 -> 0 | D94: ='AFS3'!C108 -> 23.888 | E94: ='AFS3'!D108 -> 0.102 | F94: ='AFS3'!E108 -> 0.081 | G94: ='AFS3'!F108 -> 24.466 | H94: ='AFS3'!G108 -> 30.451 | I94: ='AFS3'!H108 -> 1294.747 | J94: ='AFS3'!I108 -> 1231.965 | ... L94: ='AFS3'!K108 -> 966.781
B95: Gross financial debt | C95: =C93+C94 -> 2.3 | D95: =D93+D94 -> 50.4 | E95: =E93+E94 -> 24.012 | F95: =F93+F94 -> 20.682 | G95: =G93+G94 -> 29.278 | H95: =H93+H94 -> 34.66 | I95: =I93+I94 -> 1395.158 | J95: =J93+J94 -> 1351.985 | ... L95: =L93+L94 -> 1014.565
B96: Excess cash & equivalents (Cash & Short-Term Investments) | C96: ='AFS3'!B58 -> 270.357 | D96: ='AFS3'!C58 -> 130.468 | E96: ='AFS3'!D58 -> 173.314 | F96: ='AFS3'!E58 -> 96.525 | G96: ='AFS3'!F58 -> 202.14 | H96: ='AFS3'!G58 -> 340.007 | I96: ='AFS3'!H58 -> 403.02 | J96: ='AFS3'!I58 -> 413.218 | ... L96: ='AFS3'!K58 -> 393.268
B97: Net financial position | C97: =C95-C96 -> -268.057 | D97: =D95-D96 -> -80.068 | E97: =E95-E96 -> -149.302 | F97: =F95-F96 -> -75.843 | G97: =G95-G96 -> -172.862 | H97: =H95-H96 -> -305.347 | I97: =I95-I96 -> 992.138 | J97: =J95-J96 -> 938.767 | ... L97: =L95-L96 -> 621.297
B99: Share Capital | C99: ='AFS3'!B117-'AFS3'!B120 -> 106.202 | D99: ='AFS3'!C117-'AFS3'!C120 -> 118.095 | E99: ='AFS3'!D117-'AFS3'!D120 -> 76.601 | F99: ='AFS3'!E117-'AFS3'!E120 -> 92.773 | G99: ='AFS3'!F117-'AFS3'!F120 -> 101.29 | H99: ='AFS3'!G117-'AFS3'!G120 -> 54.995 | I99: ='AFS3'!H117-'AFS3'!H120 -> 200.999 | J99: ='AFS3'!I117-'AFS3'!I120 -> 225.25 | ... L99: ='AFS3'!K117-'AFS3'!K120 -> 221.031
B100: Retained Earnings | C100: ='AFS3'!B120 -> 480.612 | D100: ='AFS3'!C120 -> 544.722 | E100: ='AFS3'!D120 -> 664.816 | F100: ='AFS3'!E120 -> 611.96 | G100: ='AFS3'!F120 -> 747.333 | H100: ='AFS3'!G120 -> 899.683 | I100: ='AFS3'!H120 -> 1165.378 | J100: ='AFS3'!I120 -> 1293.739 | ... L100: ='AFS3'!K120 -> 1579.887
B102: Total Shareholders Equity | C102: ='AFS3'!B117 -> 586.814 | D102: ='AFS3'!C117 -> 662.817 | E102: ='AFS3'!D117 -> 741.417 | F102: ='AFS3'!E117 -> 704.733 | G102: ='AFS3'!F117 -> 848.623 | H102: ='AFS3'!G117 -> 954.678 | I102: ='AFS3'!H117 -> 1366.377 | J102: ='AFS3'!I117 -> 1518.989 | ... L102: ='AFS3'!K117 -> 1800.918
B103: Minority interests | C103: ='AFS3'!B127 -> 0.344 | D103: ='AFS3'!C127 -> 0.568 | E103: ='AFS3'!D127 -> 0.538 | F103: ='AFS3'!E127 -> 0.002 | G103: ='AFS3'!F127 -> 0 | H103: ='AFS3'!G127 -> 1.641 | I103: ='AFS3'!H127 -> 1.562 | J103: ='AFS3'!I127 -> 0.761 | ... L103: ='AFS3'!K127 -> -1.896
B104: Total equity | C104: ='AFS3'!B126+C103 -> 587.158 | D104: ='AFS3'!C126+D103 -> 663.385 | E104: ='AFS3'!D126+E103 -> 741.955 | F104: ='AFS3'!E126+F103 -> 704.735 | G104: ='AFS3'!F126+G103 -> 848.623 | H104: ='AFS3'!G126+H103 -> 956.319 | I104: ='AFS3'!H126+I103 -> 1367.939 | J104: ='AFS3'!I126+J103 -> 1519.75 | ... L104: ='AFS3'!K126+L103 -> 1799.022
B106: Total funds invested | C106: =C104+C97 -> 319.101 | D106: =D104+D97 -> 583.317 | E106: =E104+E97 -> 592.653 | F106: =F104+F97 -> 628.892 | G106: =G104+G97 -> 675.761 | H106: =H104+H97 -> 650.972 | I106: =I104+I97 -> 2360.077 | J106: =J104+J97 -> 2458.517 | ... L106: =L104+L97 -> 2420.319
B107: Check | C107: =C91-C106 -> 0 | D107: =D91-D106 -> 0 | E107: =E91-E106 -> 0 | F107: =F91-F106 -> 0 | G107: =G91-G106 -> 0 | H107: =H91-H106 -> 0 | I107: =I91-I106 -> 0 | J107: =J91-J106 -> 0 | ... L107: =L91-L106 -> 0
B110: Free Cash flows
B112: EBIT | C112: =C18 -> 156.07 | D112: =D18 -> 177.93 | E112: =E18 -> 197.56 | F112: =F18 -> 209.85 | G112: =G18 -> 222.46 | H112: =H18 -> 330.11 | I112: =I18 -> 441.4 | J112: =J18 -> 375.32 | ... L112: =L18 -> 265.04
B113: (Operational taxes) | C113: =-SUM(Assumptions!F47:F48)*C112 -> -43.54353 | D113: =-SUM(Assumptions!G47:G48)*D112 -> -49.64247 | E113: =-SUM(Assumptions!H47:H48)*E112 -> -55.11924 | F113: =-SUM(Assumptions!I47:I48)*F112 -> -58.54815 | G113: =-SUM(Assumptions!J47:J48)*G112 -> -62.06634 | H113: =-SUM(Assumptions!K47:K48)*H112 -> -92.10069 | I113: =-SUM(Assumptions!L47:L48)*I112 -> -123.1506 | J113: =-SUM(Assumptions!M47:M48)*J112 -> -104.71428 | ... L113: =-SUM(Assumptions!O47:O48)*L112 -> -73.94616
B114: NOPAT | C114: =SUM(C112:C113) -> 112.52647 | D114: =SUM(D112:D113) -> 128.28753 | E114: =SUM(E112:E113) -> 142.44076 | F114: =SUM(F112:F113) -> 151.30185 | G114: =SUM(G112:G113) -> 160.39366 | H114: =SUM(H112:H113) -> 238.00931 | I114: =SUM(I112:I113) -> 318.2494 | J114: =SUM(J112:J113) -> 270.60572 | ... L114: =SUM(L112:L113) -> 191.09384
B115: Depreciation | C115: =-C46 -> 24.875 | D115: =-D46 -> 27.141 | E115: =-E46 -> 29.666 | F115: =-F46 -> 28.531 | G115: =-G46 -> 35.132 | H115: =-H46 -> 33.558 | I115: =-I46 -> 47.131 | J115: =-J46 -> 60.404 | ... L115: =-L46 -> 53.871
B116: Amortization | C116: =-C47 -> 8.109 | D116: =-D47 -> 17.566 | E116: =-E47 -> 16.185 | F116: =-F47 -> 16.844 | G116: =-G47 -> 17.644 | H116: =-H47 -> 25.255 | I116: =-I47 -> 36.275 | J116: =-J47 -> 58.94 | ... L116: =-L47 -> 75.17
B117: Gross cash flows | C117: =SUM(C114:C116) -> 145.51047 | D117: =SUM(D114:D116) -> 172.99453 | E117: =SUM(E114:E116) -> 188.29176 | F117: =SUM(F114:F116) -> 196.67685 | G117: =SUM(G114:G116) -> 213.16966 | H117: =SUM(H114:H116) -> 296.82231 | I117: =SUM(I114:I116) -> 401.6554 | J117: =SUM(J114:J116) -> 389.94972 | ... L117: =SUM(L114:L116) -> 320.13484
B119: (Increase) and decrease in noncash WC | D119: =-(D77-C77) -> -12.585 | E119: =-(E77-D77) -> -38.909 | F119: =-(F77-E77) -> -5.276 | G119: =-(G77-F77) -> -15.47 | H119: =-(H77-G77) -> -0.475 | I119: =-(I77-H77) -> 30.249 | J119: =-(J77-I77) -> 32.605 | K119: =-(K77-J77) -> -4.214 | L119: =-(L77-K77) -> 17.272
B120: - Tangible CAPEX | D120: =-(D79-C79)-D115 -> -44.782 | E120: =-(E79-D79)-E115 -> -29.864 | F120: =-(F79-E79)-F115 -> -31.18 | G120: =-(G79-F79)-G115 -> -68.536 | H120: =-(H79-G79)-H115 -> -45.67 | I120: =-(I79-H79)-I115 -> -182.831 | J120: =-(J79-I79)-J115 -> -52.655 | K120: =-(K79-J79)-K115 -> -49.667 | L120: =-(L79-K79)-L115 -> -68.944
B121: - Intangible CAPEX | D121: =-(D81-C81)-(D80-C80)-D116 -> -256.746 | E121: =-(E81-D81)-(E80-D80)-E116 -> -3.449 | F121: =-(F81-E81)-(F80-E80)-F116 -> -45.578 | G121: =-(G81-F81)-(G80-F80)-G116 -> -14.839 | H121: =-(H81-G81)-(H80-G80)-H116 -> -11.713 | I121: =-(I81-H81)-(I80-H80)-I116 -> -1622.907 | J121: =-(J81-I81)-(J80-I80)-J116 -> -110.634 | K121: =-(K81-J81)-(K80-J80)-K116 -> 16.896 | L121: =-(L81-K81)-(L80-K80)-L116 -> -178.686
B122: FCFO | D122: =SUM(D117:D121) -> -141.11847 | E122: =SUM(E117:E121) -> 116.06976 | F122: =SUM(F117:F121) -> 114.64285 | G122: =SUM(G117:G121) -> 114.32466 | H122: =SUM(H117:H121) -> 238.96431 | I122: =SUM(I117:I121) -> -1373.8336 | J122: =SUM(J117:J121) -> 259.26572 | K122: =SUM(K117:K121) -> 249.53085 | L122: =SUM(L117:L121) -> 89.77684
B124: Tax shields | D124: =D26-D113 -> -5.93753 | E124: =E26-E113 -> 16.28924 | F124: =F26-F113 -> 12.30815 | G124: =G26-G113 -> 21.51634 | H124: =H26-H113 -> 19.02069 | I124: =I26-I113 -> 34.5506 | J124: =J26-J113 -> 18.88428 | K124: =K26-K113 -> 23.65015 | L124: =L26-L113 -> 18.55616
B125: Interest income | D125: =D52 -> 1.071 | E125: =E52 -> 1.223 | F125: =F52 -> 1.515 | G125: =G52 -> 2.833 | H125: =H52 -> 2.005 | I125: =I52 -> 0.284 | J125: =J52 -> 5.608 | K125: =K52 -> 13.931 | L125: =L52 -> 12.924
B126: Interest expenses | D126: =D53+D55 -> -8.531 | E126: =E53+E55 -> -16.155 | F126: =F53+F55 -> -6.027 | G126: =G53+G55 -> -8.579 | H126: =H53+H55 -> -9.314 | I126: =I53+I55 -> -43.716 | J126: =J53+J55 -> -54.452 | K126: =K53+K55 -> -41.182 | L126: =L53+L55 -> -34.031
...

Sheet Assumptions
B2: Assumptions
F3: Historicals | P3: Explicit forecast
B5: (EUR m) | F5: 2015 | G5: =F5+1 -> 2016 | H5: =G5+1 -> 2017 | I5: =H5+1 -> 2018 | J5: =I5+1 -> 2019 | K5: =J5+1 -> 2020 | L5: =K5+1 -> 2021 | M5: =L5+1 -> 2022 | N5: =M5+1 -> 2023 | ... T5: =S5+1 -> 2029 | V5: Notes
B8: Sales forecast assumptions
B10: Sales growth rates
B11: PAST | G11: =Restatements!D8/Restatements!C8-1 -> 0.1404904 | H11: =Restatements!E8/Restatements!D8-1 -> 0.11975901 | I11: =Restatements!F8/Restatements!E8-1 -> 0.049741957 | J11: =Restatements!G8/Restatements!F8-1 -> 0.055469217 | K11: =Restatements!H8/Restatements!G8-1 -> 0.2477489 | L11: =Restatements!I8/Restatements!H8-1 -> 0.40432992 | M11: =Restatements!J8/Restatements!I8-1 -> 0.099777805 | N11: =Restatements!K8/Restatements!J8-1 -> -0.15643505 | O11: =Restatements!L8/Restatements!K8-1 -> 0.032415673 | P11: =+AVERAGE($G$11:$J$11,$O$11) -> 0.079575252 | Q11: =+AVERAGE($G$11:$J$11,$O$11) -> 0.079575252 | R11: =+AVERAGE($G$11:$J$11,$O$11) -> 0.079575252 | S11: =+AVERAGE($G$11:$J$11,$O$11) -> 0.079575252 | T11: =+AVERAGE($G$11:$J$11,$O$11) -> 0.079575252
B12: BASE CASE | P12: 0.05 | Q12: 0.05 | R12: 0.05 | S12: 0.05 | T12: 0.05
B14: Operating expenses forecast assumptions
B16: COGS as a % of sales | F16: =-Restatements!C41/Restatements!C8 -> 0.26581594 | G16: =-Restatements!D41/Restatements!D8 -> 0.27054153 | H16: =-Restatements!E41/Restatements!E8 -> 0.2811699 | I16: =-Restatements!F41/Restatements!F8 -> 0.28329498 | J16: =-Restatements!G41/Restatements!G8 -> 0.27096359 | K16: =-Restatements!H41/Restatements!H8 -> 0.27245691 | L16: =-Restatements!I41/Restatements!I8 -> 0.30071587 | M16: =-Restatements!J41/Restatements!J8 -> 0.30510308 | ... O16: =-Restatements!L41/Restatements!L8 -> 0.29429658 | P16: 0.30430467 | Q16: 0.30430467 | R16: 0.3 | S16: 0.3 | T16: 0.3
B17: SG&A as a % of sales | F17: =-Restatements!C42/Restatements!C8 -> 0.35486598 | G17: =-Restatements!D42/Restatements!D8 -> 0.34235127 | H17: =-Restatements!E42/Restatements!E8 -> 0.33601311 | I17: =-Restatements!F42/Restatements!F8 -> 0.33725194 | J17: =-Restatements!G42/Restatements!G8 -> 0.33388974 | K17: =-Restatements!H42/Restatements!H8 -> 0.28286868 | L17: =-Restatements!I42/Restatements!I8 -> 0.27272169 | M17: =-Restatements!J42/Restatements!J8 -> 0.32641021 | ... O17: =-Restatements!L42/Restatements!L8 -> 0.36262453 | P17: =O17*(1+$O$17-$T$17)^(1/5) -> 0.3647738 | Q17: 0.36 | R17: 0.33 | S17: 0.33 | T17: =+AVERAGE($F17:$O17) -> 0.33263628 | W17: Equity | Y17: EV
V18: EV/EBITDA LTM | W18: 5398.5226 | X18: 643.35306 | Y18: 6041.8757
B19: Investment forecast assumptions | V19: P/E LTM | W19: 5976.9649 | X19: 643.35306 | Y19: 6620.318
B21: Tangible CAPEX as a % of sales | F21: =-Restatements!C120/Restatements!C38 -> 0 | G21: =-Restatements!D120/Restatements!D38 -> 0.078659856 | H21: =-Restatements!E120/Restatements!E38 -> 0.046846445 | I21: =-Restatements!F120/Restatements!F38 -> 0.046593156 | J21: =-Restatements!G120/Restatements!G38 -> 0.097032644 | K21: =-Restatements!H120/Restatements!H38 -> 0.051820879 | L21: =-Restatements!I120/Restatements!I38 -> 0.14772384 | M21: =-Restatements!J120/Restatements!J38 -> 0.038684542 | ... O21: =-Restatements!L120/Restatements!L38 -> 0.058159634 | P21: =+AVERAGE($H21:$I21) -> 0.046719801 | Q21: =+AVERAGE($H21:$I21) -> 0.046719801 | R21: =+AVERAGE($H21:$I21) -> 0.046719801 | S21: =+AVERAGE($H21:$I21) -> 0.046719801 | T21: =+AVERAGE($H21:$I21) -> 0.046719801
B22: Depreciation rate | G22: =-Restatements!D46/Restatements!C79 -> 0.36434296 | H22: =-Restatements!E46/Restatements!D79 -> 0.32198754 | I22: =-Restatements!F46/Restatements!E79 -> 0.30900446 | J22: =-Restatements!G46/Restatements!F79 -> 0.3698845 | K22: =-Restatements!H46/Restatements!G79 -> 0.26138568 | L22: =-Restatements!I46/Restatements!H79 -> 0.33545912 | M22: =-Restatements!J46/Restatements!I79 -> 0.21869897 | N22: =-Restatements!K46/Restatements!J79 -> 0.23032021 | O22: =-Restatements!L46/Restatements!K79 -> 0.21019876 | P22: =+AVERAGE($N22:$O22) -> 0.22025949 | Q22: =+AVERAGE($M22:$O22) -> 0.21973932 | R22: =+AVERAGE($M22:$O22) -> 0.21973932 | S22: =+AVERAGE($M22:$O22) -> 0.21973932 | T22: =+AVERAGE($M22:$O22) -> 0.21973932
B24: Intangible CAPEX as a % of sales | G24: =-Restatements!D121/Restatements!D38 -> 0.45097591 | H24: =-Restatements!E121/Restatements!E38 -> 0.0054103064 | I24: =-Restatements!F121/Restatements!F38 -> 0.068108494 | J24: =-Restatements!G121/Restatements!G38 -> 0.021008921 | K24: =-Restatements!H121/Restatements!H38 -> 0.013290518 | L24: =-Restatements!I121/Restatements!I38 -> 1.3112768 | M24: =-Restatements!J121/Restatements!J38 -> 0.081280517 | N24: =-Restatements!K121/Restatements!K38 -> -0.014715078 | O24: =-Restatements!L121/Restatements!L38 -> 0.15073556 | P24: =AVERAGE($H$24:$K$24,$M$24:$O$24) -> 0.046445605 | Q24: =AVERAGE($H$24:$K$24,$M$24:$O$24) -> 0.046445605 | R24: =AVERAGE($H$24:$K$24,$M$24:$O$24) -> 0.046445605 | S24: =AVERAGE($H$24:$K$24,$M$24:$O$24) -> 0.046445605 | T24: =AVERAGE($H$24:$K$24,$M$24:$O$24) -> 0.046445605
B25: Intangibles amortization as a % of BOP Intangibles | G25: =-Restatements!D121/SUM(Restatements!C80:C81) -> 2.1775482 | H25: =-Restatements!E121/SUM(Restatements!D80:D81) -> 0.0096587377 | I25: =-Restatements!F121/SUM(Restatements!E80:E81) -> 0.13235952 | J25: =-Restatements!G121/SUM(Restatements!F80:F81) -> 0.039773885 | K25: =-Restatements!H121/SUM(Restatements!G80:G81) -> 0.031632904 | L25: =-Restatements!I121/SUM(Restatements!H80:H81) -> 4.5493094 | M25: =-Restatements!J121/SUM(Restatements!I80:I81) -> 0.056928972 | N25: =-Restatements!K121/SUM(Restatements!J80:J81) -> -0.0084689055 | O25: =-Restatements!L121/SUM(Restatements!K80:K81) -> 0.092825343 | P25: =AVERAGE($O$25,$N$25,$M$25,$K$25,$J$25,$H$25) -> 0.037058489 | Q25: =AVERAGE($O$25,$N$25,$M$25,$K$25,$J$25,$H$25) -> 0.037058489 | R25: =AVERAGE($O$25,$N$25,$M$25,$K$25,$J$25,$H$25) -> 0.037058489 | S25: =AVERAGE($O$25,$N$25,$M$25,$K$25,$J$25,$H$25) -> 0.037058489 | T25: =AVERAGE($O$25,$N$25,$M$25,$K$25,$J$25,$H$25) -> 0.037058489
B27: Days receivables (Sales) | F27: =+(Restatements!C70*365)/(Restatements!C38*(1+$F$46)) -> 63.295949 | G27: =+(Restatements!D70*365)/(Restatements!D38*(1+$F$46)) -> 63.198607 | H27: =+(Restatements!E70*365)/(Restatements!E38*(1+$F$46)) -> 69.101506 | I27: =+(Restatements!F70*365)/(Restatements!F38*(1+$F$46)) -> 60.911099 | J27: =+(Restatements!G70*365)/(Restatements!G38*(1+$F$46)) -> 59.512538 | K27: =+(Restatements!H70*365)/(Restatements!H38*(1+$F$46)) -> 56.585939 | L27: =+(Restatements!I70*365)/(Restatements!I38*(1+$F$46)) -> 54.691578 | M27: =+(Restatements!J70*365)/(Restatements!J38*(1+$F$46)) -> 53.049779 | ... O27: =+(Restatements!L70*365)/(Restatements!L38*(1+$F$46)) -> 51.513924 | P27: =+AVERAGE($M27:$O27) -> 54.719061 | Q27: =+AVERAGE($M27:$O27) -> 54.719061 | R27: =+AVERAGE($M27:$O27) -> 54.719061 | S27: =+AVERAGE($M27:$O27) -> 54.719061 | T27: =+AVERAGE($M27:$O27) -> 54.719061
B28: Days payables (COGS) | F28: =Restatements!C71*365/(Restatements!C41*(1+$F$46)) -> 91.936678 | G28: =Restatements!D71*365/(Restatements!D41*(1+$F$46)) -> 92.604452 | H28: =Restatements!E71*365/(Restatements!E41*(1+$F$46)) -> 104.0387 | I28: =Restatements!F71*365/(Restatements!F41*(1+$F$46)) -> 90.403808 | J28: =Restatements!G71*365/(Restatements!G41*(1+$F$46)) -> 87.12304 | K28: =Restatements!H71*365/(Restatements!H41*(1+$F$46)) -> 81.592143 | L28: =Restatements!I71*365/(Restatements!I41*(1+$F$46)) -> 68.145375 | M28: =Restatements!J71*365/(Restatements!J41*(1+$F$46)) -> 75.070281 | ... O28: =Restatements!L71*365/(Restatements!L41*(1+$F$46)) -> 85.345822 | P28: =+AVERAGE($F$28:$I$28,$O$28) -> 92.865892 | Q28: =+AVERAGE($F$28:$I$28,$O$28) -> 92.865892 | R28: =+AVERAGE($F$28:$I$28,$O$28) -> 92.865892 | S28: =+AVERAGE($F$28:$I$28,$O$28) -> 92.865892 | T28: =+AVERAGE($F$28:$I$28,$O$28) -> 92.865892
B29: Days inventory (Sales) | F29: =365*Restatements!C72/Restatements!C8 -> 77.648233 | G29: =365*Restatements!D72/Restatements!D8 -> 82.622034 | H29: =365*Restatements!E72/Restatements!E8 -> 81.762428 | I29: =365*Restatements!F72/Restatements!F8 -> 87.484369 | J29: =365*Restatements!G72/Restatements!G8 -> 88.432092 | K29: =365*Restatements!H72/Restatements!H8 -> 79.200747 | L29: =365*Restatements!I72/Restatements!I8 -> 87.898748 | M29: =365*Restatements!J72/Restatements!J8 -> 82.191101 | ... O29: =365*Restatements!L72/Restatements!L8 -> 105.93261 | P29: =+AVERAGE($F29:$H29) -> 80.677565 | Q29: =+AVERAGE($F29:$H29) -> 80.677565 | R29: =+AVERAGE($F29:$H29) -> 80.677565 | S29: =+AVERAGE($F29:$H29) -> 80.677565 | T29: =+AVERAGE($F29:$H29) -> 80.677565
B31: Other current assets / liabilities as a % of sales | F31: =Restatements!C73/Restatements!C38 -> -0.041684279 | G31: =Restatements!D73/Restatements!D38 -> -0.055484515 | H31: =Restatements!E73/Restatements!E38 -> -0.049889645 | I31: =Restatements!F73/Restatements!F38 -> -0.043868995 | J31: =Restatements!G73/Restatements!G38 -> -0.048335101 | K31: =Restatements!H73/Restatements!H38 -> -0.050719104 | L31: =Restatements!I73/Restatements!I38 -> -0.061258639 | M31: =Restatements!J73/Restatements!J38 -> -0.026035567 | ... O31: =Restatements!L73/Restatements!L38 -> -0.07100142 | P31: =AVERAGE($F$31:$O$31) -> -0.050512314 | Q31: =AVERAGE($F$31:$O$31) -> -0.050512314 | R31: =AVERAGE($F$31:$O$31) -> -0.050512314 | S31: =AVERAGE($F$31:$O$31) -> -0.050512314 | T31: =AVERAGE($F$31:$O$31) -> -0.050512314
B33: Financing forecast assumptions
B35: Payout ratio | F35: =Restatements!C65/Restatements!C62 -> 0.0064728142 | G35: =Restatements!D65/Restatements!D62 -> 0.0071185144 | H35: =Restatements!E65/Restatements!E62 -> 0.006076724 | I35: =Restatements!F65/Restatements!F62 -> 0.0056915916 | J35: =Restatements!G65/Restatements!G62 -> 0.0054058668 | K35: =Restatements!H65/Restatements!H62 -> 0.0040343566 | L35: =Restatements!I65/Restatements!I62 -> 0.0033765532 | M35: =Restatements!J65/Restatements!J62 -> 0.0045660774 | ... O35: =Restatements!L65/Restatements!L62 -> 0.0063794158 | P35: =+AVERAGE($F35:$O35) -> 0.0056316203 | Q35: =+AVERAGE($F35:$O35) -> 0.0056316203 | R35: =+AVERAGE($F35:$O35) -> 0.0056316203 | S35: =+AVERAGE($F35:$O35) -> 0.0056316203 | T35: =+AVERAGE($F35:$O35) -> 0.0056316203
B36: Rights issues (issue of common stock)
B38: ST debt as a % of sales | F38: =Restatements!C93/Restatements!C38 -> 0.0046075472 | G38: =Restatements!D93/Restatements!D38 -> 0.04656849 | H38: =Restatements!E93/Restatements!E38 -> 0.037506647 | I38: =Restatements!F93/Restatements!F38 -> 0.030784657 | J38: =Restatements!G93/Restatements!G38 -> 0.0068127857 | K38: =Restatements!H93/Restatements!H38 -> 0.0047758721 | L38: =Restatements!I93/Restatements!I38 -> 0.081130106 | M38: =Restatements!J93/Restatements!J38 -> 0.088176217 | ... O38: =Restatements!L93/Restatements!L38 -> 0.040309526 | P38: =+AVERAGE($I$38,$G$38,$F$38) -> 0.027320231 | Q38: =+AVERAGE($I$38,$G$38,$F$38) -> 0.027320231 | R38: =+AVERAGE($I$38,$G$38,$F$38) -> 0.027320231 | S38: =+AVERAGE($I$38,$G$38,$F$38) -> 0.027320231 | T38: =+AVERAGE($I$38,$G$38,$F$38) -> 0.027320231
B39: Effective interest rate for debt | G39: =-SUM(Restatements!D53)/AVERAGE(Restatements!C95:D95) -> 0.11783681 | H39: =-SUM(Restatements!E53)/AVERAGE(Restatements!D95:E95) -> 0.11108423 | I39: =-SUM(Restatements!F53)/AVERAGE(Restatements!E95:F95) -> 0.19322504 | J39: =-SUM(Restatements!G53)/AVERAGE(Restatements!F95:G95) -> 0.15868695 | K39: =-SUM(Restatements!H53)/AVERAGE(Restatements!G95:H95) -> 0.10726016 | L39: =-SUM(Restatements!I53)/AVERAGE(Restatements!H95:I95) -> 0.030512974 | M39: =-SUM(Restatements!J53)/AVERAGE(Restatements!I95:J95) -> 0.025063857 | N39: =-SUM(Restatements!K53)/AVERAGE(Restatements!J95:K95) -> 0.023082253 | O39: =-SUM(Restatements!L53)/AVERAGE(Restatements!K95:L95) -> 0.025045091 | P39: =+AVERAGE($J39:$O39) -> 0.061608547 | Q39: =+AVERAGE($J39:$O39) -> 0.061608547 | R39: =+AVERAGE($J39:$O39) -> 0.061608547 | S39: =+AVERAGE($J39:$O39) -> 0.061608547 | T39: =+AVERAGE($J39:$O39) -> 0.061608547
B40: Bonds issuance schedule
B41: Bonds maturity schedule
B42: Effective interest rate for cash / overdraft | G42: =Restatements!D52/AVERAGE(Restatements!C96:D96) -> 0.005343978 | H42: =Restatements!E52/AVERAGE(Restatements!D96:E96) -> 0.0080518266 | I42: =Restatements!F52/AVERAGE(Restatements!E96:F96) -> 0.011228918 | J42: =Restatements!G52/AVERAGE(Restatements!F96:G96) -> 0.018971088 | K42: =Restatements!H52/AVERAGE(Restatements!G96:H96) -> 0.0073965179 | L42: =Restatements!I52/AVERAGE(Restatements!H96:I96) -> 0.00076444059 | M42: =Restatements!J52/AVERAGE(Restatements!I96:J96) -> 0.01374109 | N42: =Restatements!K52/AVERAGE(Restatements!J96:K96) -> 0.034119227 | O42: =Restatements!L52/AVERAGE(Restatements!K96:L96) -> 0.032445582 | P42: =AVERAGE($G$42:$O$42) -> 0.01467363 | Q42: =AVERAGE($G$42:$O$42) -> 0.01467363 | R42: =AVERAGE($G$42:$O$42) -> 0.01467363 | S42: =AVERAGE($G$42:$O$42) -> 0.01467363 | T42: =AVERAGE($G$42:$O$42) -> 0.01467363
B44: Tax forecast assumptions
B46: Value added tax (sales tax) | F46: 0.22 | G46: =+$F46 -> 0.22 | H46: =+$F46 -> 0.22 | I46: =+$F46 -> 0.22 | J46: =+$F46 -> 0.22 | K46: =+$F46 -> 0.22 | L46: =+$F46 -> 0.22 | M46: =+$F46 -> 0.22 | N46: =+$F46 -> 0.22 | ... T46: =+$F46 -> 0.22
B47: Income tax 1 on EBT (IRES) | F47: 0.24 | G47: =+$F47 -> 0.24 | H47: =+$F47 -> 0.24 | I47: =+$F47 -> 0.24 | J47: =+$F47 -> 0.24 | K47: =+$F47 -> 0.24 | L47: =+$F47 -> 0.24 | M47: =+$F47 -> 0.24 | N47: =+$F47 -> 0.24 | ... T47: =+$F47 -> 0.24
B48: Income tax 2 on EBIT (IRAP) | F48: 0.039 | G48: =+$F48 -> 0.039 | H48: =+$F48 -> 0.039 | I48: =+$F48 -> 0.039 | J48: =+$F48 -> 0.039 | K48: =+$F48 -> 0.039 | L48: =+$F48 -> 0.039 | M48: =+$F48 -> 0.039 | N48: =+$F48 -> 0.039 | ... T48: =+$F48 -> 0.039
B50: Steady state assumptions
B52: Terminal growth rate (2022 onwards) | T52: 0.02

Sheet Calculations >>>
C12: DIASORIN
C13: Financial Model
C17: Calculations

Sheet SalesOPEX
B2: Sales and Operating Expenses Forecasts
F3: Historicals | P3: Explicit forecast
B5: =[1]AsReported!B5 -> (EUR m) | F5: 2015 | G5: =F5+1 -> 2016 | H5: =G5+1 -> 2017 | I5: =H5+1 -> 2018 | J5: =I5+1 -> 2019 | K5: =J5+1 -> 2020 | L5: =K5+1 -> 2021 | M5: =L5+1 -> 2022 | N5: =M5+1 -> 2023 | ... T5: =S5+1 -> 2029 | V5: Notes
B8: Sales forecast
B10: Base Case | F10: =Restatements!C8 -> 499.18 | G10: =Restatements!D8 -> 569.31 | H10: =Restatements!E8 -> 637.49 | I10: =Restatements!F8 -> 669.2 | J10: =Restatements!G8 -> 706.32 | K10: =Restatements!H8 -> 881.31 | L10: =Restatements!I8 -> 1237.65 | M10: =Restatements!J8 -> 1361.14 | ... O10: =Restatements!L8 -> 1185.43 | P10: 1200 | Q10: =P10*(1+Assumptions!Q12) -> 1260 | R10: =Q10*(1+Assumptions!R12) -> 1323 | S10: =R10*(1+Assumptions!S12) -> 1389.15 | T10: =S10*(1+Assumptions!T12) -> 1458.6075
B11: Best Case | P11: =O10*(1+Assumptions!P11) -> 1279.7609 | Q11: =P10*(1+Assumptions!Q11) -> 1295.4903 | R11: =Q10*(1+Assumptions!R11) -> 1360.2648 | S11: =R10*(1+Assumptions!S11) -> 1428.2781 | T11: =S10*(1+Assumptions!T11) -> 1499.692
B13: Operational forecasts
B15: COGS | F15: =-Restatements!C10 -> -157.28 | G15: =-Restatements!D10 -> -180.16 | H15: =-Restatements!E10 -> -205.59 | I15: =-Restatements!F10 -> -213.43 | J15: =-Restatements!G10 -> -217.63 | K15: =-Restatements!H10 -> -278.4 | L15: =-Restatements!I10 -> -412.88 | M15: =-Restatements!J10 -> -460.53 | ... O15: =-Restatements!L10 -> -403.73 | P15: =-P$10*Assumptions!P16 -> -365.1656 | Q15: =-Q$10*Assumptions!Q16 -> -383.42388 | R15: =-R$10*Assumptions!R16 -> -396.9 | S15: =-S$10*Assumptions!S16 -> -416.745 | T15: =-T$10*Assumptions!T16 -> -437.58225
B16: SGAs | F16: =-Restatements!C11 -> -132.91 | G16: =-Restatements!D11 -> -148.79 | H16: =-Restatements!E11 -> -163.4 | I16: =-Restatements!F11 -> -179.71 | J16: =-Restatements!G11 -> -186.95 | K16: =-Restatements!H11 -> -193.18 | L16: =-Restatements!I11 -> -264.73 | M16: =-Restatements!J11 -> -357.18 | ... O16: =-Restatements!L11 -> -361.65 | P16: =-P$10*Assumptions!P17 -> -437.72856 | Q16: =-Q$10*Assumptions!Q17 -> -453.6 | R16: =-R$10*Assumptions!R17 -> -436.59 | S16: =-S$10*Assumptions!S17 -> -458.4195 | T16: =-T$10*Assumptions!T17 -> -485.18577
P17: =(P16+P15)/P10 -> -0.66907847

Sheet Investments
B2: Investments Forecasts
F3: Historicals | P3: Explicit forecast
B5: =[1]AsReported!B5 -> (EUR m) | F5: 42192 | G5: =F5+365 -> 42557 | H5: =G5+365 -> 42922 | I5: =H5+365 -> 43287 | J5: =I5+365 -> 43652 | K5: =J5+365 -> 44017 | L5: =K5+365 -> 44382 | M5: =L5+365 -> 44747 | N5: =M5+365 -> 45112 | ... T5: =S5+365 -> 47302 | V5: Notes
B8: Working capital forecast
B10: Trade receivables | P10: =+(Assumptions!P27*SalesOPEX!P10*(1+Assumptions!P$46))/365 -> 219.47591 | Q10: =+(Assumptions!Q27*SalesOPEX!Q10*(1+Assumptions!Q$46))/365 -> 230.4497 | R10: =+(Assumptions!R27*SalesOPEX!R10*(1+Assumptions!R$46))/365 -> 241.97219 | S10: =+(Assumptions!S27*SalesOPEX!S10*(1+Assumptions!S$46))/365 -> 254.0708 | T10: =+(Assumptions!T27*SalesOPEX!T10*(1+Assumptions!T$46))/365 -> 266.77434
B11: Trade payables | P11: =+(Assumptions!P28*SalesOPEX!P15*(1+Assumptions!P$46))/365 -> -113.34779 | Q11: =+(Assumptions!Q28*SalesOPEX!Q15*(1+Assumptions!Q$46))/365 -> -119.01518 | R11: =+(Assumptions!R28*SalesOPEX!R15*(1+Assumptions!R$46))/365 -> -123.19818 | S11: =+(Assumptions!S28*SalesOPEX!S15*(1+Assumptions!S$46))/365 -> -129.35809 | T11: =+(Assumptions!T28*SalesOPEX!T15*(1+Assumptions!T$46))/365 -> -135.826
B12: Inventory | P12: =+(Assumptions!P29*SalesOPEX!P10)/365 -> 265.24131 | Q12: =+(Assumptions!Q29*SalesOPEX!Q10)/365 -> 278.50337 | R12: =+(Assumptions!R29*SalesOPEX!R10)/365 -> 292.42854 | S12: =+(Assumptions!S29*SalesOPEX!S10)/365 -> 307.04997 | T12: =+(Assumptions!T29*SalesOPEX!T10)/365 -> 322.40247
B13: Other current assets & liabilities | P13: =Assumptions!P$31*SalesOPEX!P10 -> -60.614777 | Q13: =Assumptions!Q$31*SalesOPEX!Q10 -> -63.645515 | R13: =Assumptions!R$31*SalesOPEX!R10 -> -66.827791 | S13: =Assumptions!S$31*SalesOPEX!S10 -> -70.169181 | T13: =Assumptions!T$31*SalesOPEX!T10 -> -73.67764
B15: Deferred taxes | O15: =Restatements!L74 -> -167.969 | P15: =O15 -> -167.969 | Q15: =+P15 -> -167.969 | R15: =+Q15 -> -167.969 | S15: =+R15 -> -167.969 | T15: =+S15 -> -167.969
B16: Long term provisions | O16: =Restatements!L76 -> -54.663 | P16: =O16 -> -54.663 | Q16: =+P16 -> -54.663 | R16: =+Q16 -> -54.663 | S16: =+R16 -> -54.663 | T16: =+S16 -> -54.663
B18: Investment forecasts
B20: Evolution of tangible assets
B21: BOP tangible assets | P21: =+O24 -> 271.359 | Q21: =+P24 -> 297.53806 | R21: =+Q24 -> 290.61707 | S21: =+R24 -> 274.01202 | T21: =+S24 -> 247.23872
B22: + Tangible CAPEX | P22: =SalesOPEX!P10*Assumptions!P21 -> 56.063761 | Q22: =SalesOPEX!Q10*Assumptions!Q21 -> 58.866949 | R22: =SalesOPEX!R10*Assumptions!R21 -> 61.810296 | S22: =SalesOPEX!S10*Assumptions!S21 -> 64.900811 | T22: =SalesOPEX!T10*Assumptions!T21 -> 68.145852
B23: - Depreciation | O23: =Restatements!L46 -> -53.871 | P23: =+P32 -> -29.884697 | Q23: =+Q32 -> -65.787947 | R23: =+R32 -> -78.415345 | S23: =+S32 -> -91.674112 | T23: =+T32 -> -105.59582
B24: = EOP tangible assets | O24: =Restatements!L79 -> 271.359 | P24: =+SUM(P21:P23) -> 297.53806 | Q24: =+SUM(Q21:Q23) -> 290.61707 | R24: =+SUM(R21:R23) -> 274.01202 | S24: =+SUM(S21:S23) -> 247.23872 | T24: =+SUM(T21:T23) -> 209.78875
B26: Existing assets | C26: =+P5 -> 45842 | D26: =+O24 -> 271.359 | P26: =-MIN($D26+SUM($I26:I26),$D26*Assumptions!P$22)*(P$5>=$C26)*(IF(P$5=$C26,0.5,1)) -> -29.884697 | Q26: =-MIN($D26+SUM($I26:P26),$D26*Assumptions!Q$22)*(Q$5>=$C26)*(IF(Q$5=$C26,0.5,1)) -> -59.628241 | R26: =-MIN($D26+SUM($I26:Q26),$D26*Assumptions!R$22)*(R$5>=$C26)*(IF(R$5=$C26,0.5,1)) -> -59.628241 | S26: =-MIN($D26+SUM($I26:R26),$D26*Assumptions!S$22)*(S$5>=$C26)*(IF(S$5=$C26,0.5,1)) -> -59.628241 | T26: =-MIN($D26+SUM($I26:S26),$D26*Assumptions!T$22)*(T$5>=$C26)*(IF(T$5=$C26,0.5,1)) -> -59.628241
B27: ="CAPEX Year "&YEAR(P5) -> CAPEX Year 2025 | C27: =C26+365 -> 46207 | D27: =P22 -> 56.063761 | P27: =-MIN($D27+SUM($I27:I27),$D27*Assumptions!P$22)*(P$5>=$C27)*(IF(P$5=$C27,0.5,1)) -> 0 | Q27: =-MIN($D27+SUM($I27:P27),$D27*Assumptions!Q$22)*(Q$5>=$C27)*(IF(Q$5=$C27,0.5,1)) -> -6.1597062 | R27: =-MIN($D27+SUM($I27:Q27),$D27*Assumptions!R$22)*(R$5>=$C27)*(IF(R$5=$C27,0.5,1)) -> -12.319412 | S27: =-MIN($D27+SUM($I27:R27),$D27*Assumptions!S$22)*(S$5>=$C27)*(IF(S$5=$C27,0.5,1)) -> -12.319412 | T27: =-MIN($D27+SUM($I27:S27),$D27*Assumptions!T$22)*(T$5>=$C27)*(IF(T$5=$C27,0.5,1)) -> -12.319412
B28: ="CAPEX Year "&YEAR(Q5) -> CAPEX Year 2026 | C28: =C27+365 -> 46572 | D28: =Q22 -> 58.866949 | P28: =-MIN($D28+SUM($I28:I28),$D28*Assumptions!P$22)*(P$5>=$C28)*(IF(P$5=$C28,0.5,1)) -> 0 | Q28: =-MIN($D28+SUM($I28:P28),$D28*Assumptions!Q$22)*(Q$5>=$C28)*(IF(Q$5=$C28,0.5,1)) -> 0 | R28: =-MIN($D28+SUM($I28:Q28),$D28*Assumptions!R$22)*(R$5>=$C28)*(IF(R$5=$C28,0.5,1)) -> -6.4676915 | S28: =-MIN($D28+SUM($I28:R28),$D28*Assumptions!S$22)*(S$5>=$C28)*(IF(S$5=$C28,0.5,1)) -> -12.935383 | T28: =-MIN($D28+SUM($I28:S28),$D28*Assumptions!T$22)*(T$5>=$C28)*(IF(T$5=$C28,0.5,1)) -> -12.935383
B29: ="CAPEX Year "&YEAR(R5) -> CAPEX Year 2027 | C29: =C28+365 -> 46937 | D29: =R22 -> 61.810296 | P29: =-MIN($D29+SUM($I29:I29),$D29*Assumptions!P$22)*(P$5>=$C29)*(IF(P$5=$C29,0.5,1)) -> 0 | Q29: =-MIN($D29+SUM($I29:P29),$D29*Assumptions!Q$22)*(Q$5>=$C29)*(IF(Q$5=$C29,0.5,1)) -> 0 | R29: =-MIN($D29+SUM($I29:Q29),$D29*Assumptions!R$22)*(R$5>=$C29)*(IF(R$5=$C29,0.5,1)) -> 0 | S29: =-MIN($D29+SUM($I29:R29),$D29*Assumptions!S$22)*(S$5>=$C29)*(IF(S$5=$C29,0.5,1)) -> -6.7910761 | T29: =-MIN($D29+SUM($I29:S29),$D29*Assumptions!T$22)*(T$5>=$C29)*(IF(T$5=$C29,0.5,1)) -> -13.582152
B30: ="CAPEX Year "&YEAR(S5) -> CAPEX Year 2028 | C30: =C29+365 -> 47302 | D30: =S22 -> 64.900811 | P30: =-MIN($D30+SUM($I30:I30),$D30*Assumptions!P$22)*(P$5>=$C30)*(IF(P$5=$C30,0.5,1)) -> 0 | Q30: =-MIN($D30+SUM($I30:P30),$D30*Assumptions!Q$22)*(Q$5>=$C30)*(IF(Q$5=$C30,0.5,1)) -> 0 | R30: =-MIN($D30+SUM($I30:Q30),$D30*Assumptions!R$22)*(R$5>=$C30)*(IF(R$5=$C30,0.5,1)) -> 0 | S30: =-MIN($D30+SUM($I30:R30),$D30*Assumptions!S$22)*(S$5>=$C30)*(IF(S$5=$C30,0.5,1)) -> 0 | T30: =-MIN($D30+SUM($I30:S30),$D30*Assumptions!T$22)*(T$5>=$C30)*(IF(T$5=$C30,0.5,1)) -> -7.1306299
B31: ="CAPEX Year "&YEAR(T5) -> CAPEX Year 2029 | C31: =C30+365 -> 47667 | D31: =T22 -> 68.145852 | P31: =-MIN($D31+SUM($I31:I31),$D31*Assumptions!P$22)*(P$5>=$C31)*(IF(P$5=$C31,0.5,1)) -> 0 | Q31: =-MIN($D31+SUM($I31:P31),$D31*Assumptions!Q$22)*(Q$5>=$C31)*(IF(Q$5=$C31,0.5,1)) -> 0 | R31: =-MIN($D31+SUM($I31:Q31),$D31*Assumptions!R$22)*(R$5>=$C31)*(IF(R$5=$C31,0.5,1)) -> 0 | S31: =-MIN($D31+SUM($I31:R31),$D31*Assumptions!S$22)*(S$5>=$C31)*(IF(S$5=$C31,0.5,1)) -> 0 | T31: =-MIN($D31+SUM($I31:S31),$D31*Assumptions!T$22)*(T$5>=$C31)*(IF(T$5=$C31,0.5,1)) -> 0
B32: Total depreciation | P32: =SUM(P26:P31) -> -29.884697 | Q32: =SUM(Q26:Q31) -> -65.787947 | R32: =SUM(R26:R31) -> -78.415345 | S32: =SUM(S26:S31) -> -91.674112 | T32: =SUM(T26:T31) -> -105.59582
B34: BOP Goodwill & trademarks | P34: =+I37 -> 2028.486 | Q34: =+P37 -> 2009.0481 | R34: =+Q37 -> 1993.1173 | S34: =+R37 -> 1980.7029 | T34: =+S37 -> 1971.821
B35: Intangible CAPEX | P35: =+Assumptions!P24*SalesOPEX!P10 -> 55.734726 | Q35: =+Assumptions!Q24*SalesOPEX!Q10 -> 58.521462 | R35: =+Assumptions!R24*SalesOPEX!R10 -> 61.447536 | S35: =+Assumptions!S24*SalesOPEX!S10 -> 64.519912 | T35: =+Assumptions!T24*SalesOPEX!T10 -> 67.745908
B36: Amortization | P36: =-I37*Assumptions!P25 -> -75.172627 | Q36: =-P37*Assumptions!Q25 -> -74.452287 | R36: =-Q37*Assumptions!R25 -> -73.861915 | S36: =-R37*Assumptions!S25 -> -73.401857 | T36: =-S37*Assumptions!T25 -> -73.072706
B37: EOP Goodwill & trademarks | I37: =Restatements!L80+Restatements!L81 -> 2028.486 | P37: =SUM(P34:P36) -> 2009.0481 | Q37: =SUM(Q34:Q36) -> 1993.1173 | R37: =SUM(R34:R36) -> 1980.7029 | S37: =SUM(S34:S36) -> 1971.821 | T37: =SUM(T34:T36) -> 1966.4942

Sheet Financing
B2: Financing Forecasts
F3: Historicals | J3: Explicit forecast
B5: =[1]AsReported!B5 -> (EUR m) | F5: =[1]AsReported!F5 -> 41639 | G5: =[1]AsReported!G5 -> 42004 | H5: =[1]AsReported!H5 -> 42369 | I5: =Investments!O5 -> 45477 | J5: =Investments!P5 -> 45842 | K5: =J5+365 -> 46207 | L5: =K5+365 -> 46572 | M5: =L5+365 -> 46937 | N5: =M5+365 -> 47302 | P5: Notes
B8: Equity forecast
A10: Output Recall | B10: Total net income | J10: =+'Output (2)'!P29 -> 163.23272 | K10: =+'Output (2)'!Q29 -> 156.92259 | L10: =+'Output (2)'!R29 -> 196.00538 | M10: =+'Output (2)'!S29 -> 204.54187 | N10: =+'Output (2)'!T29 -> 210.2589
A11: IS Output | B11: Dividends | J11: =J10*Assumptions!P35 -> 0.91926471 | K11: =K10*Assumptions!Q35 -> 0.88372848 | L11: =L10*Assumptions!R35 -> 1.1038279 | M11: =M10*Assumptions!S35 -> 1.1519022 | N11: =N10*Assumptions!T35 -> 1.1840983
B13: Evolution of retained earnings
B14: BOP retained earnings | J14: =+I17 -> 1579.887 | K14: =+J17 -> 1742.2005 | L14: =+K17 -> 1898.2393 | M14: =+L17 -> 2093.1409 | N14: =+M17 -> 2296.5308
A15: Linking Cell | B15: + Total net income | J15: =+J10 -> 163.23272 | K15: =+K10 -> 156.92259 | L15: =+L10 -> 196.00538 | M15: =+M10 -> 204.54187 | N15: =+N10 -> 210.2589
B16: - Dividends | J16: =-J11 -> -0.91926471 | K16: =-K11 -> -0.88372848 | L16: =-L11 -> -1.1038279 | M16: =-M11 -> -1.1519022 | N16: =-N11 -> -1.1840983
A17: BS Output | B17: EOP retained earnings | I17: =Restatements!L100 -> 1579.887 | J17: =+SUM(J14:J16) -> 1742.2005 | K17: =+SUM(K14:K16) -> 1898.2393 | L17: =+SUM(L14:L16) -> 2093.1409 | M17: =+SUM(M14:M16) -> 2296.5308 | N17: =+SUM(N14:N16) -> 2505.6056
A19: BS Output | B19: Minorities | I19: =Restatements!L103 -> -1.896 | J19: =+I19 -> -1.896 | K19: =+J19 -> -1.896 | L19: =+K19 -> -1.896 | M19: =+L19 -> -1.896 | N19: =+M19 -> -1.896
A20: BS Output | B20: Share capital | I20: =Restatements!L99 -> 221.031 | J20: =+I20+Assumptions!P36 -> 221.031 | K20: =+J20+Assumptions!Q36 -> 221.031 | L20: =+K20+Assumptions!R36 -> 221.031 | M20: =+L20+Assumptions!S36 -> 221.031 | N20: =+M20+Assumptions!T36 -> 221.031
B22: Debt forecast
A24: BS Output | B24: ST financial debt | J24: =+SalesOPEX!P10*Assumptions!P38 -> 32.784277 | K24: =+SalesOPEX!Q10*Assumptions!Q38 -> 34.423491 | L24: =+SalesOPEX!R10*Assumptions!R38 -> 36.144666 | M24: =+SalesOPEX!S10*Assumptions!S38 -> 37.951899 | N24: =+SalesOPEX!T10*Assumptions!T38 -> 39.849494
A25: BS Output | B25: Bonds and securities | I25: =Restatements!L94 -> 966.781 | J25: =+I25+Assumptions!P40+Assumptions!P41 -> 966.781 | K25: =+J25+Assumptions!Q40+Assumptions!Q41 -> 966.781 | L25: =+K25+Assumptions!R40+Assumptions!R41 -> 966.781 | M25: =+L25+Assumptions!S40+Assumptions!S41 -> 966.781 | N25: =+M25+Assumptions!T40+Assumptions!T41 -> 966.781
A27: IS Output | B27: Interest expenses | J27: =-AVERAGE(I28:J28)*Assumptions!P39 -> -62.04382 | K27: =-AVERAGE(J28:K28)*Assumptions!Q39 -> -61.632259 | L27: =-AVERAGE(K28:L28)*Assumptions!R39 -> -61.735774 | M27: =-AVERAGE(L28:M28)*Assumptions!S39 -> -61.844464 | N27: =-AVERAGE(M28:N28)*Assumptions!T39 -> -61.958588
B28: Gross financial debt | I28: =Restatements!L95 -> 1014.565 | J28: =SUM(J24:J25) -> 999.56528 | K28: =SUM(K24:K25) -> 1001.2045 | L28: =SUM(L24:L25) -> 1002.9257 | M28: =SUM(M24:M25) -> 1004.7329 | N28: =SUM(N24:N25) -> 1006.6305
B30: Cash balance forecast
B32: Cash / bank overdraft evolution
B33: BOP cash | J33: =+I35 -> 393.268 | K33: =+J35 -> 577.97092 | L33: =+K35 -> 742.96309 | M33: =+L35 -> 950.52288 | N33: =+M35 -> 1174.1566
A34: Output Recall | B34: + change in cash | J34: ='Output (2)'!P102 -> 184.70292 | K34: ='Output (2)'!Q102 -> 164.99217 | L34: ='Output (2)'!R102 -> 207.55978 | M34: ='Output (2)'!S102 -> 223.63371 | N34: ='Output (2)'!T102 -> 235.66949
A35: Linking Cell | B35: = EOP cash / overdraft | I35: =Restatements!L96 -> 393.268 | J35: =SUM(J33:J34) -> 577.97092 | K35: =SUM(K33:K34) -> 742.96309 | L35: =SUM(L33:L34) -> 950.52288 | M35: =SUM(M33:M34) -> 1174.1566 | N35: =SUM(N33:N34) -> 1409.8261
A37: IS Output | B37: Interest inc. (exp.) on cash (overdraft) | K37: =AVERAGE(J35:K35)*(IF(AVERAGE(J35:K35)>0,Assumptions!Q42,Assumptions!Q39)) -> 9.6914484 | L37: =AVERAGE(K35:L35)*(IF(AVERAGE(K35:L35)>0,Assumptions!R42,Assumptions!R39)) -> 12.424793 | M37: =AVERAGE(L35:M35)*(IF(AVERAGE(L35:M35)>0,Assumptions!S42,Assumptions!S39)) -> 15.58838 | N37: =AVERAGE(M35:N35)*(IF(AVERAGE(M35:N35)>0,Assumptions!T42,Assumptions!T39)) -> 18.958203

Sheet Others
B2: Taxes and Other Items Forecasts
F3: Historicals | J3: Explicit forecast
B5: =[1]AsReported!B5 -> (EUR m) | F5: =[1]AsReported!F5 -> 41639 | G5: =[1]AsReported!G5 -> 42004 | H5: =[1]AsReported!H5 -> 42369 | I5: =[1]AsReported!I5 -> 42735 | J5: =[1]AsReported!J5 -> 43100 | K5: =[1]AsReported!K5 -> 43465 | L5: =[1]AsReported!L5 -> 43830 | M5: =[1]AsReported!M5 -> 44196 | N5: =[1]AsReported!N5 -> 44561 | P5: Notes
B8: Other balance sheet items forecast
A10: BS Output | B10: Associates | I10: =Restatements!L86 -> 3.589 | J10: =+I10 -> 3.589 | K10: =+J10 -> 3.589 | L10: =+K10 -> 3.589 | M10: =+L10 -> 3.589 | N10: =+M10 -> 3.589
A11: BS Output | B11: Other non-operational assets | I11: =Restatements!L88 -> 2.701 | J11: =+I11 -> 2.701 | K11: =+J11 -> 2.701 | L11: =+K11 -> 2.701 | M11: =+L11 -> 2.701 | N11: =+M11 -> 2.701
A13: IS Output | B13: Income from associates | J13: 0 | K13: =+J13 -> 0 | L13: =+K13 -> 0 | M13: =+L13 -> 0 | N13: =+M13 -> 0
A14: IS Output | B14: Except. items | J14: 0 | K14: =+J14 -> 0 | L14: =+K14 -> 0 | M14: =+L14 -> 0 | N14: =+M14 -> 0
B16: Income taxes forecast
A18: Output Recall | B18: Income before taxes | J18: =+'Output (2)'!P26 -> 229.76659 | K18: =+'Output (2)'!Q26 -> 220.98591 | L18: =+'Output (2)'!R26 -> 275.20719 | M18: =+'Output (2)'!S26 -> 287.03861 | N18: =+'Output (2)'!T26 -> 294.98496
A19: Output Recall | B19: EBIT | J19: =+'Output (2)'!P20 -> 292.04851 | K19: =+'Output (2)'!Q20 -> 282.73588 | L19: =+'Output (2)'!R20 -> 337.23274 | M19: =+'Output (2)'!S20 -> 348.90953 | N19: =+'Output (2)'!T20 -> 357.17095
B21: - Income tax 1 on EBT (IRES) | J21: =-J18*Assumptions!P47 -> -55.143983 | K21: =-K18*Assumptions!Q47 -> -53.036619 | L21: =-L18*Assumptions!R47 -> -66.049725 | M21: =-M18*Assumptions!S47 -> -68.889266 | N21: =-N18*Assumptions!T47 -> -70.79639
B22: - Income tax 2 on EBIT (IRAP) | J22: =-J19*Assumptions!P48 -> -11.389892 | K22: =-K19*Assumptions!Q48 -> -11.026699 | L22: =-L19*Assumptions!R48 -> -13.152077 | M22: =-M19*Assumptions!S48 -> -13.607472 | N22: =-N19*Assumptions!T48 -> -13.929667
A23: IS Output | B23: - Income taxes | J23: =SUM(J21:J22) -> -66.533875 | K23: =SUM(K21:K22) -> -64.063319 | L23: =SUM(L21:L22) -> -79.201801 | M23: =SUM(M21:M22) -> -82.496738 | N23: =SUM(N21:N22) -> -84.726057

Sheet Output >>>
C12: Diasorin
C13: Financial Model
C17: Output

Sheet Output (2)
B2: Output Financial Statements
F3: Historicals | P3: Explicit forecast
B5: =[1]AsReported!B5 -> (EUR m) | F5: 42192 | G5: =F5+365 -> 42557 | H5: =G5+365 -> 42922 | I5: =H5+365 -> 43287 | J5: =I5+365 -> 43652 | K5: =J5+365 -> 44017 | L5: =K5+365 -> 44382 | M5: =L5+365 -> 44747 | N5: =M5+365 -> 45112 | ... T5: =S5+365 -> 47302 | V5: Notes
B8: Income statement
B10: Sales | F10: =Restatements!C38 -> 499.181 | G10: =Restatements!D38 -> 569.312 | H10: =Restatements!E38 -> 637.487 | I10: =Restatements!F38 -> 669.197 | J10: =Restatements!G38 -> 706.319 | K10: =Restatements!H38 -> 881.305 | L10: =Restatements!I38 -> 1237.654 | M10: =Restatements!J38 -> 1361.138 | ... O10: =Restatements!L38 -> 1185.427 | P10: =+SalesOPEX!P10 -> 1200 | Q10: =+SalesOPEX!Q10 -> 1260 | R10: =+SalesOPEX!R10 -> 1323 | S10: =+SalesOPEX!S10 -> 1389.15 | T10: =+SalesOPEX!T10 -> 1458.6075
B11: Growth | F11: n/a | G11: =G10/F10-1 -> 0.14049213 | H11: =H10/G10-1 -> 0.1197498 | I11: =I10/H10-1 -> 0.049742191 | J11: =J10/I10-1 -> 0.055472454 | K11: =K10/J10-1 -> 0.24774358 | L11: =L10/K10-1 -> 0.40434242 | M11: =M10/L10-1 -> 0.099772634 | N11: =N10/M10-1 -> -0.15643381 | O11: =O10/N10-1 -> 0.03241306 | P11: =+P10/O10-1 -> 0.01229346 | Q11: =+Q10/P10-1 -> 0.05 | R11: =+R10/Q10-1 -> 0.05 | S11: =+S10/R10-1 -> 0.05 | T11: =+T10/S10-1 -> 0.05
B13: (Cost of goods sold) | F13: =Restatements!C10 -> 157.28 | G13: =Restatements!D10 -> 180.16 | H13: =Restatements!E10 -> 205.59 | I13: =Restatements!F10 -> 213.43 | J13: =Restatements!G10 -> 217.63 | K13: =Restatements!H10 -> 278.4 | L13: =Restatements!I10 -> 412.88 | M13: =Restatements!J10 -> 460.53 | ... O13: =Restatements!L10 -> 403.73 | P13: =+SalesOPEX!P15 -> -365.1656 | Q13: =+SalesOPEX!Q15 -> -383.42388 | R13: =+SalesOPEX!R15 -> -396.9 | S13: =+SalesOPEX!S15 -> -416.745 | T13: =+SalesOPEX!T15 -> -437.58225
B14: (Selling, general & adminsitrative expenses) | F14: =Restatements!C11+Restatements!C12 -> 135.19 | G14: =Restatements!D11+Restatements!D12 -> 148.04 | H14: =Restatements!E11+Restatements!E12 -> 164.73 | I14: =Restatements!F11+Restatements!F12 -> 178.41 | J14: =Restatements!G11+Restatements!G12 -> 190.81 | K14: =Restatements!H11+Restatements!H12 -> 196.15 | L14: =Restatements!I11+Restatements!I12 -> 267.86 | M14: =Restatements!J11+Restatements!J12 -> 364.07 | ... O14: =Restatements!L11+Restatements!L12 -> 367.87 | P14: =+SalesOPEX!P16 -> -437.72856 | Q14: =+SalesOPEX!Q16 -> -453.6 | R14: =+SalesOPEX!R16 -> -436.59 | S14: =+SalesOPEX!S16 -> -458.4195 | T14: =+SalesOPEX!T16 -> -485.18577
B15: EBITDA | F15: =+F10-SUM(F13:F14) -> 206.711 | G15: =+G10-SUM(G13:G14) -> 241.112 | H15: =+H10-SUM(H13:H14) -> 267.167 | I15: =+I10-SUM(I13:I14) -> 277.357 | J15: =+J10-SUM(J13:J14) -> 297.879 | K15: =+K10-SUM(K13:K14) -> 406.755 | L15: =+L10-SUM(L13:L14) -> 556.914 | M15: =+M10-SUM(M13:M14) -> 536.538 | ... O15: =+O10-SUM(O13:O14) -> 413.827 | P15: =+P10+SUM(P13:P14) -> 397.10584 | Q15: =+Q10+SUM(Q13:Q14) -> 422.97612 | R15: =+R10+SUM(R13:R14) -> 489.51 | S15: =+S10+SUM(S13:S14) -> 513.9855 | T15: =+T10+SUM(T13:T14) -> 535.83948
B16: Margin | F16: =+F15/F$10 -> 0.4141003 | G16: =+G15/G$10 -> 0.4235147 | H16: =+H15/H$10 -> 0.41909404 | I16: =+I15/I$10 -> 0.41446241 | J16: =+J15/J$10 -> 0.42173437 | K16: =+K15/K$10 -> 0.46153715 | L16: =+L15/L$10 -> 0.44997552 | M16: =+M15/M$10 -> 0.3941834 | ... T16: =+T15/T$10 -> 0.36736372
B18: (Depreciation) | F18: =Restatements!C46 -> -24.875 | G18: =Restatements!D46 -> -27.141 | H18: =Restatements!E46 -> -29.666 | I18: =Restatements!F46 -> -28.531 | J18: =Restatements!G46 -> -35.132 | K18: =Restatements!H46 -> -33.558 | L18: =Restatements!I46 -> -47.131 | M18: =Restatements!J46 -> -60.404 | ... O18: =Restatements!L46 -> -53.871 | P18: =Investments!P32 -> -29.884697 | Q18: =Investments!Q32 -> -65.787947 | R18: =Investments!R32 -> -78.415345 | S18: =Investments!S32 -> -91.674112 | T18: =Investments!T32 -> -105.59582
B19: (Amortization) | F19: =Restatements!C47 -> -8.109 | G19: =Restatements!D47 -> -17.566 | H19: =Restatements!E47 -> -16.185 | I19: =Restatements!F47 -> -16.844 | J19: =Restatements!G47 -> -17.644 | K19: =Restatements!H47 -> -25.255 | L19: =Restatements!I47 -> -36.275 | M19: =Restatements!J47 -> -58.94 | ... O19: =Restatements!L47 -> -75.17 | P19: =Investments!P36 -> -75.172627 | Q19: =Investments!Q36 -> -74.452287 | R19: =Investments!R36 -> -73.861915 | S19: =Investments!S36 -> -73.401857 | T19: =Investments!T36 -> -73.072706
B20: EBIT | F20: =+F15+F19+F18 -> 173.727 | G20: =+G15+G19+G18 -> 196.405 | H20: =+H15+H19+H18 -> 221.316 | I20: =+I15+I19+I18 -> 231.982 | J20: =+J15+J19+J18 -> 245.103 | K20: =+K15+K19+K18 -> 347.942 | L20: =+L15+L19+L18 -> 473.508 | M20: =+M15+M19+M18 -> 417.194 | ... T20: =+T15+T19+T18 -> 357.17095
B21: Margin | F21: =+F20/F$10 -> 0.34802406 | G21: =+G20/G$10 -> 0.34498658 | H21: =+H20/H$10 -> 0.34716943 | I21: =+I20/I$10 -> 0.34665726 | J21: =+J20/J$10 -> 0.34701459 | K21: =+K20/K$10 -> 0.39480316 | L21: =+L20/L$10 -> 0.38258512 | M21: =+M20/M$10 -> 0.30650382 | ... T21: =+T20/T$10 -> 0.24487119
B23: Interest income | F23: =Restatements!C51+Restatements!C52 -> -1.442 | G23: =Restatements!D51+Restatements!D52 -> 1.603 | H23: =Restatements!E51+Restatements!E52 -> -2.923 | I23: =Restatements!F51+Restatements!F52 -> 1.983 | J23: =Restatements!G51+Restatements!G52 -> -1.342 | K23: =Restatements!H51+Restatements!H52 -> -2.391 | L23: =Restatements!I51+Restatements!I52 -> -1.482 | M23: =Restatements!J51+Restatements!J52 -> -1.824 | ... O23: =Restatements!L51+Restatements!L52 -> -1.173 | P23: =AVERAGE(F23:O23) -> -0.2381 | Q23: =AVERAGE(G23:P23) -> -0.11771 | R23: =AVERAGE(H23:Q23) -> -0.289781 | S23: =AVERAGE(I23:R23) -> -0.0264591 | T23: =AVERAGE(J23:S23) -> -0.22740501
B24: (Interest expenses) | F24: =Restatements!C55+Restatements!C53 -> -4.39 | G24: =Restatements!D55+Restatements!D53 -> -8.531 | H24: =Restatements!E55+Restatements!E53 -> -16.155 | I24: =Restatements!F55+Restatements!F53 -> -6.027 | J24: =Restatements!G55+Restatements!G53 -> -8.579 | K24: =Restatements!H55+Restatements!H53 -> -9.314 | L24: =Restatements!I55+Restatements!I53 -> -43.716 | M24: =Restatements!J55+Restatements!J53 -> -54.452 | ... O24: =Restatements!L55+Restatements!L53 -> -34.031 | P24: =+Financing!J27 -> -62.04382 | Q24: =+Financing!K27 -> -61.632259 | R24: =+Financing!L27 -> -61.735774 | S24: =+Financing!M27 -> -61.844464 | T24: =+Financing!N27 -> -61.958588
B25: Other | F25: =Restatements!C54 -> -0.431 | G25: =Restatements!D54 -> -0.555 | H25: =Restatements!E54 -> -0.404 | I25: =Restatements!F54 -> -0.143 | J25: =Restatements!G54 -> -0.115 | K25: =Restatements!H54 -> 0 | L25: =Restatements!I54 -> 0 | M25: =Restatements!J54 -> 0 | ... O25: =Restatements!L54 -> 0 | P25: =+Others!J14 -> 0 | Q25: =+Others!K14 -> 0 | R25: =+Others!L14 -> 0 | S25: =+Others!M14 -> 0 | T25: =+Others!N14 -> 0
B26: EBT | F26: =+F20+SUM(F23:F25) -> 167.464 | G26: =+G20+SUM(G23:G25) -> 188.922 | H26: =+H20+SUM(H23:H25) -> 201.834 | I26: =+I20+SUM(I23:I25) -> 227.795 | J26: =+J20+SUM(J23:J25) -> 235.067 | K26: =+K20+SUM(K23:K25) -> 336.237 | L26: =+L20+SUM(L23:L25) -> 428.31 | M26: =+M20+SUM(M23:M25) -> 360.918 | ... T26: =+T20+SUM(T23:T25) -> 294.98496
B28: (Income taxes) | F28: =Restatements!C60 -> -49.554 | G28: =Restatements!D60 -> -55.578 | H28: =Restatements!E60 -> -38.828 | I28: =Restatements!F60 -> -46.235 | J28: =Restatements!G60 -> -40.552 | K28: =Restatements!H60 -> -73.077 | L28: =Restatements!I60 -> -88.603 | M28: =Restatements!J60 -> -85.83 | ... O28: =Restatements!L60 -> -55.391 | P28: =+Others!J23 -> -66.533875 | Q28: =+Others!K23 -> -64.063319 | R28: =+Others!L23 -> -79.201801 | S28: =+Others!M23 -> -82.496738 | T28: =+Others!N23 -> -84.726057
B29: Net income | F29: =+F26+F28 -> 117.91 | G29: =+G26+G28 -> 133.344 | H29: =+H26+H28 -> 163.006 | I29: =+I26+I28 -> 181.56 | J29: =+J26+J28 -> 194.515 | K29: =+K26+K28 -> 263.16 | L29: =+L26+L28 -> 339.707 | M29: =+M26+M28 -> 275.088 | ... T29: =+T26+T28 -> 210.2589
B30: Margin | F30: =+F29/F$10 -> 0.23620691 | G30: =+G29/G$10 -> 0.23421955 | H30: =+H29/H$10 -> 0.2557009 | I30: =+I29/I$10 -> 0.27131024 | J30: =+J29/J$10 -> 0.27539256 | K30: =+K29/K$10 -> 0.29860264 | L30: =+L29/L$10 -> 0.27447655 | M30: =+M29/M$10 -> 0.20210148 | ... T30: =+T29/T$10 -> 0.14415043
B32: Dividend distribution | F32: =Restatements!C65 -> 0.65 | G32: =Restatements!D65 -> 0.8 | H32: =Restatements!E65 -> 0.85 | I32: =Restatements!F65 -> 0.9 | J32: =Restatements!G65 -> 0.95 | K32: =Restatements!H65 -> 1 | L32: =Restatements!I65 -> 1.05 | M32: =Restatements!J65 -> 1.1 | ... O32: =Restatements!L65 -> 1.2 | P32: =Financing!J11 -> 0.91926471 | Q32: =Financing!K11 -> 0.88372848 | R32: =Financing!L11 -> 1.1038279 | S32: =Financing!M11 -> 1.1519022 | T32: =Financing!N11 -> 1.1840983
B33: Retained portion | F33: =+F29-F32 -> 117.26 | G33: =+G29-G32 -> 132.544 | H33: =+H29-H32 -> 162.156 | I33: =+I29-I32 -> 180.66 | J33: =+J29-J32 -> 193.565 | K33: =+K29-K32 -> 262.16 | L33: =+L29-L32 -> 338.657 | M33: =+M29-M32 -> 273.988 | ... T33: =+T29-T32 -> 209.0748
B35: Balance sheet
B37: Trade receivables | F37: =Restatements!C70 -> 105.609 | G37: =Restatements!D70 -> 120.261 | H37: =Restatements!E70 -> 147.24 | I37: =Restatements!F70 -> 136.244 | J37: =Restatements!G70 -> 140.5 | K37: =Restatements!H70 -> 166.687 | L37: =Restatements!I70 -> 226.249 | M37: =Restatements!J70 -> 241.353 | ... O37: =Restatements!L70 -> 204.111 | P37: =+Investments!P10 -> 219.47591 | Q37: =+Investments!Q10 -> 230.4497 | R37: =+Investments!R10 -> 241.97219 | S37: =+Investments!S10 -> 254.0708 | T37: =+Investments!T10 -> 266.77434
B38: (Trade payables) | F38: =Restatements!C71 -> -40.775 | G38: =Restatements!D71 -> -47.674 | H38: =Restatements!E71 -> -62.331 | I38: =Restatements!F71 -> -57.286 | J38: =Restatements!G71 -> -55.733 | K38: =Restatements!H71 -> -65.485 | L38: =Restatements!I71 -> -84.773 | M38: =Restatements!J71 -> -104.204 | ... O38: =Restatements!L71 -> -99.52 | P38: =+Investments!P11 -> -113.34779 | Q38: =+Investments!Q11 -> -119.01518 | R38: =+Investments!R11 -> -123.19818 | S38: =+Investments!S11 -> -129.35809 | T38: =+Investments!T11 -> -135.826
B39: Inventory | F39: =Restatements!C72 -> 106.193 | G39: =Restatements!D72 -> 128.87 | H39: =Restatements!E72 -> 142.802 | I39: =Restatements!F72 -> 160.396 | J39: =Restatements!G72 -> 171.127 | K39: =Restatements!H72 -> 191.234 | L39: =Restatements!I72 -> 298.049 | M39: =Restatements!J72 -> 306.503 | ... O39: =Restatements!L72 -> 344.043 | P39: =+Investments!P12 -> 265.24131 | Q39: =+Investments!Q12 -> 278.50337 | R39: =+Investments!R12 -> 292.42854 | S39: =+Investments!S12 -> 307.04997 | T39: =+Investments!T12 -> 322.40247
B40: Other current assets & liabilities | F40: =Restatements!C73 -> -20.808 | G40: =Restatements!D73 -> -31.588 | H40: =Restatements!E73 -> -31.804 | I40: =Restatements!F73 -> -29.357 | J40: =Restatements!G73 -> -34.14 | K40: =Restatements!H73 -> -44.699 | L40: =Restatements!I73 -> -75.817 | M40: =Restatements!J73 -> -35.438 | ... O40: =Restatements!L73 -> -84.167 | P40: =+Investments!P13 -> -60.614777 | Q40: =+Investments!Q13 -> -63.645515 | R40: =+Investments!R13 -> -66.827791 | S40: =+Investments!S13 -> -70.169181 | T40: =+Investments!T13 -> -73.67764
B41: (Deferred taxes) | F41: =Restatements!C74 -> 18.149 | G41: =Restatements!D74 -> 21.588 | H41: =Restatements!E74 -> 20.272 | I41: =Restatements!F74 -> 15.908 | J41: =Restatements!G74 -> 24.512 | K41: =Restatements!H74 -> 23.014 | L41: =Restatements!I74 -> -147.107 | M41: =Restatements!J74 -> -194.851 | ... O41: =Restatements!L74 -> -167.969 | P41: =+Investments!P15 -> -167.969 | Q41: =+Investments!Q15 -> -167.969 | R41: =+Investments!R15 -> -167.969 | S41: =+Investments!S15 -> -167.969 | T41: =+Investments!T15 -> -167.969
B42: (Long term provisions) | F42: =Restatements!C76 -> -35.021 | G42: =Restatements!D76 -> -41.584 | H42: =Restatements!E76 -> -32.532 | I42: =Restatements!F76 -> -32.659 | J42: =Restatements!G76 -> -36.263 | K42: =Restatements!H76 -> -41.242 | L42: =Restatements!I76 -> -40.917 | M42: =Restatements!J76 -> -62.753 | ... O42: =Restatements!L76 -> -54.663 | P42: =+Investments!P16 -> -54.663 | Q42: =+Investments!Q16 -> -54.663 | R42: =+Investments!R16 -> -54.663 | S42: =+Investments!S16 -> -54.663 | T42: =+Investments!T16 -> -54.663
B43: Noncash working capital | F43: =SUM(F37:F42) -> 133.347 | G43: =SUM(G37:G42) -> 149.873 | H43: =SUM(H37:H42) -> 183.647 | I43: =SUM(I37:I42) -> 193.246 | J43: =SUM(J37:J42) -> 210.003 | K43: =SUM(K37:K42) -> 229.509 | L43: =SUM(L37:L42) -> 175.684 | M43: =SUM(M37:M42) -> 150.61 | ... T43: =SUM(T37:T42) -> 157.04117
B45: Tangible assets | F45: =Restatements!C79 -> 74.493 | G45: =Restatements!D79 -> 92.134 | H45: =Restatements!E79 -> 92.332 | I45: =Restatements!F79 -> 94.981 | J45: =Restatements!G79 -> 128.385 | K45: =Restatements!H79 -> 140.497 | L45: =Restatements!I79 -> 276.197 | M45: =Restatements!J79 -> 268.448 | ... O45: =Restatements!L79 -> 271.359 | P45: =+Investments!P24 -> 297.53806 | Q45: =+Investments!Q24 -> 290.61707 | R45: =+Investments!R24 -> 274.01202 | S45: =+Investments!S24 -> 247.23872 | T45: =+Investments!T24 -> 209.78875
B46: Goodwill and trademarks | F46: =Restatements!C80+Restatements!C81 -> 117.906 | G46: =Restatements!D80+Restatements!D81 -> 357.086 | H46: =Restatements!E80+Restatements!E81 -> 344.35 | I46: =Restatements!F80+Restatements!F81 -> 373.084 | J46: =Restatements!G80+Restatements!G81 -> 370.279 | K46: =Restatements!H80+Restatements!H81 -> 356.737 | L46: =Restatements!I80+Restatements!I81 -> 1943.369 | M46: =Restatements!J80+Restatements!J81 -> 1995.063 | ... O46: =Restatements!L80+Restatements!L81 -> 2028.486 | P46: =+Investments!P37 -> 2009.0481 | Q46: =+Investments!Q37 -> 1993.1173 | R46: =+Investments!R37 -> 1980.7029 | S46: =+Investments!S37 -> 1971.821 | T46: =+Investments!T37 -> 1966.4942
B47: Fixed assets | F47: =SUM(F45:F46) -> 192.399 | G47: =SUM(G45:G46) -> 449.22 | H47: =SUM(H45:H46) -> 436.682 | I47: =SUM(I45:I46) -> 468.065 | J47: =SUM(J45:J46) -> 498.664 | K47: =SUM(K45:K46) -> 497.234 | L47: =SUM(L45:L46) -> 2219.566 | M47: =SUM(M45:M46) -> 2263.511 | ... T47: =SUM(T45:T46) -> 2176.2829
B49: Core capital employed | F49: =+F47+F43 -> 325.746 | G49: =+G47+G43 -> 599.093 | H49: =+H47+H43 -> 620.329 | I49: =+I47+I43 -> 661.311 | J49: =+J47+J43 -> 708.667 | K49: =+K47+K43 -> 726.743 | L49: =+L47+L43 -> 2395.25 | M49: =+M47+M43 -> 2414.121 | ... T49: =+T47+T43 -> 2333.3241
B51: Associates | F51: =Restatements!C86 -> 0.219 | G51: =Restatements!D86 -> 0.027 | H51: =Restatements!E86 -> 0.027 | I51: =Restatements!F86 -> 0.027 | J51: =Restatements!G86 -> 0.027 | K51: =Restatements!H86 -> 0.026 | L51: =Restatements!I86 -> 10.742 | M51: =Restatements!J86 -> 32.182 | ... O51: =Restatements!L86 -> 3.589 | P51: =+Others!J10 -> 3.589 | Q51: =+Others!K10 -> 3.589 | R51: =+Others!L10 -> 3.589 | S51: =+Others!M10 -> 3.589 | T51: =+Others!N10 -> 3.589
B52: Other non-operational assets | F52: =Restatements!C87 -> -1.238 | G52: =Restatements!D87 -> -6.477 | H52: =Restatements!E87 -> -28.115 | I52: =Restatements!F87 -> -24.963 | J52: =Restatements!G87 -> -24.586 | K52: =Restatements!H87 -> -48.155 | L52: =Restatements!I87 -> -43.983 | M52: =Restatements!J87 -> -22.99 | ... O52: =Restatements!L87 -> -9.582 | P52: =+Others!J11 -> 2.701 | Q52: =+Others!K11 -> 2.701 | R52: =+Others!L11 -> 2.701 | S52: =+Others!M11 -> 2.701 | T52: =+Others!N11 -> 2.701
B53: (Employee severance) | F53: =Restatements!C88 -> 0.758 | G53: =Restatements!D88 -> 0.999 | H53: =Restatements!E88 -> 5.602 | I53: =Restatements!F88 -> 2.03 | J53: =Restatements!G88 -> 2.453 | K53: =Restatements!H88 -> 2.189 | L53: =Restatements!I88 -> 4.323 | M53: =Restatements!J88 -> 48.99 | ... O53: =Restatements!L88 -> 2.701 | P53: 0 | Q53: 0 | R53: 0 | S53: 0 | T53: 0
B54: Surplus assets and other liabilities | F54: =SUM(F51:F53) -> -0.261 | G54: =SUM(G51:G53) -> -5.451 | H54: =SUM(H51:H53) -> -22.486 | I54: =SUM(I51:I53) -> -22.906 | J54: =SUM(J51:J53) -> -22.106 | K54: =SUM(K51:K53) -> -45.94 | L54: =SUM(L51:L53) -> -28.918 | M54: =SUM(M51:M53) -> 58.182 | ... T54: =SUM(T51:T53) -> 6.29
B56: Net capital employed | F56: =+F54+F49 -> 325.485 | G56: =+G54+G49 -> 593.642 | H56: =+H54+H49 -> 597.843 | I56: =+I54+I49 -> 638.405 | J56: =+J54+J49 -> 686.561 | K56: =+K54+K49 -> 680.803 | L56: =+L54+L49 -> 2366.332 | M56: =+M54+M49 -> 2472.303 | ... T56: =+T54+T49 -> 2339.6141
B58: ST financial debt | F58: =Restatements!C93 -> 2.3 | G58: =Restatements!D93 -> 26.512 | H58: =Restatements!E93 -> 23.91 | I58: =Restatements!F93 -> 20.601 | J58: =Restatements!G93 -> 4.812 | K58: =Restatements!H93 -> 4.209 | L58: =Restatements!I93 -> 100.411 | M58: =Restatements!J93 -> 120.02 | ... O58: =Restatements!L93 -> 47.784 | P58: =+Financing!J24 -> 32.784277 | Q58: =+Financing!K24 -> 34.423491 | R58: =+Financing!L24 -> 36.144666 | S58: =+Financing!M24 -> 37.951899 | T58: =+Financing!N24 -> 39.849494
B59: Bank loans | F59: 0 | G59: 0 | H59: 0 | I59: 0 | J59: 0 | K59: 0 | L59: 0 | M59: 0 | N59: 0 | O59: 0 | P59: 0 | Q59: 0 | R59: 0 | S59: 0 | T59: 0
B60: Bonds and securities | F60: =Restatements!C94 -> 0 | G60: =Restatements!D94 -> 23.888 | H60: =Restatements!E94 -> 0.102 | I60: =Restatements!F94 -> 0.081 | J60: =Restatements!G94 -> 24.466 | K60: =Restatements!H94 -> 30.451 | L60: =Restatements!I94 -> 1294.747 | M60: =Restatements!J94 -> 1231.965 | ... O60: =Restatements!L94 -> 966.781 | P60: =+Financing!J25 -> 966.781 | Q60: =+Financing!K25 -> 966.781 | R60: =+Financing!L25 -> 966.781 | S60: =+Financing!M25 -> 966.781 | T60: =+Financing!N25 -> 966.781
B61: Gross financial debt | F61: =SUM(F58:F60) -> 2.3 | G61: =SUM(G58:G60) -> 50.4 | H61: =SUM(H58:H60) -> 24.012 | I61: =SUM(I58:I60) -> 20.682 | J61: =SUM(J58:J60) -> 29.278 | K61: =SUM(K58:K60) -> 34.66 | L61: =SUM(L58:L60) -> 1395.158 | M61: =SUM(M58:M60) -> 1351.985 | ... T61: =SUM(T58:T60) -> 1006.6305
B62: (Excess cash & equivalents) | F62: =-Restatements!C96 -> -270.357 | G62: =-Restatements!D96 -> -130.468 | H62: =-Restatements!E96 -> -173.314 | I62: =-Restatements!F96 -> -96.525 | J62: =-Restatements!G96 -> -202.14 | K62: =-Restatements!H96 -> -340.007 | L62: =-Restatements!I96 -> -403.02 | M62: =-Restatements!J96 -> -413.218 | ... O62: =-Restatements!L96 -> -393.268 | P62: =-Financing!J35 -> -577.97092 | Q62: =-Financing!K35 -> -742.96309 | R62: =-Financing!L35 -> -950.52288 | S62: =-Financing!M35 -> -1174.1566 | T62: =-Financing!N35 -> -1409.8261
B63: Net debt | F63: =+SUM(F61:F62) -> -268.057 | G63: =+SUM(G61:G62) -> -80.068 | H63: =+SUM(H61:H62) -> -149.302 | I63: =+SUM(I61:I62) -> -75.843 | J63: =+SUM(J61:J62) -> -172.862 | K63: =+SUM(K61:K62) -> -305.347 | L63: =+SUM(L61:L62) -> 992.138 | M63: =+SUM(M61:M62) -> 938.767 | ... T63: =+SUM(T61:T62) -> -403.19558
B65: Share capital | F65: =Restatements!C99 -> 106.202 | G65: =Restatements!D99 -> 118.095 | H65: =Restatements!E99 -> 76.601 | I65: =Restatements!F99 -> 92.773 | J65: =Restatements!G99 -> 101.29 | K65: =Restatements!H99 -> 54.995 | L65: =Restatements!I99 -> 200.999 | M65: =Restatements!J99 -> 225.25 | ... O65: =Restatements!L99 -> 221.031 | P65: =+Financing!J20 -> 221.031 | Q65: =+Financing!K20 -> 221.031 | R65: =+Financing!L20 -> 221.031 | S65: =+Financing!M20 -> 221.031 | T65: =+Financing!N20 -> 221.031
B66: Retained earnings | F66: =Restatements!C100 -> 480.612 | G66: =Restatements!D100 -> 544.722 | H66: =Restatements!E100 -> 664.816 | I66: =Restatements!F100 -> 611.96 | J66: =Restatements!G100 -> 747.333 | K66: =Restatements!H100 -> 899.683 | L66: =Restatements!I100 -> 1165.378 | M66: =Restatements!J100 -> 1293.739 | ... O66: =Restatements!L100 -> 1579.887 | P66: =+Financing!J17 -> 1742.2005 | Q66: =+Financing!K17 -> 1898.2393 | R66: =+Financing!L17 -> 2093.1409 | S66: =+Financing!M17 -> 2296.5308 | T66: =+Financing!N17 -> 2505.6056
B67: Group equity | F67: =SUM(F65:F66) -> 586.814 | G67: =SUM(G65:G66) -> 662.817 | H67: =SUM(H65:H66) -> 741.417 | I67: =SUM(I65:I66) -> 704.733 | J67: =SUM(J65:J66) -> 848.623 | K67: =SUM(K65:K66) -> 954.678 | L67: =SUM(L65:L66) -> 1366.377 | M67: =SUM(M65:M66) -> 1518.989 | ... T67: =SUM(T65:T66) -> 2726.6366
B68: Minorities | F68: =Restatements!C103 -> 0.344 | G68: =Restatements!D103 -> 0.568 | H68: =Restatements!E103 -> 0.538 | I68: =Restatements!F103 -> 0.002 | J68: =Restatements!G103 -> 0 | K68: =Restatements!H103 -> 1.641 | L68: =Restatements!I103 -> 1.562 | M68: =Restatements!J103 -> 0.761 | ... O68: =Restatements!L103 -> -1.896 | P68: =+Financing!J19 -> -1.896 | Q68: =+Financing!K19 -> -1.896 | R68: =+Financing!L19 -> -1.896 | S68: =+Financing!M19 -> -1.896 | T68: =+Financing!N19 -> -1.896
B69: Total equity | F69: =+F68+F67 -> 587.158 | G69: =+G68+G67 -> 663.385 | H69: =+H68+H67 -> 741.955 | I69: =+I68+I67 -> 704.735 | J69: =+J68+J67 -> 848.623 | K69: =+K68+K67 -> 956.319 | L69: =+L68+L67 -> 1367.939 | M69: =+M68+M67 -> 1519.75 | ... T69: =+T68+T67 -> 2724.7406
B71: Total funds invested | F71: =+F69+F63 -> 319.101 | G71: =+G69+G63 -> 583.317 | H71: =+H69+H63 -> 592.653 | I71: =+I69+I63 -> 628.892 | J71: =+J69+J63 -> 675.761 | K71: =+K69+K63 -> 650.972 | L71: =+L69+L63 -> 2360.077 | M71: =+M69+M63 -> 2458.517 | ... T71: =+T69+T63 -> 2321.5451
B73: Check | F73: =+F71-F56 -> -6.384 | G73: =+G71-G56 -> -10.325 | H73: =+H71-H56 -> -5.19 | I73: =+I71-I56 -> -9.513 | J73: =+J71-J56 -> -10.8 | K73: =+K71-K56 -> -29.831 | L73: =+L71-L56 -> -6.255 | M73: =+M71-M56 -> -13.786 | ... T73: =+T71-T56 -> -18.069
B75: Cash flows
B77: EBIT | P77: =+P20 -> 292.04851 | Q77: =+Q20 -> 282.73588 | R77: =+R20 -> 337.23274 | S77: =+S20 -> 348.90953 | T77: =+T20 -> 357.17095
B78: (Operational taxes) | P78: =+-P77*SUM(Assumptions!$F$47:$F$48) -> -81.481536 | Q78: =+-Q77*SUM(Assumptions!$F$47:$F$48) -> -78.883311 | R78: =+-R77*SUM(Assumptions!$F$47:$F$48) -> -94.087934 | S78: =+-S77*SUM(Assumptions!$F$47:$F$48) -> -97.345759 | T78: =+-T77*SUM(Assumptions!$F$47:$F$48) -> -99.650696
B79: NOPAT | P79: =SUM(P77:P78) -> 210.56698 | Q79: =SUM(Q77:Q78) -> 203.85257 | R79: =SUM(R77:R78) -> 243.14481 | S79: =SUM(S77:S78) -> 251.56377 | T79: =SUM(T77:T78) -> 257.52026
B80: Depreciation | P80: =-P18 -> 29.884697 | Q80: =-Q18 -> 65.787947 | R80: =-R18 -> 78.415345 | S80: =-S18 -> 91.674112 | T80: =-T18 -> 105.59582
B81: Amortization | P81: =-P19 -> 75.172627 | Q81: =-Q19 -> 74.452287 | R81: =-R19 -> 73.861915 | S81: =-S19 -> 73.401857 | T81: =-T19 -> 73.072706
B82: Gross cash flows | P82: =SUM(P79:P81) -> 315.6243 | Q82: =SUM(Q79:Q81) -> 344.09281 | R82: =SUM(R79:R81) -> 395.42207 | S82: =SUM(S79:S81) -> 416.63974 | T82: =SUM(T79:T81) -> 436.18878
B84: (Increase) and decrease in noncash WC | P84: =-(P43-O43) -> 53.712353 | Q84: =-(Q43-P43) -> -15.537732 | R84: =-(R43-Q43) -> -18.082377 | S84: =-(S43-R43) -> -17.218738 | T84: =-(T43-S43) -> -18.079675
B85: - Tangible CAPEX | P85: =-((P45-O45)+P80) -> -56.063761 | Q85: =-((Q45-P45)+Q80) -> -58.866949 | R85: =-((R45-Q45)+R80) -> -61.810296 | S85: =-((S45-R45)+S80) -> -64.900811 | T85: =-((T45-S45)+T80) -> -68.145852
B86: - Intangible CAPEX | P86: =-((P46-O46)+P81) -> -55.734726 | Q86: =-((Q46-P46)+Q81) -> -58.521462 | R86: =-((R46-Q46)+R81) -> -61.447536 | S86: =-((S46-R46)+S81) -> -64.519912 | T86: =-((T46-S46)+T81) -> -67.745908
B87: FCFO | P87: =+SUM(P82:P86) -> 257.53817 | Q87: =+SUM(Q82:Q86) -> 211.16666 | R87: =+SUM(R82:R86) -> 254.08186 | S87: =+SUM(S82:S86) -> 270.00028 | T87: =+SUM(T82:T86) -> 282.21735
B89: Tax shields | P89: =+P28-P78 -> 14.947661 | Q89: =+Q28-Q78 -> 14.819993 | R89: =+R28-R78 -> 14.886133 | S89: =+S28-S78 -> 14.849021 | T89: =+T28-T78 -> 14.924638
B90: Interest income | P90: =+P23 -> -0.2381 | Q90: =+Q23 -> -0.11771 | R90: =+R23 -> -0.289781 | S90: =+S23 -> -0.0264591 | T90: =+T23 -> -0.22740501
B91: (Interest expenses) | P91: =+P24 -> -62.04382 | Q91: =+Q24 -> -61.632259 | R91: =+R24 -> -61.735774 | S91: =+S24 -> -61.844464 | T91: =+T24 -> -61.958588
B92: Income from associates | P92: =0 -> 0 | Q92: =0 -> 0 | R92: =0 -> 0 | S92: =0 -> 0 | T92: =0 -> 0
B93: Except. items | P93: =+P25 -> 0 | Q93: =+Q25 -> 0 | R93: =+R25 -> 0 | S93: =+S25 -> 0 | T93: =+T25 -> 0
B94: Increase and (decrease) in gross debt | P94: =+(P61-O61) -> -14.999723 | Q94: =+(Q61-P61) -> 1.6392139 | R94: =+(R61-Q61) -> 1.7211746 | S94: =+(S61-R61) -> 1.8072333 | T94: =+(T61-S61) -> 1.897595
B95: (Increase) and decrease in surplus assets and other liabilities | P95: =-(P54-O54) -> -9.582 | Q95: =-(Q54-P54) -> 0 | R95: =-(R54-Q54) -> 0 | S95: =-(S54-R54) -> 0 | T95: =-(T54-S54) -> 0
B96: FCFE | P96: =+SUM(P87:P95) -> 185.62219 | Q96: =+SUM(Q87:Q95) -> 165.8759 | R96: =+SUM(R87:R95) -> 208.66361 | S96: =+SUM(S87:S95) -> 224.78561 | T96: =+SUM(T87:T95) -> 236.85359
B98: (Dividends) | P98: =-P32 -> -0.91926471 | Q98: =-Q32 -> -0.88372848 | R98: =-R32 -> -1.1038279 | S98: =-S32 -> -1.1519022 | T98: =-T32 -> -1.1840983
B99: Other movements in group equity | P99: =+P67-O67-P29+P32 -> -1.1490808e-13 | Q99: =+Q67-P67-Q29+Q32 -> 3.0619951e-13 | R99: =+R67-Q67-R29+R32 -> -1.2034818e-13 | S99: =+S67-R67-S29+S32 -> 2.469136e-13 | T99: =+T67-S67-T29+T32 -> -2.1183055e-13
B100: Change in minorities | P100: =+P68-O68 -> 0 | Q100: =+Q68-P68 -> 0 | R100: =+R68-Q68 -> 0 | S100: =+S68-R68 -> 0 | T100: =+T68-S68 -> 0
B102: Change in cash | P102: =+SUM(P96:P100) -> 184.70292 | Q102: =+SUM(Q96:Q100) -> 164.99217 | R102: =+SUM(R96:R100) -> 207.55978 | S102: =+SUM(S96:S100) -> 223.63371 | T102: =+SUM(T96:T100) -> 235.66949
B103: Check | P103: =+P102+(P62-O62) -> 0 | Q103: =+Q102+(Q62-P62) -> 0 | R103: =+R102+(R62-Q62) -> 0 | S103: =+S102+(S62-R62) -> 0 | T103: =+T102+(T62-S62) -> 0

Sheet Sheet1

Sheet Analysis
B2: Financial Analysis
F3: Historicals | P3: Explicit forecast
B5: =[1]AsReported!B5 -> (EUR m) | F5: 42192 | G5: =F5+365 -> 42557 | H5: =G5+365 -> 42922 | I5: =H5+365 -> 43287 | J5: =I5+365 -> 43652 | K5: =J5+365 -> 44017 | L5: =K5+365 -> 44382 | M5: =L5+365 -> 44747 | N5: =M5+365 -> 45112 | ... T5: =S5+365 -> 47302
B8: Value creation and profitability analysis
B10: Sales growth | M10: =+'Output (2)'!M11 -> 0.099772634 | N10: =+'Output (2)'!N11 -> -0.15643381 | O10: =+'Output (2)'!O11 -> 0.03241306 | P10: =+'Output (2)'!P11 -> 0.01229346 | Q10: =+'Output (2)'!Q11 -> 0.05 | R10: =+'Output (2)'!R11 -> 0.05 | S10: =+'Output (2)'!S11 -> 0.05 | T10: =+'Output (2)'!T11 -> 0.05
B11: EBITDA margin | F11: =+'Output (2)'!F16 -> 0.4141003 | M11: =+'Output (2)'!M16 -> 0.3941834 | N11: =+'Output (2)'!N16 -> 0.34507625 | O11: =+'Output (2)'!O16 -> 0.3490953 | P11: =+'Output (2)'!P16 -> 0.33092153 | Q11: =+'Output (2)'!Q16 -> 0.33569533 | R11: =+'Output (2)'!R16 -> 0.37 | S11: =+'Output (2)'!S16 -> 0.37 | T11: =+'Output (2)'!T16 -> 0.36736372
B12: EBIT margin | F12: =+'Output (2)'!F21 -> 0.34802406 | M12: =+'Output (2)'!M21 -> 0.30650382 | N12: =+'Output (2)'!N21 -> 0.24489771 | O12: =+'Output (2)'!O21 -> 0.24023917 | P12: =+'Output (2)'!P21 -> 0.24337376 | Q12: =+'Output (2)'!Q21 -> 0.22439356 | R12: =+'Output (2)'!R21 -> 0.25490003 | S12: =+'Output (2)'!S21 -> 0.25116764 | T12: =+'Output (2)'!T21 -> 0.24487119
B13: Net income margin | F13: =+'Output (2)'!F30 -> 0.23620691 | M13: =+'Output (2)'!M30 -> 0.20210148 | N13: =+'Output (2)'!N30 -> 0.17759295 | O13: =+'Output (2)'!O30 -> 0.16381523 | P13: =+'Output (2)'!P30 -> 0.13602727 | Q13: =+'Output (2)'!Q30 -> 0.12454174 | R13: =+'Output (2)'!R30 -> 0.14815222 | S13: =+'Output (2)'!S30 -> 0.14724247 | T13: =+'Output (2)'!T30 -> 0.14415043
B15: Investment analysis - CAPEX
B17: Total CAPEX | M17: =-'Output (2)'!M86-'Output (2)'!M85 -> 0 | N17: =-'Output (2)'!N86-'Output (2)'!N85 -> 0 | O17: =-'Output (2)'!O86-'Output (2)'!O85 -> 0 | P17: =-'Output (2)'!P86-'Output (2)'!P85 -> 111.79849 | Q17: =-'Output (2)'!Q86-'Output (2)'!Q85 -> 117.38841 | R17: =-'Output (2)'!R86-'Output (2)'!R85 -> 123.25783 | S17: =-'Output (2)'!S86-'Output (2)'!S85 -> 129.42072 | T17: =-'Output (2)'!T86-'Output (2)'!T85 -> 135.89176
B18: D&A | M18: =+'Output (2)'!M81+'Output (2)'!M80 -> 0 | N18: =+'Output (2)'!N81+'Output (2)'!N80 -> 0 | O18: =+'Output (2)'!O81+'Output (2)'!O80 -> 0 | P18: =+'Output (2)'!P81+'Output (2)'!P80 -> 105.05732 | Q18: =+'Output (2)'!Q81+'Output (2)'!Q80 -> 140.24023 | R18: =+'Output (2)'!R81+'Output (2)'!R80 -> 152.27726 | S18: =+'Output (2)'!S81+'Output (2)'!S80 -> 165.07597 | T18: =+'Output (2)'!T81+'Output (2)'!T80 -> 178.66852
B20: Expanding or downsizing? | M20: =+IF(M17>M18,"Expanding",IF(M17<M18,"Downsizing","Neither")) -> Neither | N20: =+IF(N17>N18,"Expanding",IF(N17<N18,"Downsizing","Neither")) -> Neither | O20: =+IF(O17>O18,"Expanding",IF(O17<O18,"Downsizing","Neither")) -> Neither | P20: =+IF(P17>P18,"Expanding",IF(P17<P18,"Downsizing","Neither")) -> Expanding | Q20: =+IF(Q17>Q18,"Expanding",IF(Q17<Q18,"Downsizing","Neither")) -> Downsizing | R20: =+IF(R17>R18,"Expanding",IF(R17<R18,"Downsizing","Neither")) -> Downsizing | S20: =+IF(S17>S18,"Expanding",IF(S17<S18,"Downsizing","Neither")) -> Downsizing | T20: =+IF(T17>T18,"Expanding",IF(T17<T18,"Downsizing","Neither")) -> Downsizing
B21: Is the company divesting? | M21: =+IF(M17>0,"No","Yes") -> Yes | N21: =+IF(N17>0,"No","Yes") -> Yes | O21: =+IF(O17>0,"No","Yes") -> Yes | P21: =+IF(P17>0,"No","Yes") -> No | Q21: =+IF(Q17>0,"No","Yes") -> No | R21: =+IF(R17>0,"No","Yes") -> No | S21: =+IF(S17>0,"No","Yes") -> No | T21: =+IF(T17>0,"No","Yes") -> No
B23: D&A as a % of CAPEX | M23: =+M18/M17 -> #DIV/0! | N23: =+N18/N17 -> #DIV/0! | O23: =+O18/O17 -> #DIV/0! | P23: =+P18/P17 -> 0.93970256 | Q23: =+Q18/Q17 -> 1.1946685 | R23: =+R18/R17 -> 1.2354368 | S23: =+S18/S17 -> 1.2754987 | T23: =+T18/T17 -> 1.3147856
B24: D&A as a % average fixed asset | M24: =+M18/AVERAGE('Output (2)'!F47:M47) -> 0 | N24: =+N18/AVERAGE('Output (2)'!M47:N47) -> 0 | O24: =+O18/AVERAGE('Output (2)'!N47:O47) -> 0 | P24: =+P18/AVERAGE('Output (2)'!O47:P47) -> 0.045613326 | Q24: =+Q18/AVERAGE('Output (2)'!P47:Q47) -> 0.061102589 | R24: =+R18/AVERAGE('Output (2)'!Q47:R47) -> 0.067105415 | S24: =+S18/AVERAGE('Output (2)'!R47:S47) -> 0.073797178 | T24: =+T18/AVERAGE('Output (2)'!S47:T47) -> 0.081299021
B26: Investment analysis - WC
B28: DSO | F28: =365*'Output (2)'!F37/((1+Assumptions!$F$46)*'Output (2)'!F10) -> 63.295949 | M28: =365*'Output (2)'!M37/((1+Assumptions!$F$46)*'Output (2)'!M10) -> 53.049779 | N28: =365*'Output (2)'!N37/((1+Assumptions!$F$46)*'Output (2)'!N10) -> 59.593482 | O28: =365*'Output (2)'!O37/((1+Assumptions!$F$46)*'Output (2)'!O10) -> 51.513924 | P28: =365*'Output (2)'!P37/((1+Assumptions!$F$46)*'Output (2)'!P10) -> 54.719061 | Q28: =365*'Output (2)'!Q37/((1+Assumptions!$F$46)*'Output (2)'!Q10) -> 54.719061 | R28: =365*'Output (2)'!R37/((1+Assumptions!$F$46)*'Output (2)'!R10) -> 54.719061 | S28: =365*'Output (2)'!S37/((1+Assumptions!$F$46)*'Output (2)'!S10) -> 54.719061 | T28: =365*'Output (2)'!T37/((1+Assumptions!$F$46)*'Output (2)'!T10) -> 54.719061
B29: DPO | F29: =365*'Output (2)'!F38/((1+Assumptions!$F$46)*'Output (2)'!F13) -> -77.562804 | M29: =365*'Output (2)'!M38/((1+Assumptions!$F$46)*'Output (2)'!M13) -> -67.695453 | N29: =365*'Output (2)'!N38/((1+Assumptions!$F$46)*'Output (2)'!N13) -> -74.024014 | O29: =365*'Output (2)'!O38/((1+Assumptions!$F$46)*'Output (2)'!O13) -> -73.748362 | P29: =365*'Output (2)'!P38/((1+Assumptions!$F$46)*'Output (2)'!P13) -> 92.865892 | Q29: =365*'Output (2)'!Q38/((1+Assumptions!$F$46)*'Output (2)'!Q13) -> 92.865892 | R29: =365*'Output (2)'!R38/((1+Assumptions!$F$46)*'Output (2)'!R13) -> 92.865892 | S29: =365*'Output (2)'!S38/((1+Assumptions!$F$46)*'Output (2)'!S13) -> 92.865892 | T29: =365*'Output (2)'!T38/((1+Assumptions!$F$46)*'Output (2)'!T13) -> 92.865892
B30: Days inventory | F30: =365*'Output (2)'!F39/('Output (2)'!F10) -> 77.648078 | M30: =365*'Output (2)'!M39/('Output (2)'!M10) -> 82.191222 | N30: =365*'Output (2)'!N39/('Output (2)'!N10) -> 100.29306 | O30: =365*'Output (2)'!O39/('Output (2)'!O10) -> 105.93288 | P30: =365*'Output (2)'!P39/('Output (2)'!P10) -> 80.677565 | Q30: =365*'Output (2)'!Q39/('Output (2)'!Q10) -> 80.677565 | R30: =365*'Output (2)'!R39/('Output (2)'!R10) -> 80.677565 | S30: =365*'Output (2)'!S39/('Output (2)'!S10) -> 80.677565 | T30: =365*'Output (2)'!T39/('Output (2)'!T10) -> 80.677565
B32: Clients are paying | M32: =+IF(M28>F28,"Later",IF(M28<F28,"Sooner","Equally")) -> Sooner | N32: =+IF(N28>M28,"Later",IF(N28<M28,"Sooner","Equally")) -> Later | O32: =+IF(O28>N28,"Later",IF(O28<N28,"Sooner","Equally")) -> Sooner | P32: =+IF(P28>O28,"Later",IF(P28<O28,"Sooner","Equally")) -> Later | Q32: =+IF(Q28>P28,"Later",IF(Q28<P28,"Sooner","Equally")) -> Equally | R32: =+IF(R28>Q28,"Later",IF(R28<Q28,"Sooner","Equally")) -> Equally | S32: =+IF(S28>R28,"Later",IF(S28<R28,"Sooner","Equally")) -> Equally | T32: =+IF(T28>S28,"Later",IF(T28<S28,"Sooner","Equally")) -> Equally
B33: Diasorin is paying suppliers | M33: =+IF(M29>F29,"Later",IF(M29<F29,"Sooner","Equally")) -> Later | N33: =+IF(N29>M29,"Later",IF(N29<M29,"Sooner","Equally")) -> Sooner | O33: =+IF(O29>N29,"Later",IF(O29<N29,"Sooner","Equally")) -> Later | P33: =+IF(P29>O29,"Later",IF(P29<O29,"Sooner","Equally")) -> Later | Q33: =+IF(Q29>P29,"Later",IF(Q29<P29,"Sooner","Equally")) -> Equally | R33: =+IF(R29>Q29,"Later",IF(R29<Q29,"Sooner","Equally")) -> Equally | S33: =+IF(S29>R29,"Later",IF(S29<R29,"Sooner","Equally")) -> Equally | T33: =+IF(T29>S29,"Later",IF(T29<S29,"Sooner","Equally")) -> Equally
B34: Products stay on stock | M34: =+IF(M30>F30,"Longer",IF(M30<F30,"Less","Equally")) -> Longer | N34: =+IF(N30>M30,"Longer",IF(N30<M30,"Less","Equally")) -> Longer | O34: =+IF(O30>N30,"Longer",IF(O30<N30,"Less","Equally")) -> Longer | P34: =+IF(P30>O30,"Longer",IF(P30<O30,"Less","Equally")) -> Less | Q34: =+IF(Q30>P30,"Longer",IF(Q30<P30,"Less","Equally")) -> Equally | R34: =+IF(R30>Q30,"Longer",IF(R30<Q30,"Less","Equally")) -> Equally | S34: =+IF(S30>R30,"Longer",IF(S30<R30,"Less","Equally")) -> Equally | T34: =+IF(T30>S30,"Longer",IF(T30<S30,"Less","Equally")) -> Longer
B36: Financing analysis
B38: Leverage D/E | F38: =+'Output (2)'!F63/'Output (2)'!F69 -> -0.45653299 | M38: =+'Output (2)'!M63/'Output (2)'!M69 -> 0.61771147 | N38: =+'Output (2)'!N63/'Output (2)'!N69 -> 0.51318688 | O38: =+'Output (2)'!O63/'Output (2)'!O69 -> 0.34535264 | P38: =+'Output (2)'!P63/'Output (2)'!P69 -> 0.2149527 | Q38: =+'Output (2)'!Q63/'Output (2)'!Q69 -> 0.12196303 | R38: =+'Output (2)'!R63/'Output (2)'!R69 -> 0.022662863 | S38: =+'Output (2)'!S63/'Output (2)'!S69 -> -0.067347452 | T38: =+'Output (2)'!T63/'Output (2)'!T69 -> -0.14797576
B39: Leverage D/(D+E) | F39: =+'Output (2)'!F63/'Output (2)'!F71 -> -0.84003811 | M39: =+'Output (2)'!M63/'Output (2)'!M71 -> 0.38184279 | N39: =+'Output (2)'!N63/'Output (2)'!N71 -> 0.33914309 | O39: =+'Output (2)'!O63/'Output (2)'!O71 -> 0.25670046 | P39: =+'Output (2)'!P63/'Output (2)'!P71 -> 0.17692269 | Q39: =+'Output (2)'!Q63/'Output (2)'!Q71 -> 0.10870504 | R39: =+'Output (2)'!R63/'Output (2)'!R71 -> 0.022160639 | S39: =+'Output (2)'!S63/'Output (2)'!S71 -> -0.072210656 | T39: =+'Output (2)'!T63/'Output (2)'!T71 -> -0.17367553
B41: Debt coverage | F41: =+'Output (2)'!F63/'Output (2)'!F15 -> -1.2967718 | M41: =+'Output (2)'!M63/'Output (2)'!M15 -> 1.7496748 | N41: =+'Output (2)'!N63/'Output (2)'!N15 -> 1.9919868 | O41: =+'Output (2)'!O63/'Output (2)'!O15 -> 1.5013448 | P41: =+'Output (2)'!P63/'Output (2)'!P15 -> 1.0616675 | Q41: =+'Output (2)'!Q63/'Output (2)'!Q15 -> 0.61053423 | R41: =+'Output (2)'!R63/'Output (2)'!R15 -> 0.10705152 | S41: =+'Output (2)'!S63/'Output (2)'!S15 -> -0.32962736 | T41: =+'Output (2)'!T63/'Output (2)'!T15 -> -0.75245591
B42: Interest coverage | F42: =+'Output (2)'!F20/-('Output (2)'!F23+'Output (2)'!F24) -> 29.78858 | M42: =+'Output (2)'!M20/-('Output (2)'!M23+'Output (2)'!M24) -> 7.4133556 | N42: =+'Output (2)'!N20/-('Output (2)'!N23+'Output (2)'!N24) -> 8.1335763 | O42: =+'Output (2)'!O20/-('Output (2)'!O23+'Output (2)'!O24) -> 8.0895921 | P42: =+'Output (2)'!P20/-('Output (2)'!P23+'Output (2)'!P24) -> 4.6891379 | Q42: =+'Output (2)'!Q20/-('Output (2)'!Q23+'Output (2)'!Q24) -> 4.578721 | R42: =+'Output (2)'!R20/-('Output (2)'!R23+'Output (2)'!R24) -> 5.4369968 | S42: =+'Output (2)'!S20/-('Output (2)'!S23+'Output (2)'!S24) -> 5.6393135 | T42: =+'Output (2)'!T20/-('Output (2)'!T23+'Output (2)'!T24) -> 5.7435917
B44: DSCR | M44: =+'Output (2)'!M87/-('Output (2)'!M90+'Output (2)'!M91+'Output (2)'!M94) -> #DIV/0! | N44: =+'Output (2)'!N87/-('Output (2)'!N90+'Output (2)'!N91+'Output (2)'!N94) -> #DIV/0! | O44: =+'Output (2)'!O87/-('Output (2)'!O90+'Output (2)'!O91+'Output (2)'!O94) -> #DIV/0! | P44: =+'Output (2)'!P87/-('Output (2)'!P90+'Output (2)'!P91+'Output (2)'!P94) -> 3.3324624 | Q44: =+'Output (2)'!Q87/-('Output (2)'!Q90+'Output (2)'!Q91+'Output (2)'!Q94) -> 3.5129597 | R44: =+'Output (2)'!R87/-('Output (2)'!R90+'Output (2)'!R91+'Output (2)'!R94) -> 4.2133234 | S44: =+'Output (2)'!S87/-('Output (2)'!S90+'Output (2)'!S91+'Output (2)'!S94) -> 4.495233 | T44: =+'Output (2)'!T87/-('Output (2)'!T90+'Output (2)'!T91+'Output (2)'!T94) -> 4.681122
B46: Liquidity analysis
B48: Current ratio | F48: =+[1]AsReported!F54/[1]AsReported!F78 -> 2.5942657 | M48: =+[1]AsReported!G54/[1]AsReported!G78 -> 2.1335294 | N48: =+[1]AsReported!H54/[1]AsReported!H78 -> 2.0570039 | O48: =+[1]AsReported!I54/[1]AsReported!I78 -> 2.3097394
B49: Acid test | F49: =+([1]AsReported!F54-[1]AsReported!F47)/[1]AsReported!F78 -> 1.6813119 | M49: =+([1]AsReported!G54-[1]AsReported!G47)/[1]AsReported!G78 -> 1.1982353 | N49: =+([1]AsReported!H54-[1]AsReported!H47)/[1]AsReported!H78 -> 1.4725175 | O49: =+([1]AsReported!I54-[1]AsReported!I47)/[1]AsReported!I78 -> 1.3200887
B51: Profitability analysis
B53: ROCE | M53: =+('Output (2)'!M20*(1-M56)/AVERAGE('Output (2)'!F49:M49)) -> 0.30100221 | N53: =+('Output (2)'!N20*(1-N56)/AVERAGE('Output (2)'!M49:N49)) -> 0.097980705 | O53: =+('Output (2)'!O20*(1-O56)/AVERAGE('Output (2)'!N49:O49)) -> 0.092840848 | P53: =+('Output (2)'!P20*(1-P56)/AVERAGE('Output (2)'!O49:P49)) -> 0.085799374 | Q53: =+('Output (2)'!Q20*(1-Q56)/AVERAGE('Output (2)'!P49:Q49)) -> 0.083967813 | R53: =+('Output (2)'!R20*(1-R56)/AVERAGE('Output (2)'!Q49:R49)) -> 0.10083462 | S53: =+('Output (2)'!S20*(1-S56)/AVERAGE('Output (2)'!R49:S49)) -> 0.1050298 | T53: =+('Output (2)'!T20*(1-T56)/AVERAGE('Output (2)'!S49:T49)) -> 0.10853336
B55: ROCE decomposition
B56: Effective operating tax rate | M56: =-'Output (2)'!M28/'Output (2)'!M26 -> 0.23781025 | N56: =-'Output (2)'!N28/'Output (2)'!N26 -> 0.1731719 | O56: =-'Output (2)'!O28/'Output (2)'!O26 -> 0.22193508 | P56: =-'Output (2)'!P28/'Output (2)'!P26 -> 0.28957158 | Q56: =-'Output (2)'!Q28/'Output (2)'!Q26 -> 0.28989775 | R56: =-'Output (2)'!R28/'Output (2)'!R26 -> 0.28778973 | S56: =-'Output (2)'!S28/'Output (2)'!S26 -> 0.28740642 | T56: =-'Output (2)'!T28/'Output (2)'!T26 -> 0.28722162
B57: EBIT margin | M57: =+'Output (2)'!M21 -> 0.30650382 | N57: =+'Output (2)'!N21 -> 0.24489771 | O57: =+'Output (2)'!O21 -> 0.24023917 | P57: =+'Output (2)'!P21 -> 0.24337376 | Q57: =+'Output (2)'!Q21 -> 0.22439356 | R57: =+'Output (2)'!R21 -> 0.25490003 | S57: =+'Output (2)'!S21 -> 0.25116764 | T57: =+'Output (2)'!T21 -> 0.24487119
B58: Asset turnover | M58: =+'Output (2)'!M10/AVERAGE('Output (2)'!F49:M49) -> 1.2884592 | N58: =+'Output (2)'!N10/AVERAGE('Output (2)'!M49:N49) -> 0.48388327 | O58: =+'Output (2)'!O10/AVERAGE('Output (2)'!N49:O49) -> 0.49668316 | P58: =+'Output (2)'!P10/AVERAGE('Output (2)'!O49:P49) -> 0.49623802 | Q58: =+'Output (2)'!Q10/AVERAGE('Output (2)'!P49:Q49) -> 0.52696475 | R58: =+'Output (2)'!R10/AVERAGE('Output (2)'!Q49:R49) -> 0.55543283 | S58: =+'Output (2)'!S10/AVERAGE('Output (2)'!R49:S49) -> 0.58682277 | T58: =+'Output (2)'!T10/AVERAGE('Output (2)'!S49:T49) -> 0.6218291
B59: ROCE | M59: =+M58*(1-M56)*M57 -> 0.30100221 | N59: =+N58*(1-N56)*N57 -> 0.097980705 | O59: =+O58*(1-O56)*O57 -> 0.092840848 | P59: =+P58*(1-P56)*P57 -> 0.085799374 | Q59: =+Q58*(1-Q56)*Q57 -> 0.083967813 | R59: =+R58*(1-R56)*R57 -> 0.10083462 | S59: =+S58*(1-S56)*S57 -> 0.1050298 | T59: =AVERAGE(M59:O59) -> 0.16394125
B60: Check | M60: =+M59-M53 -> 0 | N60: =+N59-N53 -> 0 | O60: =+O59-O53 -> 0 | P60: =+P59-P53 -> 0 | Q60: =+Q59-Q53 -> 0 | R60: =+R59-R53 -> 0 | S60: =+S59-S53 -> 0
B62: ROE | M62: =+'Output (2)'!M29/AVERAGE('Output (2)'!F69:M69) -> 0.29780034 | N62: =+'Output (2)'!N29/AVERAGE('Output (2)'!M69:N69) -> 0.13337659 | O62: =+'Output (2)'!O29/AVERAGE('Output (2)'!N69:O69) -> 0.11638692 | P62: =+'Output (2)'!P29/AVERAGE('Output (2)'!O69:P69) -> 0.086817661 | Q62: =+'Output (2)'!Q29/AVERAGE('Output (2)'!P69:Q69) -> 0.076947174 | R62: =+'Output (2)'!R29/AVERAGE('Output (2)'!Q69:R69) -> 0.088497003 | S62: =+'Output (2)'!S29/AVERAGE('Output (2)'!R69:S69) -> 0.084732535 | T62: =+'Output (2)'!T29/AVERAGE('Output (2)'!S69:T69) -> 0.080245264
B63: Effective interest rate (with average ND) | M63: =-('Output (2)'!M23+'Output (2)'!M24)/(AVERAGE('Output (2)'!F63:M63)) -> 0.51193392 | N63: =-('Output (2)'!N23+'Output (2)'!N24)/(AVERAGE('Output (2)'!M63:N63)) -> 0.040013148 | O63: =-('Output (2)'!O23+'Output (2)'!O24)/(AVERAGE('Output (2)'!N63:O63)) -> 0.049914857 | P63: =-('Output (2)'!P23+'Output (2)'!P24)/(AVERAGE('Output (2)'!O63:P63)) -> 0.11944086 | Q63: =-('Output (2)'!Q23+'Output (2)'!Q24)/(AVERAGE('Output (2)'!P63:Q63)) -> 0.18166144 | R63: =-('Output (2)'!R23+'Output (2)'!R24)/(AVERAGE('Output (2)'!Q63:R63)) -> 0.39933504 | S63: =-('Output (2)'!S23+'Output (2)'!S24)/(AVERAGE('Output (2)'!R63:S63)) -> -1.0574338 | T63: =-('Output (2)'!T23+'Output (2)'!T24)/(AVERAGE('Output (2)'!S63:T63)) -> -0.2171984
B65: Non-cash equity metrics (supporting FCFE valuation)
B67: Interest income, after tax | M67: =+'Output (2)'!M90*(1-Assumptions!G47) -> 0 | N67: =+'Output (2)'!N90*(1-Assumptions!H47) -> 0 | O67: =+'Output (2)'!O90*(1-Assumptions!I47) -> 0 | P67: =+'Output (2)'!P90*(1-Assumptions!P47) -> -0.180956 | Q67: =+'Output (2)'!Q90*(1-Assumptions!Q47) -> -0.0894596 | R67: =+'Output (2)'!R90*(1-Assumptions!R47) -> -0.22023356 | S67: =+'Output (2)'!S90*(1-Assumptions!S47) -> -0.020108916 | T67: =+'Output (2)'!T90*(1-Assumptions!T47) -> -0.17282781
B68: FCFE excluding interest income (after tax) | M68: =+'Output (2)'!M96-M67 -> 0 | N68: =+'Output (2)'!N96-N67 -> 0 | O68: =+'Output (2)'!O96-O67 -> 0 | P68: =+'Output (2)'!P96-P67 -> 185.80314 | Q68: =+'Output (2)'!Q96-Q67 -> 165.96536 | R68: =+'Output (2)'!R96-R67 -> 208.88384 | S68: =+'Output (2)'!S96-S67 -> 224.80572 | T68: =+'Output (2)'!T96-T67 -> 237.02641
B69: Net income excluding interest income (after tax) | F69: =+'Output (2)'!F29-'Output (2)'!F90*(1-Assumptions!F47) -> 117.91 | M69: =+'Output (2)'!M29-'Output (2)'!M90*(1-Assumptions!G47) -> 275.088 | N69: =+'Output (2)'!N29-'Output (2)'!N90*(1-Assumptions!H47) -> 203.914 | O69: =+'Output (2)'!O29-'Output (2)'!O90*(1-Assumptions!I47) -> 194.191 | P69: =+'Output (2)'!P29-'Output (2)'!P90*(1-Assumptions!P47) -> 163.41368 | Q69: =+'Output (2)'!Q29-'Output (2)'!Q90*(1-Assumptions!Q47) -> 157.01205 | R69: =+'Output (2)'!R29-'Output (2)'!R90*(1-Assumptions!R47) -> 196.22562 | S69: =+'Output (2)'!S29-'Output (2)'!S90*(1-Assumptions!S47) -> 204.56198 | T69: =+'Output (2)'!T29-'Output (2)'!T90*(1-Assumptions!T47) -> 210.43173
B70: Equity, excluding cash | F70: =+'Output (2)'!F69+'Output (2)'!F62 -> 316.801 | M70: =+'Output (2)'!M69+'Output (2)'!M62 -> 1106.532 | N70: =+'Output (2)'!N69+'Output (2)'!N62 -> 1134.579 | O70: =+'Output (2)'!O69+'Output (2)'!O62 -> 1405.754 | P70: =+'Output (2)'!P69+'Output (2)'!P62 -> 1383.3645 | Q70: =+'Output (2)'!Q69+'Output (2)'!Q62 -> 1374.4112 | R70: =+'Output (2)'!R69+'Output (2)'!R62 -> 1361.753 | S70: =+'Output (2)'!S69+'Output (2)'!S62 -> 1341.5093 | T70: =+'Output (2)'!T69+'Output (2)'!T62 -> 1314.9146
B71: Noncash ROE | M71: =+Analysis!M69/AVERAGE(Analysis!F70:M70) -> 0.38654061 | N71: =+Analysis!N69/AVERAGE(Analysis!M70:N70) -> 0.18197581 | O71: =+Analysis!O69/AVERAGE(Analysis!N70:O70) -> 0.15288626 | P71: =+Analysis!P69/AVERAGE(Analysis!O70:P70) -> 0.11717944 | Q71: =+Analysis!Q69/AVERAGE(Analysis!P70:Q70) -> 0.11386862 | R71: =+Analysis!R69/AVERAGE(Analysis!Q70:R70) -> 0.14343117 | S71: =+Analysis!S69/AVERAGE(Analysis!R70:S70) -> 0.15134453 | T71: =+Analysis!T69/AVERAGE(Analysis!S70:T70) -> 0.15843235

Sheet Valuation >>>
C12: Diasorin
C13: Financial Model
C17: Valuation

Sheet TV
B2: Terminal Cash Flows
D4: Fundamental growth | F4: Bankers' normalized best practice | I4: Simple FCFO
B5: Terminal FCFO | C5: 2021 | E5: TV 2022 | G5: TV 2022 | I5: TV 2022
B7: Sales | C7: ='Output (2)'!$T$10 -> 1458.6075 | G7: =+C7*(1+$E$19) -> 1487.7797
B8: EBITDA | C8: =+'Output (2)'!T15 -> 535.83948 | G8: =+G7*E20 -> 546.55627
B9: D&A | C9: =+'Output (2)'!T18+'Output (2)'!T19 -> -178.66852 | G9: =G15 -> -138.60959
B10: EBIT | C10: =+C8+C9 -> 357.17095 | G10: =SUM(G8:G9) -> 407.94667
B11: (Operational taxes) | C11: =+-C10*SUM(Assumptions!$F$47:$F$48) -> -99.650696 | G11: =+-G10*SUM(Assumptions!$F$47:$F$48) -> -113.81712
B12: NOPAT | C12: =+C10+C11 -> 257.52026 | E12: =+'Output (2)'!T79*(1+$E$19) -> 262.67066 | G12: =+SUM(G10:G11) -> 294.12955
B13: D&A | C13: =-C9 -> 178.66852 | G13: =-G9 -> 138.60959
B14: Change in noncash WC | C14: =+'Output (2)'!T84 -> -18.079675 | G14: 0
B15: CAPEX | C15: =+'Output (2)'!T85+'Output (2)'!T86 -> -135.89176 | G15: =-E21*G7 -> -138.60959
B16: FCFO | C16: =+SUM(C12:C15) -> 282.21735 | E16: =+E12*(1-E23) -> 230.62618 | G16: =+SUM(G12:G15) -> 294.12955 | I16: =+C16*(1+E19) -> 287.86169
C17: =+C16-'Output (2)'!T87 -> 0
B18: Assumptions
B19: Terminal growth rate | E19: =+Assumptions!T52 -> 0.02
B20: EBITDA margin | E20: =+C8/C7 -> 0.36736372
B21: CAPEX / Sales | E21: =-(C15)/C7 -> 0.093165406
E22: =+Analysis!T59 -> 0.16394125
B23: Implied terminal capital reinvestment rate | E23: =+E19/E22 -> 0.12199492
D25: Fundamental growth | G25: Simple FCFE
B26: Terminal FCFE | C26: 2021 | E26: TV 2022 | G26: TV 2022
B28: Noncash net income | C28: =+Analysis!T69 -> 210.43173 | E28: =+C28*(1+E38) -> 214.64036
B29: + D&A | C29: =+C13 -> 178.66852
B30: Change in WC | C30: =+C14 -> -18.079675
B31: CAPEX | C31: =+C15 -> -135.89176
B32: Change in gross debt | C32: =+'Output (2)'!T94 -> 1.897595
B33: Change in surplus assets | C33: =+'Output (2)'!T95 -> 0
B34: FCFE | C34: =SUM(C28:C33) -> 237.02641 | E34: =+E28*(1-E40) -> 187.54484 | G34: =+C34*(1+E38) -> 241.76694
C35: =+C34-Analysis!T68 -> 0
B37: Assumptions
B38: Terminal growth rate | E38: =+E19 -> 0.02
B39: 2021 noncash ROE = Terminal noncash ROE | E39: =Analysis!$T$71 -> 0.15843235
B40: Implied terminal equity reinvestment rate | E40: =+E38/E39 -> 0.12623685
B42: Terminal tax shield | C42: 2021 | E42: TV 2022
B44: Tax shields | C44: =+'Output (2)'!T89 -> 14.924638 | E44: =+E45+E46 -> 4.7926831
B45: Tax shield on interest expense | E45: =+E48*E53*E55 -> 9.8569258
B46: Tax effect of interest income | E46: =-E49*E55*IF(E49<0,E53,E54) -> -5.0642427
B48: Gross debt | C48: ='Output (2)'!T61 -> 1006.6305 | E48: =+C48*(1+$E$52) -> 1026.7631
B49: Cash (overdraft) | C49: =-'Output (2)'!T62 -> 1409.8261 | E49: =+C49*(1+$E$52) -> 1438.0226
B51: Assumptions
B52: Terminal growth rate | E52: =+E38 -> 0.02
B53: Cost of debt | E53: 0.04
B54: Interest income rate | E54: =+Assumptions!T42 -> 0.01467363
B55: Income tax rate (with interest deductibility) | E55: =+Assumptions!T47 -> 0.24

Sheet DCF
B2: DCF / APV Valuation
F3: Historicals | J3: Explicit forecast | O3: TV
B5: =[1]AsReported!B5 -> (EUR m) | I5: 45489 | J5: =I5+365 -> 45854 | K5: =J5+365 -> 46219 | L5: =K5+365 -> 46584 | M5: =L5+365 -> 46949 | N5: =M5+365 -> 47314 | O5: =+EOMONTH(N5,12) -> 47695 | Q5: Notes
B8: Assumptions
B10: Perpetual growth | F10: 0.0254
B11: WACC | F11: 0.063558
B12: kEU | F12: 0.065
B13: kEL | F13: 0.076
B14: kD | F14: 0.0252
B15: Tax shields - Theoretical tax rate | F15: =0.24 -> 0.24
B16: Valuation date (= last fiscal year closing date) | F16: 46051
B18: Year | I18: =+YEAR(I$5)-YEAR($I$5) -> 0 | J18: =+YEAR(J$5)-YEAR($I$5) -> 1 | K18: =+YEAR(K$5)-YEAR($I$5) -> 2 | L18: =+YEAR(L$5)-YEAR($I$5) -> 3 | M18: =+YEAR(M$5)-YEAR($I$5) -> 4 | N18: =+YEAR(N$5)-YEAR($I$5) -> 5
F19: 0.24
B20: DCF asset side (FCFO) | J20: 45855 | K20: =J20+365 -> 46220 | L20: =K20+365 -> 46585 | M20: =L20+365 -> 46950 | N20: =M20+365 -> 47315 | O20: =N20+365 -> 47680
B22: FCFO | J22: =+'Output (2)'!P87 -> 257.53817 | K22: =+'Output (2)'!Q87 -> 211.16666 | L22: =+'Output (2)'!R87 -> 254.08186 | M22: =+'Output (2)'!S87 -> 270.00028 | N22: =+'Output (2)'!T87 -> 282.21735 | O22: =+TV!E16 -> 230.62618
B23: Discount factor (WACC) | J23: =1/((1+$F$11)^(J18-0.5)) -> 0.96965984 | K23: =1/((1+$F$11)^(K18-0.5)) -> 0.91171318 | L23: =1/((1+$F$11)^(L18-0.5)) -> 0.85722939 | M23: =1/((1+$F$11)^(M18-0.5)) -> 0.80600155 | N23: =1/((1+$F$11)^(N18-0.5)) -> 0.75783506
B24: Present value of FCFO | J24: =+J23*J22 -> 249.72442 | K24: =+K23*K22 -> 192.52343 | L24: =+L23*L22 -> 217.80644 | M24: =+M23*M22 -> 217.62064 | N24: =+N23*N22 -> 213.8742
B25: Terminal value | N25: =+O22/(F11-F10) -> 6043.9797
B26: PV of FCFO | I26: =+SUM(J24:N24) -> 1091.5491
B27: PV of TV | I27: =+N25*N23 -> 4580.3397
B29: Enterprise value | I29: =+I27+I26 -> 5671.8888 | J29: =J33-SUM(I30:I32) -> 6096.893 | K29: =K33-SUM(I30:I32) -> 9132.693
B30: (Net debt) | I30: =-'Output (2)'!$O$63 -> -621.297
B31: Surplus assets, associates and (pensions) | I31: =+'Output (2)'!$O$54 -> -3.292 | N31: =J101/I34 -> 118.56021
B32: (Minorities) | I32: =-'Output (2)'!$O$68 -> 1.896
B33: Equity value | I33: =SUM(I29:I32) -> 5049.1958 | J33: =5474.2 -> 5474.2 | K33: 8510 | L33: =H103/I34 -> 71.494861
B34: Number of shares (NOSH) (m) | I34: 54.15
B35: Equity value per share (€) | I35: =+I33/I34 -> 93.244614
B36: Implied EV / EBITDA 2016A multiple | I36: =+I29/'Output (2)'!$O$15 -> 13.705942
B38: Adjusted present value | I38: =+I$5 -> 45489 | J38: =+J$5 -> 45854 | K38: =+K$5 -> 46219 | L38: =+L$5 -> 46584 | M38: =+M$5 -> 46949 | N38: =+N$5 -> 47314 | O38: =+O$5 -> 47695
B40: FCFO | J40: =+J22 -> 257.53817 | K40: =+K22 -> 211.16666 | L40: =+L22 -> 254.08186 | M40: =+M22 -> 270.00028 | N40: =+N22 -> 282.21735 | O40: =+O22 -> 230.62618
B41: Discount factor (kEU) | J41: =1/((1+$F$12)^J18) -> 0.93896714 | K41: =1/((1+$F$12)^K18) -> 0.88165928 | L41: =1/((1+$F$12)^L18) -> 0.82784909 | M41: =1/((1+$F$12)^M18) -> 0.77732309 | N41: =1/((1+$F$12)^N18) -> 0.72988084
B42: Present value of FCFO | J42: =+J41*J40 -> 241.81988 | K42: =+K41*K40 -> 186.17705 | L42: =+L41*L40 -> 210.34143 | M42: =+M41*M40 -> 209.87745 | N42: =+N41*N40 -> 205.98503
B43: Terminal value | N43: =+O40/(F12-F10) -> 5823.8933
B44: PV of FCFO | I44: =+SUM(J42:N42) -> 1054.2008
B45: PV of TV | I45: =+N43*N41 -> 4250.7481
B46: Unlevered value | I46: =+I45+I44 -> 5304.949
B48: Accounting yealry tax shields | J48: =+'Output (2)'!P89 -> 14.947661 | K48: =+'Output (2)'!Q89 -> 14.819993 | L48: =+'Output (2)'!R89 -> 14.886133 | M48: =+'Output (2)'!S89 -> 14.849021 | N48: =+'Output (2)'!T89 -> 14.924638 | O48: =+TV!E44 -> 4.7926831
B50: Discount factor (kD) | J50: =1/((1+$F$14)^J18) -> 0.97541943 | K50: =1/((1+$F$14)^K18) -> 0.95144307 | L50: =1/((1+$F$14)^L18) -> 0.92805605 | M50: =1/((1+$F$14)^M18) -> 0.90524391 | N50: =1/((1+$F$14)^N18) -> 0.8829925
B51: Present value of TS | J51: =+J50*J48 -> 14.580239 | K51: =+K50*K48 -> 14.100379 | L51: =+L50*L48 -> 13.815166 | M51: =+M50*M48 -> 13.441986 | N51: =+N50*N48 -> 13.178344
B52: Terminal value | N52: =+O48/(F14-F10) -> -23963.415
B53: PV of TS | I53: =+SUM(J51:N51) -> 69.116114
B54: PV of TV | I54: =+N52*N50 -> -21159.516
B55: Value of tax shields | I55: =+I54+I53 -> -21090.4
B57: Enterprise value | I57: =+I55+I46 -> -15785.451
B58: (Net debt) | I58: =-'Output (2)'!$O$63 -> -621.297
B59: Surplus assets, associates and (pensions) | I59: =+'Output (2)'!$O$54 -> -3.292
B60: (Minorities) | I60: =-'Output (2)'!$O$68 -> 1.896
B61: Equity value | I61: =SUM(I57:I60) -> -16408.144
B62: Number of shares (NOSH) (m) | I62: 55.948257
B63: Equity value per share (€) | I63: =+I61/I62 -> -293.27355
B64: Implied EV / EBITDA 2016A multiple | I64: =+I57/'Output (2)'!$O$15 -> -38.145048
B66: DCF equity side (FCFE) | F66: =+F$5 -> 0 | G66: =+G$5 -> 0 | H66: =+H$5 -> 0 | I66: =+I$5 -> 45489 | J66: =+J$5 -> 45854 | K66: =+K$5 -> 46219 | L66: =+L$5 -> 46584 | M66: =+M$5 -> 46949 | ... O66: =+O$5 -> 47695
B68: Noncash FCFE | J68: =+Analysis!P68 -> 185.80314 | K68: =+Analysis!Q68 -> 165.96536 | L68: =+Analysis!R68 -> 208.88384 | M68: =+Analysis!S68 -> 224.80572 | N68: =+Analysis!T68 -> 237.02641 | O68: =+TV!E34 -> 187.54484
B69: Discount factor (kEL) | J69: =1/((1+$F$13)^J18) -> 0.92936803 | K69: =1/((1+$F$13)^K18) -> 0.86372493 | L69: =1/((1+$F$13)^L18) -> 0.80271834 | M69: =1/((1+$F$13)^M18) -> 0.74602076 | N69: =1/((1+$F$13)^N18) -> 0.69332785
B70: Present value of FCFE | J70: =+J69*J68 -> 172.6795 | K70: =+K69*K68 -> 143.34842 | L70: =+L69*L68 -> 167.67489 | M70: =+M69*M68 -> 167.70974 | N70: =+N69*N68 -> 164.33701
B71: Terminal value | N71: =+O68/(F13-F10) -> 3706.4198
B72: PV of FCFE | I72: =+SUM(J70:N70) -> 815.74956
B73: PV of TV | I73: =+N71*N69 -> 2569.7641
B75: Equity value from continuing operations | I75: =+I73+I72 -> 3385.5136
B76: Cash | I76: =-'Output (2)'!O62 -> 393.268
B77: Surplus assets | I77: =+'Output (2)'!$O$52 -> -9.582
B78: (Minorities) | I78: =+I32 -> 1.896
B79: Equity value | I79: =+SUM(I75:I78) -> 3771.0956
B80: Number of shares (NOSH) (m) | I80: =[1]AsReported!$I$124 -> 1180
B81: Equity value per share (€) | I81: =+I79/I80 -> 3.1958437
B83: Gross debt | I83: =+'Output (2)'!O61 -> 1014.565
B84: Enterprise value | I84: =+I75+I83 -> 4400.0786
B85: Implied EV / EBITDA 2016A multiple | I85: =+I84/'Output (2)'!$O$15 -> 10.632652
B87: Sensitivity analysis
B89: Lower bound | F89: =+MIN(H101:J103) -> 3871.4467 | G89: =+MIN(H131:J133) -> #REF! | H89: =+MIN(H121:J123) -> #REF!
B90: Upper bound | F90: =+MAX(H101:J103) -> 6420.0352 | G90: =+MAX(H131:J133) -> #REF! | H90: =+MAX(H121:J123) -> #REF!
B91: Average | F91: =+AVERAGE(H101:J103) -> 4933.3438 | G91: =+AVERAGE(H131:J133) -> #REF! | H91: =+AVERAGE(H121:J123) -> #REF!
B93: In order for the following sensitivity tables to function properly, the grey-colored cells need to be hardcoded (raw numbers) and equal to the
B94: corresponding input to subject to sensitivity
B96: DCF asset side: equity value sensitivity: WACC and perpetual growth
G98: Perpetual growth | L98: Checks
F99: =I33 -> 5049.1958 | G99: =+H99-0.5% -> 0.014 | H99: =+I99-0.5% -> 0.019 | I99: 0.024 | J99: =+I99+0.5% -> 0.029 | K99: =+J99+0.5% -> 0.034 | L99: =+F10-I99 -> 0.0014
E100: WACC | F100: =+F101-0.5% -> 0.054 | G100: 5044.0056 | H100: 5694.0871 | I100: 6560.8625 | J100: 7774.348 | K100: 9594.5762 | L100: =+F11-F102 -> -0.000442
F101: =+F102-0.5% -> 0.059 | G101: 4440.1762 | H101: 4935.1409 | I101: 5571.5242 | J101: 6420.0352 | K101: 7607.9506 | L101: =+I102-I33 -> -220.20044
F102: 0.064 | G102: 3956.7448 | H102: 4344.4117 | I102: 4828.9954 | J102: 5452.0315 | K102: 6282.7464
F103: =+F102+0.5% -> 0.069 | G103: 3560.8862 | H103: 3871.4467 | I103: 4251.0207 | J103: 4725.4882 | K103: 5335.5177
F104: =+F103+0.5% -> 0.074 | G104: 3230.7165 | H104: 3484.1392 | I104: 3788.2463 | J104: 4159.9328 | K104: 4624.541
B106: DCF asset side: implied multiple sensitivity: WACC and perpetual growth
G108: Perpetual growth | L108: Checks
F109: =+I36 -> 13.705942 | G109: =+H109-0.5% -> 0.01 | H109: =+I109-0.5% -> 0.015 | I109: =+Assumptions!$T$52 -> 0.02 | J109: =+I109+0.5% -> 0.025 | K109: =+J109+0.5% -> 0.03 | L109: =+$F$10-I109 -> 0.0054
E110: WACC | F110: =+F111-0.5% -> #REF! | G110: #REF! | H110: #REF! | I110: #REF! | J110: #REF! | K110: #REF! | L110: =+F112-F11 -> #REF!
F111: =+F112-0.5% -> #REF! | G111: #REF! | H111: #REF! | I111: #REF! | J111: #REF! | K111: #REF! | L111: =+I112-I36 -> #REF!
F112: =#REF! -> #REF! | G112: #REF! | H112: #REF! | I112: #REF! | J112: #REF! | K112: #REF!
F113: =+F112+0.5% -> #REF! | G113: #REF! | H113: #REF! | I113: #REF! | J113: #REF! | K113: #REF!
F114: =+F113+0.5% -> #REF! | G114: #REF! | H114: #REF! | I114: #REF! | J114: #REF! | K114: #REF!
B116: DCF equity side: equity value sensitivity: kEL and perpetual growth
G118: Perpetual growth | L118: Checks
F119: =+I79 -> 3771.0956 | G119: =+H119-0.5% -> 0.01 | H119: =+I119-0.5% -> 0.015 | I119: =+Assumptions!$T$52 -> 0.02 | J119: =+I119+0.5% -> 0.025 | K119: =+J119+0.5% -> 0.03 | L119: =+$F$10-I119 -> 0.0054
E120: kEL | F120: =+F121-0.5% -> #REF! | G120: #REF! | H120: #REF! | I120: #REF! | J120: #REF! | K120: #REF! | L120: =+F13-F122 -> #REF!
F121: =+F122-0.5% -> #REF! | G121: #REF! | H121: #REF! | I121: #REF! | J121: #REF! | K121: #REF! | L121: =+I122-I79 -> #REF!
F122: =+#REF! -> #REF! | G122: #REF! | H122: #REF! | I122: #REF! | J122: #REF! | K122: #REF!
F123: =+F122+0.5% -> #REF! | G123: #REF! | H123: #REF! | I123: #REF! | J123: #REF! | K123: #REF!
F124: =+F123+0.5% -> #REF! | G124: #REF! | H124: #REF! | I124: #REF! | J124: #REF! | K124: #REF!
B126: APV: equity value sensitivity: kEU and kD
G128: Cost of debt | L128: Checks
...
